Workbook

Sheet README
A1: VendorFlow — Supplier Invoice, Payment & Performance System
A2: An Excel control system for recording supplier deliveries and invoices, tracking full and partial payments, and monitoring vendor performance.
B4: PURPOSE
B5: VendorFlow replaces scattered spreadsheets and paper files with one controlled workbook.
B6: Employees record vendors, deliveries, invoices and payments. The workbook calculates balances,
B7: due dates, overdue amounts, aging and supplier performance automatically, checks the data for
B8: errors, prioritises upcoming payments, and reports everything on a management dashboard.
B10: SHEET MAP
B11: Sheet | C11: Who uses it | D11: What it does
B12: Dashboard | C12: Read only | D12: Management view: KPIs, aging, top vendors, monthly trend, charts.
B13: Vendor Master | C13: Enter vendors | D13: One row per supplier. Payment terms and contacts live here.
B14: Invoice & Delivery Log | C14: Enter invoices | D14: One row per supplier invoice / delivery. The core table.
B15: Payments Log | C15: Enter payments | D15: One row per payment. Several rows may point at one invoice.
B16: Payment Planner | C16: Plan payments | D16: Open invoices ranked by urgency, plus cash-requirement summary.
B17: Data Quality & Reconciliation | C17: Read + act | D17: Control totals that must tie, and a list of data exceptions.
B18: Settings | C18: Admin only | D18: Reporting date, aging bands, scoring weights and dropdown lists.
B20: COLOUR LEGEND
B21: Input cell | C21: Type here. Blue text on a light yellow background.
B22: Calculated cell | C22: Do not type here — a formula fills it in.
B23: Linked value | C23: Green text: pulled automatically from another sheet.
B24: Completed / OK | C24: Invoice fully paid, or a check that passed.
B25: Warning | C25: Partly paid, due soon, or something to review.
B26: Overdue / Error | C26: Past the due date, or a data error to fix.
B27: Closed / inactive | C27: No action needed.
B29: DAILY WORKFLOW
B30: 1. New supplier? Add a row on Vendor Master and give it the next free Vendor ID.
B31: 2. Goods arrive? Add a row on Invoice & Delivery Log: Invoice ID, Vendor ID, dates, amount.
B32: 3. Money leaves? Add a row on Payments Log and pick the Invoice ID it settles.
B33: 4. Every morning: open Data Quality & Reconciliation. Every control must read PASS.
B34: 5. Weekly: open Payment Planner, work down the ranked list, enter planned dates and amounts.
B35: 6. Managers: read the Dashboard. It refreshes itself from the three logs.
B37: RULES THAT KEEP THE FILE RELIABLE
B38: • Never delete or overwrite a calculated column — copy the formula down instead.
B39: • Invoice ID and Payment ID must be unique. Payments must quote an Invoice ID that exists.
B40: • Record part payments as separate rows. Never edit the invoice amount to show a part payment.
B41: • Settings!C5 (Reporting Date) drives every overdue and aging calculation. Update it, or replace
... B58: Built with formulas only — no macros, no VBA, no Power Query. Opens in Microsoft Excel, LibreOffice Calc and Google Sheets.

Sheet Dashboard
A1: VendorFlow — Management Dashboard
A2: =" Reporting date: "&TEXT(Settings!$C$5,"yyyy-mm-dd")&" | Currency: "&Settings!$C$6&" | Invoices recorded: "&COUNTA('Invoice & Delivery Log'!$A$8:$A$157)&" | Payments recorded: "&COUNTA('Payments Log'!$A$8:$A$207) -> Reporting date: 2026-09-07 | Currency: USD | Invoices recorded: 60 | Payments recorded: 63
A4: Key Performance Indicators
A5: TOTAL INVOICED | C5: TOTAL PAID | F5: TOTAL OUTSTANDING | H5: TOTAL OVERDUE
A6: =SUM('Invoice & Delivery Log'!$N$8:$N$157) -> 202408.71 | C6: =SUM('Invoice & Delivery Log'!$O$8:$O$157) -> 149164.99 | F6: =SUM('Invoice & Delivery Log'!$P$8:$P$157) -> 53243.72 | H6: =SUM('Invoice & Delivery Log'!$S$8:$S$157) -> 32710.06
A7: ="Across "&COUNTA('Invoice & Delivery Log'!$A$8:$A$157)&" supplier invoices" -> Across 60 supplier invoices | C7: ="Settled through "&COUNTA('Payments Log'!$A$8:$A$207)&" payments" -> Settled through 63 payments | F7: =IFERROR(TEXT(SUM('Invoice & Delivery Log'!$P$8:$P$157)/SUM('Invoice & Delivery Log'!$N$8:$N$157),"0.0%")&" of invoiced value","") -> 26.3% of invoiced value | H7: =IFERROR(TEXT(SUM('Invoice & Delivery Log'!$S$8:$S$157)/SUM('Invoice & Delivery Log'!$P$8:$P$157),"0.0%")&" of the open balance","") -> 61.4% of the open balance
A9: OPEN INVOICES | C9: OVERDUE INVOICES | F9: ON-TIME PAYMENT RATE | H9: AVG DAYS TO PAY
A10: =COUNTIF('Invoice & Delivery Log'!$Y$8:$Y$157,"Yes") -> 18 | C10: =COUNTIFS('Invoice & Delivery Log'!$R$8:$R$157,">0") -> 12 | F10: =IFERROR(COUNTIF('Payments Log'!$N$8:$N$207,"On Time")/(COUNTIF('Payments Log'!$N$8:$N$207,"On Time")+COUNTIF('Payments Log'!$N$8:$N$207,"Late")),"") -> 0.83870968 | H10: =IFERROR(ROUND(AVERAGEIFS('Payments Log'!$L$8:$L$207,'Payments Log'!$L$8:$L$207,">=0"),0),"") -> 19
A11: ="of "&COUNTA('Invoice & Delivery Log'!$A$8:$A$157)&" invoices recorded" -> of 60 invoices recorded | C11: =IFERROR(TEXT(COUNTIFS('Invoice & Delivery Log'!$R$8:$R$157,">0")/COUNTIF('Invoice & Delivery Log'!$Y$8:$Y$157,"Yes"),"0.0%")&" of open invoices","") -> 66.7% of open invoices | F11: ="Payments made on or before the due date" -> Payments made on or before the due date | H11: ="Days from invoice date to payment" -> Days from invoice date to payment
A13: =IF(COUNTIF('Data Quality & Reconciliation'!$F$8:$F$17,"FAIL")>0,"RECONCILIATION CONTROL FAILED — open Data Quality & Reconciliation",IF(COUNTIF('Invoice & Delivery Log'!$W$8:$W$157,"REVIEW")+COUNTIF('Payments Log'!$Q$8:$Q$207,"REVIEW")=0,"All reconciliation controls passed and no data exceptions were found","All reconciliation controls passed — "&(COUNTIF('Invoice & Delivery Log'!$W$8:$W$157,"REVIEW")+COUNTIF('Payments Log'!$Q$8:$Q$207,"REVIEW"))&" data exceptions to review")) -> All reconciliation controls passed — 8 data exceptions to review
A15: Accounts Payable Aging | F15: Payment Status Summary
A16: Aging Bucket | B16: Invoices | C16: Amount | D16: % of Total | F16: Payment Status | G16: Invoices | H16: Invoice Value | I16: % of Value
A17: Not Due Yet | B17: =COUNTIFS('Invoice & Delivery Log'!$T$8:$T$157,$A17) -> 6 | C17: =SUMIFS('Invoice & Delivery Log'!$P$8:$P$157,'Invoice & Delivery Log'!$T$8:$T$157,$A17) -> 21046.05 | D17: =IFERROR($C17/$C$24,"") -> 0.3952776 | F17: Unpaid | G17: =COUNTIFS('Invoice & Delivery Log'!$Q$8:$Q$157,$F17) -> 12 | H17: =SUMIFS('Invoice & Delivery Log'!$N$8:$N$157,'Invoice & Delivery Log'!$Q$8:$Q$157,$F17) -> 47350.33 | I17: =IFERROR($H17/$H$24,"") -> 0.23393425
A18: 1-30 Days Overdue | B18: =COUNTIFS('Invoice & Delivery Log'!$T$8:$T$157,$A18) -> 2 | C18: =SUMIFS('Invoice & Delivery Log'!$P$8:$P$157,'Invoice & Delivery Log'!$T$8:$T$157,$A18) -> 3865.78 | D18: =IFERROR($C18/$C$24,"") -> 0.07260537 | F18: Partially Paid | G18: =COUNTIFS('Invoice & Delivery Log'!$Q$8:$Q$157,$F18) -> 6 | H18: =SUMIFS('Invoice & Delivery Log'!$N$8:$N$157,'Invoice & Delivery Log'!$Q$8:$Q$157,$F18) -> 12700.07 | I18: =IFERROR($H18/$H$24,"") -> 0.062744681
A19: 31-60 Days Overdue | B19: =COUNTIFS('Invoice & Delivery Log'!$T$8:$T$157,$A19) -> 4 | C19: =SUMIFS('Invoice & Delivery Log'!$P$8:$P$157,'Invoice & Delivery Log'!$T$8:$T$157,$A19) -> 5691.73 | D19: =IFERROR($C19/$C$24,"") -> 0.10689956 | F19: Paid | G19: =COUNTIFS('Invoice & Delivery Log'!$Q$8:$Q$157,$F19) -> 41 | H19: =SUMIFS('Invoice & Delivery Log'!$N$8:$N$157,'Invoice & Delivery Log'!$Q$8:$Q$157,$F19) -> 138088.39 | I19: =IFERROR($H19/$H$24,"") -> 0.68222553
A20: 61-90 Days Overdue | B20: =COUNTIFS('Invoice & Delivery Log'!$T$8:$T$157,$A20) -> 2 | C20: =SUMIFS('Invoice & Delivery Log'!$P$8:$P$157,'Invoice & Delivery Log'!$T$8:$T$157,$A20) -> 4839.4 | D20: =IFERROR($C20/$C$24,"") -> 0.09089147 | F20: Overpaid | G20: =COUNTIFS('Invoice & Delivery Log'!$Q$8:$Q$157,$F20) -> 1 | H20: =SUMIFS('Invoice & Delivery Log'!$N$8:$N$157,'Invoice & Delivery Log'!$Q$8:$Q$157,$F20) -> 4269.92 | I20: =IFERROR($H20/$H$24,"") -> 0.021095535
A21: 90+ Days Overdue | B21: =COUNTIFS('Invoice & Delivery Log'!$T$8:$T$157,$A21) -> 4 | C21: =SUMIFS('Invoice & Delivery Log'!$P$8:$P$157,'Invoice & Delivery Log'!$T$8:$T$157,$A21) -> 18313.15 | D21: =IFERROR($C21/$C$24,"") -> 0.34394948 | F21: Check Amount | G21: =COUNTIFS('Invoice & Delivery Log'!$Q$8:$Q$157,$F21) -> 0 | H21: =SUMIFS('Invoice & Delivery Log'!$N$8:$N$157,'Invoice & Delivery Log'!$Q$8:$Q$157,$F21) -> 0 | I21: =IFERROR($H21/$H$24,"") -> 0
A22: No Due Date | B22: =COUNTIFS('Invoice & Delivery Log'!$T$8:$T$157,$A22) -> 0 | C22: =SUMIFS('Invoice & Delivery Log'!$P$8:$P$157,'Invoice & Delivery Log'!$T$8:$T$157,$A22) -> 0 | D22: =IFERROR($C22/$C$24,"") -> 0
A23: Supplier Credit | B23: =COUNTIFS('Invoice & Delivery Log'!$T$8:$T$157,$A23) -> 1 | C23: =SUMIFS('Invoice & Delivery Log'!$P$8:$P$157,'Invoice & Delivery Log'!$T$8:$T$157,$A23) -> -512.39 | D23: =IFERROR($C23/$C$24,"") -> -0.0096234824
A24: Total Outstanding | B24: =SUM($B$17:$B$23) -> 19 | C24: =SUM($C$17:$C$23) -> 53243.72 | D24: 100.0% | F24: Total Invoiced Value | G24: =SUM($G$17:$G$23) -> 60 | H24: =SUM($H$17:$H$23) -> 202408.71 | I24: 100.0%
A26: Top 5 Vendors by Outstanding Balance | F26: Next 5 Payments Due
A27: Vendor Name | B27: Outstanding | C27: Overdue | D27: Rating | F27: Invoice ID | G27: Vendor Name | H27: Due Date | I27: Outstanding
A28: =IFERROR(IF(LARGE('Vendor Master'!$S$8:$S$47,1)<=0,"",INDEX('Vendor Master'!$B$8:$B$47,MATCH(LARGE('Vendor Master'!$S$8:$S$47,1),'Vendor Master'!$S$8:$S$47,0))),"") -> Copperfield Textiles | B28: =IFERROR(IF(LARGE('Vendor Master'!$S$8:$S$47,1)<=0,"",INDEX('Vendor Master'!$L$8:$L$47,MATCH(LARGE('Vendor Master'!$S$8:$S$47,1),'Vendor Master'!$S$8:$S$47,0))),"") -> 17948.79 | C28: =IFERROR(IF(LARGE('Vendor Master'!$S$8:$S$47,1)<=0,"",INDEX('Vendor Master'!$M$8:$M$47,MATCH(LARGE('Vendor Master'!$S$8:$S$47,1),'Vendor Master'!$S$8:$S$47,0))),"") -> 9042.96 | D28: =IFERROR(IF(LARGE('Vendor Master'!$S$8:$S$47,1)<=0,"",INDEX('Vendor Master'!$R$8:$R$47,MATCH(LARGE('Vendor Master'!$S$8:$S$47,1),'Vendor Master'!$S$8:$S$47,0))),"") -> C | F28: =IFERROR(INDEX('Invoice & Delivery Log'!$A$8:$A$157,MATCH(1,'Invoice & Delivery Log'!$Z$8:$Z$157,0)),"") -> INV-1003 | G28: =IFERROR(INDEX('Invoice & Delivery Log'!$C$8:$C$157,MATCH(1,'Invoice & Delivery Log'!$Z$8:$Z$157,0)),"") -> Harborline Logistics | H28: =IFERROR(INDEX('Invoice & Delivery Log'!$M$8:$M$157,MATCH(1,'Invoice & Delivery Log'!$Z$8:$Z$157,0)),"") -> 46121 | I28: =IFERROR(INDEX('Invoice & Delivery Log'!$P$8:$P$157,MATCH(1,'Invoice & Delivery Log'!$Z$8:$Z$157,0)),"") -> 6019.33
A29: =IFERROR(IF(LARGE('Vendor Master'!$S$8:$S$47,2)<=0,"",INDEX('Vendor Master'!$B$8:$B$47,MATCH(LARGE('Vendor Master'!$S$8:$S$47,2),'Vendor Master'!$S$8:$S$47,0))),"") -> Ironbridge Hardware Co. | B29: =IFERROR(IF(LARGE('Vendor Master'!$S$8:$S$47,2)<=0,"",INDEX('Vendor Master'!$L$8:$L$47,MATCH(LARGE('Vendor Master'!$S$8:$S$47,2),'Vendor Master'!$S$8:$S$47,0))),"") -> 10402.56 | C29: =IFERROR(IF(LARGE('Vendor Master'!$S$8:$S$47,2)<=0,"",INDEX('Vendor Master'!$M$8:$M$47,MATCH(LARGE('Vendor Master'!$S$8:$S$47,2),'Vendor Master'!$S$8:$S$47,0))),"") -> 4198.12 | D29: =IFERROR(IF(LARGE('Vendor Master'!$S$8:$S$47,2)<=0,"",INDEX('Vendor Master'!$R$8:$R$47,MATCH(LARGE('Vendor Master'!$S$8:$S$47,2),'Vendor Master'!$S$8:$S$47,0))),"") -> C | F29: =IFERROR(INDEX('Invoice & Delivery Log'!$A$8:$A$157,MATCH(2,'Invoice & Delivery Log'!$Z$8:$Z$157,0)),"") -> INV-1015 | G29: =IFERROR(INDEX('Invoice & Delivery Log'!$C$8:$C$157,MATCH(2,'Invoice & Delivery Log'!$Z$8:$Z$157,0)),"") -> Northwind Paper Supply | H29: =IFERROR(INDEX('Invoice & Delivery Log'!$M$8:$M$157,MATCH(2,'Invoice & Delivery Log'!$Z$8:$Z$157,0)),"") -> 46144 | I29: =IFERROR(INDEX('Invoice & Delivery Log'!$P$8:$P$157,MATCH(2,'Invoice & Delivery Log'!$Z$8:$Z$157,0)),"") -> 2483.16
A30: =IFERROR(IF(LARGE('Vendor Master'!$S$8:$S$47,3)<=0,"",INDEX('Vendor Master'!$B$8:$B$47,MATCH(LARGE('Vendor Master'!$S$8:$S$47,3),'Vendor Master'!$S$8:$S$47,0))),"") -> Harborline Logistics | B30: =IFERROR(IF(LARGE('Vendor Master'!$S$8:$S$47,3)<=0,"",INDEX('Vendor Master'!$L$8:$L$47,MATCH(LARGE('Vendor Master'!$S$8:$S$47,3),'Vendor Master'!$S$8:$S$47,0))),"") -> 7891.53 | C30: =IFERROR(IF(LARGE('Vendor Master'!$S$8:$S$47,3)<=0,"",INDEX('Vendor Master'!$M$8:$M$47,MATCH(LARGE('Vendor Master'!$S$8:$S$47,3),'Vendor Master'!$S$8:$S$47,0))),"") -> 7891.53 | D30: =IFERROR(IF(LARGE('Vendor Master'!$S$8:$S$47,3)<=0,"",INDEX('Vendor Master'!$R$8:$R$47,MATCH(LARGE('Vendor Master'!$S$8:$S$47,3),'Vendor Master'!$S$8:$S$47,0))),"") -> C | F30: =IFERROR(INDEX('Invoice & Delivery Log'!$A$8:$A$157,MATCH(3,'Invoice & Delivery Log'!$Z$8:$Z$157,0)),"") -> INV-1010 | G30: =IFERROR(INDEX('Invoice & Delivery Log'!$C$8:$C$157,MATCH(3,'Invoice & Delivery Log'!$Z$8:$Z$157,0)),"") -> Copperfield Textiles | H30: =IFERROR(INDEX('Invoice & Delivery Log'!$M$8:$M$157,MATCH(3,'Invoice & Delivery Log'!$Z$8:$Z$157,0)),"") -> 46167 | I30: =IFERROR(INDEX('Invoice & Delivery Log'!$P$8:$P$157,MATCH(3,'Invoice & Delivery Log'!$Z$8:$Z$157,0)),"") -> 9042.96
A31: =IFERROR(IF(LARGE('Vendor Master'!$S$8:$S$47,4)<=0,"",INDEX('Vendor Master'!$B$8:$B$47,MATCH(LARGE('Vendor Master'!$S$8:$S$47,4),'Vendor Master'!$S$8:$S$47,0))),"") -> Lakeshore Packaging Group | B31: =IFERROR(IF(LARGE('Vendor Master'!$S$8:$S$47,4)<=0,"",INDEX('Vendor Master'!$L$8:$L$47,MATCH(LARGE('Vendor Master'!$S$8:$S$47,4),'Vendor Master'!$S$8:$S$47,0))),"") -> 6278.18 | C31: =IFERROR(IF(LARGE('Vendor Master'!$S$8:$S$47,4)<=0,"",INDEX('Vendor Master'!$M$8:$M$47,MATCH(LARGE('Vendor Master'!$S$8:$S$47,4),'Vendor Master'!$S$8:$S$47,0))),"") -> 1941.11 | D31: =IFERROR(IF(LARGE('Vendor Master'!$S$8:$S$47,4)<=0,"",INDEX('Vendor Master'!$R$8:$R$47,MATCH(LARGE('Vendor Master'!$S$8:$S$47,4),'Vendor Master'!$S$8:$S$47,0))),"") -> A | F31: =IFERROR(INDEX('Invoice & Delivery Log'!$A$8:$A$157,MATCH(4,'Invoice & Delivery Log'!$Z$8:$Z$157,0)),"") -> INV-1019 | G31: =IFERROR(INDEX('Invoice & Delivery Log'!$C$8:$C$157,MATCH(4,'Invoice & Delivery Log'!$Z$8:$Z$157,0)),"") -> Harborline Logistics | H31: =IFERROR(INDEX('Invoice & Delivery Log'!$M$8:$M$157,MATCH(4,'Invoice & Delivery Log'!$Z$8:$Z$157,0)),"") -> 46168 | I31: =IFERROR(INDEX('Invoice & Delivery Log'!$P$8:$P$157,MATCH(4,'Invoice & Delivery Log'!$Z$8:$Z$157,0)),"") -> 767.7
A32: =IFERROR(IF(LARGE('Vendor Master'!$S$8:$S$47,5)<=0,"",INDEX('Vendor Master'!$B$8:$B$47,MATCH(LARGE('Vendor Master'!$S$8:$S$47,5),'Vendor Master'!$S$8:$S$47,0))),"") -> Northwind Paper Supply | B32: =IFERROR(IF(LARGE('Vendor Master'!$S$8:$S$47,5)<=0,"",INDEX('Vendor Master'!$L$8:$L$47,MATCH(LARGE('Vendor Master'!$S$8:$S$47,5),'Vendor Master'!$S$8:$S$47,0))),"") -> 5176.74 | C32: =IFERROR(IF(LARGE('Vendor Master'!$S$8:$S$47,5)<=0,"",INDEX('Vendor Master'!$M$8:$M$47,MATCH(LARGE('Vendor Master'!$S$8:$S$47,5),'Vendor Master'!$S$8:$S$47,0))),"") -> 4090.42 | D32: =IFERROR(IF(LARGE('Vendor Master'!$S$8:$S$47,5)<=0,"",INDEX('Vendor Master'!$R$8:$R$47,MATCH(LARGE('Vendor Master'!$S$8:$S$47,5),'Vendor Master'!$S$8:$S$47,0))),"") -> B | F32: =IFERROR(INDEX('Invoice & Delivery Log'!$A$8:$A$157,MATCH(5,'Invoice & Delivery Log'!$Z$8:$Z$157,0)),"") -> INV-1024 | G32: =IFERROR(INDEX('Invoice & Delivery Log'!$C$8:$C$157,MATCH(5,'Invoice & Delivery Log'!$Z$8:$Z$157,0)),"") -> Ironbridge Hardware Co. | H32: =IFERROR(INDEX('Invoice & Delivery Log'!$M$8:$M$157,MATCH(5,'Invoice & Delivery Log'!$Z$8:$Z$157,0)),"") -> 46186 | I32: =IFERROR(INDEX('Invoice & Delivery Log'!$P$8:$P$157,MATCH(5,'Invoice & Delivery Log'!$Z$8:$Z$157,0)),"") -> 4198.12
A34: Monthly Invoiced vs Paid
A35: Month | B35: Invoiced | C35: Paid | D35: Net Movement
A36: 46082 | B36: =SUMIFS('Invoice & Delivery Log'!$N$8:$N$157,'Invoice & Delivery Log'!$H$8:$H$157,">="&$A36,'Invoice & Delivery Log'!$H$8:$H$157,"<="&EOMONTH($A36,0)) -> 49496.27 | C36: =SUMIFS('Payments Log'!$F$8:$F$207,'Payments Log'!$E$8:$E$207,">="&$A36,'Payments Log'!$E$8:$E$207,"<="&EOMONTH($A36,0)) -> 11300.96 | D36: =$B36-$C36 -> 38195.31
A37: 46113 | B37: =SUMIFS('Invoice & Delivery Log'!$N$8:$N$157,'Invoice & Delivery Log'!$H$8:$H$157,">="&$A37,'Invoice & Delivery Log'!$H$8:$H$157,"<="&EOMONTH($A37,0)) -> 43450.64 | C37: =SUMIFS('Payments Log'!$F$8:$F$207,'Payments Log'!$E$8:$E$207,">="&$A37,'Payments Log'!$E$8:$E$207,"<="&EOMONTH($A37,0)) -> 40062.55 | D37: =$B37-$C37 -> 3388.09
A38: 46143 | B38: =SUMIFS('Invoice & Delivery Log'!$N$8:$N$157,'Invoice & Delivery Log'!$H$8:$H$157,">="&$A38,'Invoice & Delivery Log'!$H$8:$H$157,"<="&EOMONTH($A38,0)) -> 33916.81 | C38: =SUMIFS('Payments Log'!$F$8:$F$207,'Payments Log'!$E$8:$E$207,">="&$A38,'Payments Log'!$E$8:$E$207,"<="&EOMONTH($A38,0)) -> 26867.57 | D38: =$B38-$C38 -> 7049.24
A39: 46174 | B39: =SUMIFS('Invoice & Delivery Log'!$N$8:$N$157,'Invoice & Delivery Log'!$H$8:$H$157,">="&$A39,'Invoice & Delivery Log'!$H$8:$H$157,"<="&EOMONTH($A39,0)) -> 29918.12 | C39: =SUMIFS('Payments Log'!$F$8:$F$207,'Payments Log'!$E$8:$E$207,">="&$A39,'Payments Log'!$E$8:$E$207,"<="&EOMONTH($A39,0)) -> 38431.19 | D39: =$B39-$C39 -> -8513.07
A40: 46204 | B40: =SUMIFS('Invoice & Delivery Log'!$N$8:$N$157,'Invoice & Delivery Log'!$H$8:$H$157,">="&$A40,'Invoice & Delivery Log'!$H$8:$H$157,"<="&EOMONTH($A40,0)) -> 23033.09 | C40: =SUMIFS('Payments Log'!$F$8:$F$207,'Payments Log'!$E$8:$E$207,">="&$A40,'Payments Log'!$E$8:$E$207,"<="&EOMONTH($A40,0)) -> 22048.71 | D40: =$B40-$C40 -> 984.38
A41: 46235 | B41: =SUMIFS('Invoice & Delivery Log'!$N$8:$N$157,'Invoice & Delivery Log'!$H$8:$H$157,">="&$A41,'Invoice & Delivery Log'!$H$8:$H$157,"<="&EOMONTH($A41,0)) -> 19263.63 | C41: =SUMIFS('Payments Log'!$F$8:$F$207,'Payments Log'!$E$8:$E$207,">="&$A41,'Payments Log'!$E$8:$E$207,"<="&EOMONTH($A41,0)) -> 11095.77 | D41: =$B41-$C41 -> 8167.86
A42: 46266 | B42: =SUMIFS('Invoice & Delivery Log'!$N$8:$N$157,'Invoice & Delivery Log'!$H$8:$H$157,">="&$A42,'Invoice & Delivery Log'!$H$8:$H$157,"<="&EOMONTH($A42,0)) -> 3330.15 | C42: =SUMIFS('Payments Log'!$F$8:$F$207,'Payments Log'!$E$8:$E$207,">="&$A42,'Payments Log'!$E$8:$E$207,"<="&EOMONTH($A42,0)) -> 838.24 | D42: =$B42-$C42 -> 2491.91
A43: Total | B43: =SUM($B$36:$B$42) -> 202408.71 | C43: =SUM($C$36:$C$42) -> 150644.99 | D43: =SUM($D$36:$D$42) -> 51763.72
A45: The monthly table counts invoices by invoice date and payments by payment date, so the two columns answer different questions: what we committed to, and what actually left the bank.

Sheet Vendor Master
A1: Vendor Master
A2: One row per supplier. Yellow columns are typed in; the rest is calculated from the invoice and payment logs.
A4: Vendor ID is the key that links this sheet to the Invoice & Delivery Log. Never reuse or renumber an ID.
A5: Supplier Score = On-Time Delivery Rate x weight (Settings!C14) + Full Receipt Rate x weight (Settings!C15). Rating bands are set in Settings rows 17-19.
A7: Vendor ID | B7: Vendor Name | C7: Category | D7: Contact Person | E7: Email | F7: Phone | G7: Payment Terms (Days) | H7: Vendor Status | I7: Invoices | J7: Total Invoiced | K7: Total Paid | L7: Outstanding Balance | M7: Overdue Amount | N7: On-Time Delivery Rate | O7: Full Receipt Rate | P7: Avg Days to Pay | Q7: Supplier Score | R7: Performance Rating | S7: Rank Key (helper)
A8: VEN-001 | B8: Northwind Paper Supply | C8: Office Supplies | D8: Dana Whitfield | E8: dana.whitfield@northwindpaper.example | F8: (312) 555-0142 | G8: 30 | H8: Active | I8: =IF($A8="","",COUNTIFS('Invoice & Delivery Log'!$B$8:$B$157,$A8)) -> 6 | J8: =IF($A8="","",SUMIFS('Invoice & Delivery Log'!$N$8:$N$157,'Invoice & Delivery Log'!$B$8:$B$157,$A8)) -> 8999.05 | K8: =IF($A8="","",SUMIFS('Invoice & Delivery Log'!$O$8:$O$157,'Invoice & Delivery Log'!$B$8:$B$157,$A8)) -> 3822.31 | L8: =IF($A8="","",SUMIFS('Invoice & Delivery Log'!$P$8:$P$157,'Invoice & Delivery Log'!$B$8:$B$157,$A8)) -> 5176.74 | M8: =IF($A8="","",SUMIFS('Invoice & Delivery Log'!$S$8:$S$157,'Invoice & Delivery Log'!$B$8:$B$157,$A8)) -> 4090.42 | N8: =IF($A8="","",IFERROR(COUNTIFS('Invoice & Delivery Log'!$B$8:$B$157,$A8,'Invoice & Delivery Log'!$V$8:$V$157,"On Time")/(COUNTIFS('Invoice & Delivery Log'!$B$8:$B$157,$A8,'Invoice & Delivery Log'!$V$8:$V$157,"On Time")+COUNTIFS('Invoice & Delivery Log'!$B$8:$B$157,$A8,'Invoice & Delivery Log'!$V$8:$V$157,"Late")),"")) -> 0.83333333 | O8: =IF($A8="","",IFERROR(COUNTIFS('Invoice & Delivery Log'!$B$8:$B$157,$A8,'Invoice & Delivery Log'!$K$8:$K$157,"Received in Full")/$I8,"")) -> 0.83333333 | P8: =IF($A8="","",IFERROR(ROUND(AVERAGEIFS('Payments Log'!$L$8:$L$207,'Payments Log'!$C$8:$C$207,$A8,'Payments Log'!$L$8:$L$207,">=0"),0),"")) -> 21 | Q8: =IF(OR($A8="",$I8=0),"",Settings!$C$14*IF($N8="",0,$N8)+Settings!$C$15*IF($O8="",0,$O8)) -> 0.83333333 | R8: =IF($Q8="","",IF($Q8>=Settings!$C$17,"A",IF($Q8>=Settings!$C$18,"B",IF($Q8>=Settings!$C$19,"C","D")))) -> B | S8: =IF($A8="","",$L8+ROW()/1000000) -> 5176.74
A9: VEN-002 | B9: Cascade Foods Distribution | C9: Food & Beverage | D9: Marco Ruiz | E9: marco.ruiz@cascadefoods.example | F9: (312) 555-0177 | G9: 15 | H9: Active | I9: =IF($A9="","",COUNTIFS('Invoice & Delivery Log'!$B$8:$B$157,$A9)) -> 6 | J9: =IF($A9="","",SUMIFS('Invoice & Delivery Log'!$N$8:$N$157,'Invoice & Delivery Log'!$B$8:$B$157,$A9)) -> 16224.28 | K9: =IF($A9="","",SUMIFS('Invoice & Delivery Log'!$O$8:$O$157,'Invoice & Delivery Log'!$B$8:$B$157,$A9)) -> 14304.51 | L9: =IF($A9="","",SUMIFS('Invoice & Delivery Log'!$P$8:$P$157,'Invoice & Delivery Log'!$B$8:$B$157,$A9)) -> 1919.77 | M9: =IF($A9="","",SUMIFS('Invoice & Delivery Log'!$S$8:$S$157,'Invoice & Delivery Log'!$B$8:$B$157,$A9)) -> 1919.77 | N9: =IF($A9="","",IFERROR(COUNTIFS('Invoice & Delivery Log'!$B$8:$B$157,$A9,'Invoice & Delivery Log'!$V$8:$V$157,"On Time")/(COUNTIFS('Invoice & Delivery Log'!$B$8:$B$157,$A9,'Invoice & Delivery Log'!$V$8:$V$157,"On Time")+COUNTIFS('Invoice & Delivery Log'!$B$8:$B$157,$A9,'Invoice & Delivery Log'!$V$8:$V$157,"Late")),"")) -> 0.83333333 | O9: =IF($A9="","",IFERROR(COUNTIFS('Invoice & Delivery Log'!$B$8:$B$157,$A9,'Invoice & Delivery Log'!$K$8:$K$157,"Received in Full")/$I9,"")) -> 0.5 | P9: =IF($A9="","",IFERROR(ROUND(AVERAGEIFS('Payments Log'!$L$8:$L$207,'Payments Log'!$C$8:$C$207,$A9,'Payments Log'!$L$8:$L$207,">=0"),0),"")) -> 10 | Q9: =IF(OR($A9="",$I9=0),"",Settings!$C$14*IF($N9="",0,$N9)+Settings!$C$15*IF($O9="",0,$O9)) -> 0.7 | R9: =IF($Q9="","",IF($Q9>=Settings!$C$17,"A",IF($Q9>=Settings!$C$18,"B",IF($Q9>=Settings!$C$19,"C","D")))) -> C | S9: =IF($A9="","",$L9+ROW()/1000000) -> 1919.77
A10: VEN-003 | B10: Ironbridge Hardware Co. | C10: Maintenance & Repair | D10: Priya Nadar | E10: priya.nadar@ironbridgehw.example | F10: (773) 555-0188 | G10: 45 | H10: Active | I10: =IF($A10="","",COUNTIFS('Invoice & Delivery Log'!$B$8:$B$157,$A10)) -> 5 | J10: =IF($A10="","",SUMIFS('Invoice & Delivery Log'!$N$8:$N$157,'Invoice & Delivery Log'!$B$8:$B$157,$A10)) -> 16426.14 | K10: =IF($A10="","",SUMIFS('Invoice & Delivery Log'!$O$8:$O$157,'Invoice & Delivery Log'!$B$8:$B$157,$A10)) -> 6023.58 | L10: =IF($A10="","",SUMIFS('Invoice & Delivery Log'!$P$8:$P$157,'Invoice & Delivery Log'!$B$8:$B$157,$A10)) -> 10402.56 | M10: =IF($A10="","",SUMIFS('Invoice & Delivery Log'!$S$8:$S$157,'Invoice & Delivery Log'!$B$8:$B$157,$A10)) -> 4198.12 | N10: =IF($A10="","",IFERROR(COUNTIFS('Invoice & Delivery Log'!$B$8:$B$157,$A10,'Invoice & Delivery Log'!$V$8:$V$157,"On Time")/(COUNTIFS('Invoice & Delivery Log'!$B$8:$B$157,$A10,'Invoice & Delivery Log'!$V$8:$V$157,"On Time")+COUNTIFS('Invoice & Delivery Log'!$B$8:$B$157,$A10,'Invoice & Delivery Log'!$V$8:$V$157,"Late")),"")) -> 0.6 | O10: =IF($A10="","",IFERROR(COUNTIFS('Invoice & Delivery Log'!$B$8:$B$157,$A10,'Invoice & Delivery Log'!$K$8:$K$157,"Received in Full")/$I10,"")) -> 1 | P10: =IF($A10="","",IFERROR(ROUND(AVERAGEIFS('Payments Log'!$L$8:$L$207,'Payments Log'!$C$8:$C$207,$A10,'Payments Log'!$L$8:$L$207,">=0"),0),"")) -> 8 | Q10: =IF(OR($A10="",$I10=0),"",Settings!$C$14*IF($N10="",0,$N10)+Settings!$C$15*IF($O10="",0,$O10)) -> 0.76 | R10: =IF($Q10="","",IF($Q10>=Settings!$C$17,"A",IF($Q10>=Settings!$C$18,"B",IF($Q10>=Settings!$C$19,"C","D")))) -> C | S10: =IF($A10="","",$L10+ROW()/1000000) -> 10402.56
A11: VEN-004 | B11: Lakeshore Packaging Group | C11: Packaging | D11: Ellen Novak | E11: ellen.novak@lakeshorepkg.example | F11: (847) 555-0113 | G11: 30 | H11: Active | I11: =IF($A11="","",COUNTIFS('Invoice & Delivery Log'!$B$8:$B$157,$A11)) -> 7 | J11: =IF($A11="","",SUMIFS('Invoice & Delivery Log'!$N$8:$N$157,'Invoice & Delivery Log'!$B$8:$B$157,$A11)) -> 28514.87 | K11: =IF($A11="","",SUMIFS('Invoice & Delivery Log'!$O$8:$O$157,'Invoice & Delivery Log'!$B$8:$B$157,$A11)) -> 22236.69 | L11: =IF($A11="","",SUMIFS('Invoice & Delivery Log'!$P$8:$P$157,'Invoice & Delivery Log'!$B$8:$B$157,$A11)) -> 6278.18 | M11: =IF($A11="","",SUMIFS('Invoice & Delivery Log'!$S$8:$S$157,'Invoice & Delivery Log'!$B$8:$B$157,$A11)) -> 1941.11 | N11: =IF($A11="","",IFERROR(COUNTIFS('Invoice & Delivery Log'!$B$8:$B$157,$A11,'Invoice & Delivery Log'!$V$8:$V$157,"On Time")/(COUNTIFS('Invoice & Delivery Log'!$B$8:$B$157,$A11,'Invoice & Delivery Log'!$V$8:$V$157,"On Time")+COUNTIFS('Invoice & Delivery Log'!$B$8:$B$157,$A11,'Invoice & Delivery Log'!$V$8:$V$157,"Late")),"")) -> 1 | O11: =IF($A11="","",IFERROR(COUNTIFS('Invoice & Delivery Log'!$B$8:$B$157,$A11,'Invoice & Delivery Log'!$K$8:$K$157,"Received in Full")/$I11,"")) -> 1 | P11: =IF($A11="","",IFERROR(ROUND(AVERAGEIFS('Payments Log'!$L$8:$L$207,'Payments Log'!$C$8:$C$207,$A11,'Payments Log'!$L$8:$L$207,">=0"),0),"")) -> 16 | Q11: =IF(OR($A11="",$I11=0),"",Settings!$C$14*IF($N11="",0,$N11)+Settings!$C$15*IF($O11="",0,$O11)) -> 1 | R11: =IF($Q11="","",IF($Q11>=Settings!$C$17,"A",IF($Q11>=Settings!$C$18,"B",IF($Q11>=Settings!$C$19,"C","D")))) -> A | S11: =IF($A11="","",$L11+ROW()/1000000) -> 6278.18
A12: VEN-005 | B12: Summit Cleaning Services | C12: Facility Services | D12: Tomas Berg | E12: tomas.berg@summitclean.example | F12: (224) 555-0166 | G12: 14 | H12: Active | I12: =IF($A12="","",COUNTIFS('Invoice & Delivery Log'!$B$8:$B$157,$A12)) -> 7 | J12: =IF($A12="","",SUMIFS('Invoice & Delivery Log'!$N$8:$N$157,'Invoice & Delivery Log'!$B$8:$B$157,$A12)) -> 11595.55 | K12: =IF($A12="","",SUMIFS('Invoice & Delivery Log'!$O$8:$O$157,'Invoice & Delivery Log'!$B$8:$B$157,$A12)) -> 11595.55 | L12: =IF($A12="","",SUMIFS('Invoice & Delivery Log'!$P$8:$P$157,'Invoice & Delivery Log'!$B$8:$B$157,$A12)) -> 0 | M12: =IF($A12="","",SUMIFS('Invoice & Delivery Log'!$S$8:$S$157,'Invoice & Delivery Log'!$B$8:$B$157,$A12)) -> 0 | N12: =IF($A12="","",IFERROR(COUNTIFS('Invoice & Delivery Log'!$B$8:$B$157,$A12,'Invoice & Delivery Log'!$V$8:$V$157,"On Time")/(COUNTIFS('Invoice & Delivery Log'!$B$8:$B$157,$A12,'Invoice & Delivery Log'!$V$8:$V$157,"On Time")+COUNTIFS('Invoice & Delivery Log'!$B$8:$B$157,$A12,'Invoice & Delivery Log'!$V$8:$V$157,"Late")),"")) -> 0.71428571 | O12: =IF($A12="","",IFERROR(COUNTIFS('Invoice & Delivery Log'!$B$8:$B$157,$A12,'Invoice & Delivery Log'!$K$8:$K$157,"Received in Full")/$I12,"")) -> 0.85714286 | P12: =IF($A12="","",IFERROR(ROUND(AVERAGEIFS('Payments Log'!$L$8:$L$207,'Payments Log'!$C$8:$C$207,$A12,'Payments Log'!$L$8:$L$207,">=0"),0),"")) -> 9 | Q12: =IF(OR($A12="",$I12=0),"",Settings!$C$14*IF($N12="",0,$N12)+Settings!$C$15*IF($O12="",0,$O12)) -> 0.77142857 | R12: =IF($Q12="","",IF($Q12>=Settings!$C$17,"A",IF($Q12>=Settings!$C$18,"B",IF($Q12>=Settings!$C$19,"C","D")))) -> C | S12: =IF($A12="","",$L12+ROW()/1000000) -> 1.2e-05
A13: VEN-006 | B13: Harborline Logistics | C13: Logistics | D13: Aisha Karim | E13: aisha.karim@harborlinelog.example | F13: (312) 555-0120 | G13: 30 | H13: Active | I13: =IF($A13="","",COUNTIFS('Invoice & Delivery Log'!$B$8:$B$157,$A13)) -> 10 | J13: =IF($A13="","",SUMIFS('Invoice & Delivery Log'!$N$8:$N$157,'Invoice & Delivery Log'!$B$8:$B$157,$A13)) -> 35790.13 | K13: =IF($A13="","",SUMIFS('Invoice & Delivery Log'!$O$8:$O$157,'Invoice & Delivery Log'!$B$8:$B$157,$A13)) -> 27898.6 | L13: =IF($A13="","",SUMIFS('Invoice & Delivery Log'!$P$8:$P$157,'Invoice & Delivery Log'!$B$8:$B$157,$A13)) -> 7891.53 | M13: =IF($A13="","",SUMIFS('Invoice & Delivery Log'!$S$8:$S$157,'Invoice & Delivery Log'!$B$8:$B$157,$A13)) -> 7891.53 | N13: =IF($A13="","",IFERROR(COUNTIFS('Invoice & Delivery Log'!$B$8:$B$157,$A13,'Invoice & Delivery Log'!$V$8:$V$157,"On Time")/(COUNTIFS('Invoice & Delivery Log'!$B$8:$B$157,$A13,'Invoice & Delivery Log'!$V$8:$V$157,"On Time")+COUNTIFS('Invoice & Delivery Log'!$B$8:$B$157,$A13,'Invoice & Delivery Log'!$V$8:$V$157,"Late")),"")) -> 0.6 | O13: =IF($A13="","",IFERROR(COUNTIFS('Invoice & Delivery Log'!$B$8:$B$157,$A13,'Invoice & Delivery Log'!$K$8:$K$157,"Received in Full")/$I13,"")) -> 0.9 | P13: =IF($A13="","",IFERROR(ROUND(AVERAGEIFS('Payments Log'!$L$8:$L$207,'Payments Log'!$C$8:$C$207,$A13,'Payments Log'!$L$8:$L$207,">=0"),0),"")) -> 22 | Q13: =IF(OR($A13="",$I13=0),"",Settings!$C$14*IF($N13="",0,$N13)+Settings!$C$15*IF($O13="",0,$O13)) -> 0.72 | R13: =IF($Q13="","",IF($Q13>=Settings!$C$17,"A",IF($Q13>=Settings!$C$18,"B",IF($Q13>=Settings!$C$19,"C","D")))) -> C | S13: =IF($A13="","",$L13+ROW()/1000000) -> 7891.53
A14: VEN-007 | B14: Bluepoint Electrical Supply | C14: Electrical | D14: Greg Salinas | E14: greg.salinas@bluepointel.example | F14: (630) 555-0195 | G14: 30 | H14: Active | I14: =IF($A14="","",COUNTIFS('Invoice & Delivery Log'!$B$8:$B$157,$A14)) -> 2 | J14: =IF($A14="","",SUMIFS('Invoice & Delivery Log'!$N$8:$N$157,'Invoice & Delivery Log'!$B$8:$B$157,$A14)) -> 3767.45 | K14: =IF($A14="","",SUMIFS('Invoice & Delivery Log'!$O$8:$O$157,'Invoice & Delivery Log'!$B$8:$B$157,$A14)) -> 3767.45 | L14: =IF($A14="","",SUMIFS('Invoice & Delivery Log'!$P$8:$P$157,'Invoice & Delivery Log'!$B$8:$B$157,$A14)) -> 0 | M14: =IF($A14="","",SUMIFS('Invoice & Delivery Log'!$S$8:$S$157,'Invoice & Delivery Log'!$B$8:$B$157,$A14)) -> 0 | N14: =IF($A14="","",IFERROR(COUNTIFS('Invoice & Delivery Log'!$B$8:$B$157,$A14,'Invoice & Delivery Log'!$V$8:$V$157,"On Time")/(COUNTIFS('Invoice & Delivery Log'!$B$8:$B$157,$A14,'Invoice & Delivery Log'!$V$8:$V$157,"On Time")+COUNTIFS('Invoice & Delivery Log'!$B$8:$B$157,$A14,'Invoice & Delivery Log'!$V$8:$V$157,"Late")),"")) -> 0.5 | O14: =IF($A14="","",IFERROR(COUNTIFS('Invoice & Delivery Log'!$B$8:$B$157,$A14,'Invoice & Delivery Log'!$K$8:$K$157,"Received in Full")/$I14,"")) -> 1 | P14: =IF($A14="","",IFERROR(ROUND(AVERAGEIFS('Payments Log'!$L$8:$L$207,'Payments Log'!$C$8:$C$207,$A14,'Payments Log'!$L$8:$L$207,">=0"),0),"")) -> 19 | Q14: =IF(OR($A14="",$I14=0),"",Settings!$C$14*IF($N14="",0,$N14)+Settings!$C$15*IF($O14="",0,$O14)) -> 0.7 | R14: =IF($Q14="","",IF($Q14>=Settings!$C$17,"A",IF($Q14>=Settings!$C$18,"B",IF($Q14>=Settings!$C$19,"C","D")))) -> C | S14: =IF($A14="","",$L14+ROW()/1000000) -> 1.4e-05
A15: VEN-008 | B15: Prairie Print & Signage | C15: Marketing & Print | D15: Nora Feldman | E15: nora.feldman@prairieprint.example | F15: (773) 555-0154 | G15: 21 | H15: Active | I15: =IF($A15="","",COUNTIFS('Invoice & Delivery Log'!$B$8:$B$157,$A15)) -> 1 | J15: =IF($A15="","",SUMIFS('Invoice & Delivery Log'!$N$8:$N$157,'Invoice & Delivery Log'!$B$8:$B$157,$A15)) -> 672.92 | K15: =IF($A15="","",SUMIFS('Invoice & Delivery Log'!$O$8:$O$157,'Invoice & Delivery Log'!$B$8:$B$157,$A15)) -> 672.92 | L15: =IF($A15="","",SUMIFS('Invoice & Delivery Log'!$P$8:$P$157,'Invoice & Delivery Log'!$B$8:$B$157,$A15)) -> 0 | M15: =IF($A15="","",SUMIFS('Invoice & Delivery Log'!$S$8:$S$157,'Invoice & Delivery Log'!$B$8:$B$157,$A15)) -> 0 | N15: =IF($A15="","",IFERROR(COUNTIFS('Invoice & Delivery Log'!$B$8:$B$157,$A15,'Invoice & Delivery Log'!$V$8:$V$157,"On Time")/(COUNTIFS('Invoice & Delivery Log'!$B$8:$B$157,$A15,'Invoice & Delivery Log'!$V$8:$V$157,"On Time")+COUNTIFS('Invoice & Delivery Log'!$B$8:$B$157,$A15,'Invoice & Delivery Log'!$V$8:$V$157,"Late")),"")) -> 1 | O15: =IF($A15="","",IFERROR(COUNTIFS('Invoice & Delivery Log'!$B$8:$B$157,$A15,'Invoice & Delivery Log'!$K$8:$K$157,"Received in Full")/$I15,"")) -> 1 | P15: =IF($A15="","",IFERROR(ROUND(AVERAGEIFS('Payments Log'!$L$8:$L$207,'Payments Log'!$C$8:$C$207,$A15,'Payments Log'!$L$8:$L$207,">=0"),0),"")) -> 8 | Q15: =IF(OR($A15="",$I15=0),"",Settings!$C$14*IF($N15="",0,$N15)+Settings!$C$15*IF($O15="",0,$O15)) -> 1 | R15: =IF($Q15="","",IF($Q15>=Settings!$C$17,"A",IF($Q15>=Settings!$C$18,"B",IF($Q15>=Settings!$C$19,"C","D")))) -> A | S15: =IF($A15="","",$L15+ROW()/1000000) -> 1.5e-05
A16: VEN-009 | B16: Vertex IT Solutions | C16: IT & Software | D16: Kevin Osei | E16: kevin.osei@vertexit.example | F16: (312) 555-0131 | G16: 30 | H16: Active | I16: =IF($A16="","",COUNTIFS('Invoice & Delivery Log'!$B$8:$B$157,$A16)) -> 5 | J16: =IF($A16="","",SUMIFS('Invoice & Delivery Log'!$N$8:$N$157,'Invoice & Delivery Log'!$B$8:$B$157,$A16)) -> 23638.56 | K16: =IF($A16="","",SUMIFS('Invoice & Delivery Log'!$O$8:$O$157,'Invoice & Delivery Log'!$B$8:$B$157,$A16)) -> 22773.69 | L16: =IF($A16="","",SUMIFS('Invoice & Delivery Log'!$P$8:$P$157,'Invoice & Delivery Log'!$B$8:$B$157,$A16)) -> 864.87 | M16: =IF($A16="","",SUMIFS('Invoice & Delivery Log'!$S$8:$S$157,'Invoice & Delivery Log'!$B$8:$B$157,$A16)) -> 864.87 | N16: =IF($A16="","",IFERROR(COUNTIFS('Invoice & Delivery Log'!$B$8:$B$157,$A16,'Invoice & Delivery Log'!$V$8:$V$157,"On Time")/(COUNTIFS('Invoice & Delivery Log'!$B$8:$B$157,$A16,'Invoice & Delivery Log'!$V$8:$V$157,"On Time")+COUNTIFS('Invoice & Delivery Log'!$B$8:$B$157,$A16,'Invoice & Delivery Log'!$V$8:$V$157,"Late")),"")) -> 1 | O16: =IF($A16="","",IFERROR(COUNTIFS('Invoice & Delivery Log'!$B$8:$B$157,$A16,'Invoice & Delivery Log'!$K$8:$K$157,"Received in Full")/$I16,"")) -> 1 | P16: =IF($A16="","",IFERROR(ROUND(AVERAGEIFS('Payments Log'!$L$8:$L$207,'Payments Log'!$C$8:$C$207,$A16,'Payments Log'!$L$8:$L$207,">=0"),0),"")) -> 20 | Q16: =IF(OR($A16="",$I16=0),"",Settings!$C$14*IF($N16="",0,$N16)+Settings!$C$15*IF($O16="",0,$O16)) -> 1 | R16: =IF($Q16="","",IF($Q16>=Settings!$C$17,"A",IF($Q16>=Settings!$C$18,"B",IF($Q16>=Settings!$C$19,"C","D")))) -> A | S16: =IF($A16="","",$L16+ROW()/1000000) -> 864.87002
A17: VEN-010 | B17: Copperfield Textiles | C17: Textiles | D17: Marta Silva | E17: marta.silva@copperfieldtex.example | F17: (847) 555-0109 | G17: 60 | H17: Active | I17: =IF($A17="","",COUNTIFS('Invoice & Delivery Log'!$B$8:$B$157,$A17)) -> 6 | J17: =IF($A17="","",SUMIFS('Invoice & Delivery Log'!$N$8:$N$157,'Invoice & Delivery Log'!$B$8:$B$157,$A17)) -> 47071.78 | K17: =IF($A17="","",SUMIFS('Invoice & Delivery Log'!$O$8:$O$157,'Invoice & Delivery Log'!$B$8:$B$157,$A17)) -> 29122.99 | L17: =IF($A17="","",SUMIFS('Invoice & Delivery Log'!$P$8:$P$157,'Invoice & Delivery Log'!$B$8:$B$157,$A17)) -> 17948.79 | M17: =IF($A17="","",SUMIFS('Invoice & Delivery Log'!$S$8:$S$157,'Invoice & Delivery Log'!$B$8:$B$157,$A17)) -> 9042.96 | N17: =IF($A17="","",IFERROR(COUNTIFS('Invoice & Delivery Log'!$B$8:$B$157,$A17,'Invoice & Delivery Log'!$V$8:$V$157,"On Time")/(COUNTIFS('Invoice & Delivery Log'!$B$8:$B$157,$A17,'Invoice & Delivery Log'!$V$8:$V$157,"On Time")+COUNTIFS('Invoice & Delivery Log'!$B$8:$B$157,$A17,'Invoice & Delivery Log'!$V$8:$V$157,"Late")),"")) -> 0.66666667 | O17: =IF($A17="","",IFERROR(COUNTIFS('Invoice & Delivery Log'!$B$8:$B$157,$A17,'Invoice & Delivery Log'!$K$8:$K$157,"Received in Full")/$I17,"")) -> 0.83333333 | P17: =IF($A17="","",IFERROR(ROUND(AVERAGEIFS('Payments Log'!$L$8:$L$207,'Payments Log'!$C$8:$C$207,$A17,'Payments Log'!$L$8:$L$207,">=0"),0),"")) -> 49 | Q17: =IF(OR($A17="",$I17=0),"",Settings!$C$14*IF($N17="",0,$N17)+Settings!$C$15*IF($O17="",0,$O17)) -> 0.73333333 | R17: =IF($Q17="","",IF($Q17>=Settings!$C$17,"A",IF($Q17>=Settings!$C$18,"B",IF($Q17>=Settings!$C$19,"C","D")))) -> C | S17: =IF($A17="","",$L17+ROW()/1000000) -> 17948.79
A18: VEN-011 | B18: Redstone Safety Equipment | C18: Safety & PPE | D18: Owen Brady | E18: owen.brady@redstonesafety.example | F18: (630) 555-0172 | G18: 30 | H18: Active | I18: =IF($A18="","",COUNTIFS('Invoice & Delivery Log'!$B$8:$B$157,$A18)) -> 2 | J18: =IF($A18="","",SUMIFS('Invoice & Delivery Log'!$N$8:$N$157,'Invoice & Delivery Log'!$B$8:$B$157,$A18)) -> 5653.27 | K18: =IF($A18="","",SUMIFS('Invoice & Delivery Log'!$O$8:$O$157,'Invoice & Delivery Log'!$B$8:$B$157,$A18)) -> 2891.99 | L18: =IF($A18="","",SUMIFS('Invoice & Delivery Log'!$P$8:$P$157,'Invoice & Delivery Log'!$B$8:$B$157,$A18)) -> 2761.28 | M18: =IF($A18="","",SUMIFS('Invoice & Delivery Log'!$S$8:$S$157,'Invoice & Delivery Log'!$B$8:$B$157,$A18)) -> 2761.28 | N18: =IF($A18="","",IFERROR(COUNTIFS('Invoice & Delivery Log'!$B$8:$B$157,$A18,'Invoice & Delivery Log'!$V$8:$V$157,"On Time")/(COUNTIFS('Invoice & Delivery Log'!$B$8:$B$157,$A18,'Invoice & Delivery Log'!$V$8:$V$157,"On Time")+COUNTIFS('Invoice & Delivery Log'!$B$8:$B$157,$A18,'Invoice & Delivery Log'!$V$8:$V$157,"Late")),"")) -> 1 | O18: =IF($A18="","",IFERROR(COUNTIFS('Invoice & Delivery Log'!$B$8:$B$157,$A18,'Invoice & Delivery Log'!$K$8:$K$157,"Received in Full")/$I18,"")) -> 1 | P18: =IF($A18="","",IFERROR(ROUND(AVERAGEIFS('Payments Log'!$L$8:$L$207,'Payments Log'!$C$8:$C$207,$A18,'Payments Log'!$L$8:$L$207,">=0"),0),"")) -> 13 | Q18: =IF(OR($A18="",$I18=0),"",Settings!$C$14*IF($N18="",0,$N18)+Settings!$C$15*IF($O18="",0,$O18)) -> 1 | R18: =IF($Q18="","",IF($Q18>=Settings!$C$17,"A",IF($Q18>=Settings!$C$18,"B",IF($Q18>=Settings!$C$19,"C","D")))) -> A | S18: =IF($A18="","",$L18+ROW()/1000000) -> 2761.28
A19: VEN-012 | B19: Willowbrook Beverage Co. | C19: Food & Beverage | D19: Lena Hart | E19: lena.hart@willowbrookbev.example | F19: (224) 555-0148 | G19: 15 | H19: Inactive | I19: =IF($A19="","",COUNTIFS('Invoice & Delivery Log'!$B$8:$B$157,$A19)) -> 3 | J19: =IF($A19="","",SUMIFS('Invoice & Delivery Log'!$N$8:$N$157,'Invoice & Delivery Log'!$B$8:$B$157,$A19)) -> 4054.71 | K19: =IF($A19="","",SUMIFS('Invoice & Delivery Log'!$O$8:$O$157,'Invoice & Delivery Log'!$B$8:$B$157,$A19)) -> 4054.71 | L19: =IF($A19="","",SUMIFS('Invoice & Delivery Log'!$P$8:$P$157,'Invoice & Delivery Log'!$B$8:$B$157,$A19)) -> 0 | M19: =IF($A19="","",SUMIFS('Invoice & Delivery Log'!$S$8:$S$157,'Invoice & Delivery Log'!$B$8:$B$157,$A19)) -> 0 | N19: =IF($A19="","",IFERROR(COUNTIFS('Invoice & Delivery Log'!$B$8:$B$157,$A19,'Invoice & Delivery Log'!$V$8:$V$157,"On Time")/(COUNTIFS('Invoice & Delivery Log'!$B$8:$B$157,$A19,'Invoice & Delivery Log'!$V$8:$V$157,"On Time")+COUNTIFS('Invoice & Delivery Log'!$B$8:$B$157,$A19,'Invoice & Delivery Log'!$V$8:$V$157,"Late")),"")) -> 1 | O19: =IF($A19="","",IFERROR(COUNTIFS('Invoice & Delivery Log'!$B$8:$B$157,$A19,'Invoice & Delivery Log'!$K$8:$K$157,"Received in Full")/$I19,"")) -> 1 | P19: =IF($A19="","",IFERROR(ROUND(AVERAGEIFS('Payments Log'!$L$8:$L$207,'Payments Log'!$C$8:$C$207,$A19,'Payments Log'!$L$8:$L$207,">=0"),0),"")) -> 15 | Q19: =IF(OR($A19="",$I19=0),"",Settings!$C$14*IF($N19="",0,$N19)+Settings!$C$15*IF($O19="",0,$O19)) -> 1 | R19: =IF($Q19="","",IF($Q19>=Settings!$C$17,"A",IF($Q19>=Settings!$C$18,"B",IF($Q19>=Settings!$C$19,"C","D")))) -> A | S19: =IF($A19="","",$L19+ROW()/1000000) -> 1.9e-05
I20: =IF($A20="","",COUNTIFS('Invoice & Delivery Log'!$B$8:$B$157,$A20)) | J20: =IF($A20="","",SUMIFS('Invoice & Delivery Log'!$N$8:$N$157,'Invoice & Delivery Log'!$B$8:$B$157,$A20)) | K20: =IF($A20="","",SUMIFS('Invoice & Delivery Log'!$O$8:$O$157,'Invoice & Delivery Log'!$B$8:$B$157,$A20)) | L20: =IF($A20="","",SUMIFS('Invoice & Delivery Log'!$P$8:$P$157,'Invoice & Delivery Log'!$B$8:$B$157,$A20)) | M20: =IF($A20="","",SUMIFS('Invoice & Delivery Log'!$S$8:$S$157,'Invoice & Delivery Log'!$B$8:$B$157,$A20)) | N20: =IF($A20="","",IFERROR(COUNTIFS('Invoice & Delivery Log'!$B$8:$B$157,$A20,'Invoice & Delivery Log'!$V$8:$V$157,"On Time")/(COUNTIFS('Invoice & Delivery Log'!$B$8:$B$157,$A20,'Invoice & Delivery Log'!$V$8:$V$157,"On Time")+COUNTIFS('Invoice & Delivery Log'!$B$8:$B$157,$A20,'Invoice & Delivery Log'!$V$8:$V$157,"Late")),"")) | O20: =IF($A20="","",IFERROR(COUNTIFS('Invoice & Delivery Log'!$B$8:$B$157,$A20,'Invoice & Delivery Log'!$K$8:$K$157,"Received in Full")/$I20,"")) | P20: =IF($A20="","",IFERROR(ROUND(AVERAGEIFS('Payments Log'!$L$8:$L$207,'Payments Log'!$C$8:$C$207,$A20,'Payments Log'!$L$8:$L$207,">=0"),0),"")) | Q20: =IF(OR($A20="",$I20=0),"",Settings!$C$14*IF($N20="",0,$N20)+Settings!$C$15*IF($O20="",0,$O20)) | R20: =IF($Q20="","",IF($Q20>=Settings!$C$17,"A",IF($Q20>=Settings!$C$18,"B",IF($Q20>=Settings!$C$19,"C","D")))) | S20: =IF($A20="","",$L20+ROW()/1000000)
I21: =IF($A21="","",COUNTIFS('Invoice & Delivery Log'!$B$8:$B$157,$A21)) | J21: =IF($A21="","",SUMIFS('Invoice & Delivery Log'!$N$8:$N$157,'Invoice & Delivery Log'!$B$8:$B$157,$A21)) | K21: =IF($A21="","",SUMIFS('Invoice & Delivery Log'!$O$8:$O$157,'Invoice & Delivery Log'!$B$8:$B$157,$A21)) | L21: =IF($A21="","",SUMIFS('Invoice & Delivery Log'!$P$8:$P$157,'Invoice & Delivery Log'!$B$8:$B$157,$A21)) | M21: =IF($A21="","",SUMIFS('Invoice & Delivery Log'!$S$8:$S$157,'Invoice & Delivery Log'!$B$8:$B$157,$A21)) | N21: =IF($A21="","",IFERROR(COUNTIFS('Invoice & Delivery Log'!$B$8:$B$157,$A21,'Invoice & Delivery Log'!$V$8:$V$157,"On Time")/(COUNTIFS('Invoice & Delivery Log'!$B$8:$B$157,$A21,'Invoice & Delivery Log'!$V$8:$V$157,"On Time")+COUNTIFS('Invoice & Delivery Log'!$B$8:$B$157,$A21,'Invoice & Delivery Log'!$V$8:$V$157,"Late")),"")) | O21: =IF($A21="","",IFERROR(COUNTIFS('Invoice & Delivery Log'!$B$8:$B$157,$A21,'Invoice & Delivery Log'!$K$8:$K$157,"Received in Full")/$I21,"")) | P21: =IF($A21="","",IFERROR(ROUND(AVERAGEIFS('Payments Log'!$L$8:$L$207,'Payments Log'!$C$8:$C$207,$A21,'Payments Log'!$L$8:$L$207,">=0"),0),"")) | Q21: =IF(OR($A21="",$I21=0),"",Settings!$C$14*IF($N21="",0,$N21)+Settings!$C$15*IF($O21="",0,$O21)) | R21: =IF($Q21="","",IF($Q21>=Settings!$C$17,"A",IF($Q21>=Settings!$C$18,"B",IF($Q21>=Settings!$C$19,"C","D")))) | S21: =IF($A21="","",$L21+ROW()/1000000)
I22: =IF($A22="","",COUNTIFS('Invoice & Delivery Log'!$B$8:$B$157,$A22)) | J22: =IF($A22="","",SUMIFS('Invoice & Delivery Log'!$N$8:$N$157,'Invoice & Delivery Log'!$B$8:$B$157,$A22)) | K22: =IF($A22="","",SUMIFS('Invoice & Delivery Log'!$O$8:$O$157,'Invoice & Delivery Log'!$B$8:$B$157,$A22)) | L22: =IF($A22="","",SUMIFS('Invoice & Delivery Log'!$P$8:$P$157,'Invoice & Delivery Log'!$B$8:$B$157,$A22)) | M22: =IF($A22="","",SUMIFS('Invoice & Delivery Log'!$S$8:$S$157,'Invoice & Delivery Log'!$B$8:$B$157,$A22)) | N22: =IF($A22="","",IFERROR(COUNTIFS('Invoice & Delivery Log'!$B$8:$B$157,$A22,'Invoice & Delivery Log'!$V$8:$V$157,"On Time")/(COUNTIFS('Invoice & Delivery Log'!$B$8:$B$157,$A22,'Invoice & Delivery Log'!$V$8:$V$157,"On Time")+COUNTIFS('Invoice & Delivery Log'!$B$8:$B$157,$A22,'Invoice & Delivery Log'!$V$8:$V$157,"Late")),"")) | O22: =IF($A22="","",IFERROR(COUNTIFS('Invoice & Delivery Log'!$B$8:$B$157,$A22,'Invoice & Delivery Log'!$K$8:$K$157,"Received in Full")/$I22,"")) | P22: =IF($A22="","",IFERROR(ROUND(AVERAGEIFS('Payments Log'!$L$8:$L$207,'Payments Log'!$C$8:$C$207,$A22,'Payments Log'!$L$8:$L$207,">=0"),0),"")) | Q22: =IF(OR($A22="",$I22=0),"",Settings!$C$14*IF($N22="",0,$N22)+Settings!$C$15*IF($O22="",0,$O22)) | R22: =IF($Q22="","",IF($Q22>=Settings!$C$17,"A",IF($Q22>=Settings!$C$18,"B",IF($Q22>=Settings!$C$19,"C","D")))) | S22: =IF($A22="","",$L22+ROW()/1000000)
I23: =IF($A23="","",COUNTIFS('Invoice & Delivery Log'!$B$8:$B$157,$A23)) | J23: =IF($A23="","",SUMIFS('Invoice & Delivery Log'!$N$8:$N$157,'Invoice & Delivery Log'!$B$8:$B$157,$A23)) | K23: =IF($A23="","",SUMIFS('Invoice & Delivery Log'!$O$8:$O$157,'Invoice & Delivery Log'!$B$8:$B$157,$A23)) | L23: =IF($A23="","",SUMIFS('Invoice & Delivery Log'!$P$8:$P$157,'Invoice & Delivery Log'!$B$8:$B$157,$A23)) | M23: =IF($A23="","",SUMIFS('Invoice & Delivery Log'!$S$8:$S$157,'Invoice & Delivery Log'!$B$8:$B$157,$A23)) | N23: =IF($A23="","",IFERROR(COUNTIFS('Invoice & Delivery Log'!$B$8:$B$157,$A23,'Invoice & Delivery Log'!$V$8:$V$157,"On Time")/(COUNTIFS('Invoice & Delivery Log'!$B$8:$B$157,$A23,'Invoice & Delivery Log'!$V$8:$V$157,"On Time")+COUNTIFS('Invoice & Delivery Log'!$B$8:$B$157,$A23,'Invoice & Delivery Log'!$V$8:$V$157,"Late")),"")) | O23: =IF($A23="","",IFERROR(COUNTIFS('Invoice & Delivery Log'!$B$8:$B$157,$A23,'Invoice & Delivery Log'!$K$8:$K$157,"Received in Full")/$I23,"")) | P23: =IF($A23="","",IFERROR(ROUND(AVERAGEIFS('Payments Log'!$L$8:$L$207,'Payments Log'!$C$8:$C$207,$A23,'Payments Log'!$L$8:$L$207,">=0"),0),"")) | Q23: =IF(OR($A23="",$I23=0),"",Settings!$C$14*IF($N23="",0,$N23)+Settings!$C$15*IF($O23="",0,$O23)) | R23: =IF($Q23="","",IF($Q23>=Settings!$C$17,"A",IF($Q23>=Settings!$C$18,"B",IF($Q23>=Settings!$C$19,"C","D")))) | S23: =IF($A23="","",$L23+ROW()/1000000)
I24: =IF($A24="","",COUNTIFS('Invoice & Delivery Log'!$B$8:$B$157,$A24)) | J24: =IF($A24="","",SUMIFS('Invoice & Delivery Log'!$N$8:$N$157,'Invoice & Delivery Log'!$B$8:$B$157,$A24)) | K24: =IF($A24="","",SUMIFS('Invoice & Delivery Log'!$O$8:$O$157,'Invoice & Delivery Log'!$B$8:$B$157,$A24)) | L24: =IF($A24="","",SUMIFS('Invoice & Delivery Log'!$P$8:$P$157,'Invoice & Delivery Log'!$B$8:$B$157,$A24)) | M24: =IF($A24="","",SUMIFS('Invoice & Delivery Log'!$S$8:$S$157,'Invoice & Delivery Log'!$B$8:$B$157,$A24)) | N24: =IF($A24="","",IFERROR(COUNTIFS('Invoice & Delivery Log'!$B$8:$B$157,$A24,'Invoice & Delivery Log'!$V$8:$V$157,"On Time")/(COUNTIFS('Invoice & Delivery Log'!$B$8:$B$157,$A24,'Invoice & Delivery Log'!$V$8:$V$157,"On Time")+COUNTIFS('Invoice & Delivery Log'!$B$8:$B$157,$A24,'Invoice & Delivery Log'!$V$8:$V$157,"Late")),"")) | O24: =IF($A24="","",IFERROR(COUNTIFS('Invoice & Delivery Log'!$B$8:$B$157,$A24,'Invoice & Delivery Log'!$K$8:$K$157,"Received in Full")/$I24,"")) | P24: =IF($A24="","",IFERROR(ROUND(AVERAGEIFS('Payments Log'!$L$8:$L$207,'Payments Log'!$C$8:$C$207,$A24,'Payments Log'!$L$8:$L$207,">=0"),0),"")) | Q24: =IF(OR($A24="",$I24=0),"",Settings!$C$14*IF($N24="",0,$N24)+Settings!$C$15*IF($O24="",0,$O24)) | R24: =IF($Q24="","",IF($Q24>=Settings!$C$17,"A",IF($Q24>=Settings!$C$18,"B",IF($Q24>=Settings!$C$19,"C","D")))) | S24: =IF($A24="","",$L24+ROW()/1000000)
I25: =IF($A25="","",COUNTIFS('Invoice & Delivery Log'!$B$8:$B$157,$A25)) | J25: =IF($A25="","",SUMIFS('Invoice & Delivery Log'!$N$8:$N$157,'Invoice & Delivery Log'!$B$8:$B$157,$A25)) | K25: =IF($A25="","",SUMIFS('Invoice & Delivery Log'!$O$8:$O$157,'Invoice & Delivery Log'!$B$8:$B$157,$A25)) | L25: =IF($A25="","",SUMIFS('Invoice & Delivery Log'!$P$8:$P$157,'Invoice & Delivery Log'!$B$8:$B$157,$A25)) | M25: =IF($A25="","",SUMIFS('Invoice & Delivery Log'!$S$8:$S$157,'Invoice & Delivery Log'!$B$8:$B$157,$A25)) | N25: =IF($A25="","",IFERROR(COUNTIFS('Invoice & Delivery Log'!$B$8:$B$157,$A25,'Invoice & Delivery Log'!$V$8:$V$157,"On Time")/(COUNTIFS('Invoice & Delivery Log'!$B$8:$B$157,$A25,'Invoice & Delivery Log'!$V$8:$V$157,"On Time")+COUNTIFS('Invoice & Delivery Log'!$B$8:$B$157,$A25,'Invoice & Delivery Log'!$V$8:$V$157,"Late")),"")) | O25: =IF($A25="","",IFERROR(COUNTIFS('Invoice & Delivery Log'!$B$8:$B$157,$A25,'Invoice & Delivery Log'!$K$8:$K$157,"Received in Full")/$I25,"")) | P25: =IF($A25="","",IFERROR(ROUND(AVERAGEIFS('Payments Log'!$L$8:$L$207,'Payments Log'!$C$8:$C$207,$A25,'Payments Log'!$L$8:$L$207,">=0"),0),"")) | Q25: =IF(OR($A25="",$I25=0),"",Settings!$C$14*IF($N25="",0,$N25)+Settings!$C$15*IF($O25="",0,$O25)) | R25: =IF($Q25="","",IF($Q25>=Settings!$C$17,"A",IF($Q25>=Settings!$C$18,"B",IF($Q25>=Settings!$C$19,"C","D")))) | S25: =IF($A25="","",$L25+ROW()/1000000)
I26: =IF($A26="","",COUNTIFS('Invoice & Delivery Log'!$B$8:$B$157,$A26)) | J26: =IF($A26="","",SUMIFS('Invoice & Delivery Log'!$N$8:$N$157,'Invoice & Delivery Log'!$B$8:$B$157,$A26)) | K26: =IF($A26="","",SUMIFS('Invoice & Delivery Log'!$O$8:$O$157,'Invoice & Delivery Log'!$B$8:$B$157,$A26)) | L26: =IF($A26="","",SUMIFS('Invoice & Delivery Log'!$P$8:$P$157,'Invoice & Delivery Log'!$B$8:$B$157,$A26)) | M26: =IF($A26="","",SUMIFS('Invoice & Delivery Log'!$S$8:$S$157,'Invoice & Delivery Log'!$B$8:$B$157,$A26)) | N26: =IF($A26="","",IFERROR(COUNTIFS('Invoice & Delivery Log'!$B$8:$B$157,$A26,'Invoice & Delivery Log'!$V$8:$V$157,"On Time")/(COUNTIFS('Invoice & Delivery Log'!$B$8:$B$157,$A26,'Invoice & Delivery Log'!$V$8:$V$157,"On Time")+COUNTIFS('Invoice & Delivery Log'!$B$8:$B$157,$A26,'Invoice & Delivery Log'!$V$8:$V$157,"Late")),"")) | O26: =IF($A26="","",IFERROR(COUNTIFS('Invoice & Delivery Log'!$B$8:$B$157,$A26,'Invoice & Delivery Log'!$K$8:$K$157,"Received in Full")/$I26,"")) | P26: =IF($A26="","",IFERROR(ROUND(AVERAGEIFS('Payments Log'!$L$8:$L$207,'Payments Log'!$C$8:$C$207,$A26,'Payments Log'!$L$8:$L$207,">=0"),0),"")) | Q26: =IF(OR($A26="",$I26=0),"",Settings!$C$14*IF($N26="",0,$N26)+Settings!$C$15*IF($O26="",0,$O26)) | R26: =IF($Q26="","",IF($Q26>=Settings!$C$17,"A",IF($Q26>=Settings!$C$18,"B",IF($Q26>=Settings!$C$19,"C","D")))) | S26: =IF($A26="","",$L26+ROW()/1000000)
I27: =IF($A27="","",COUNTIFS('Invoice & Delivery Log'!$B$8:$B$157,$A27)) | J27: =IF($A27="","",SUMIFS('Invoice & Delivery Log'!$N$8:$N$157,'Invoice & Delivery Log'!$B$8:$B$157,$A27)) | K27: =IF($A27="","",SUMIFS('Invoice & Delivery Log'!$O$8:$O$157,'Invoice & Delivery Log'!$B$8:$B$157,$A27)) | L27: =IF($A27="","",SUMIFS('Invoice & Delivery Log'!$P$8:$P$157,'Invoice & Delivery Log'!$B$8:$B$157,$A27)) | M27: =IF($A27="","",SUMIFS('Invoice & Delivery Log'!$S$8:$S$157,'Invoice & Delivery Log'!$B$8:$B$157,$A27)) | N27: =IF($A27="","",IFERROR(COUNTIFS('Invoice & Delivery Log'!$B$8:$B$157,$A27,'Invoice & Delivery Log'!$V$8:$V$157,"On Time")/(COUNTIFS('Invoice & Delivery Log'!$B$8:$B$157,$A27,'Invoice & Delivery Log'!$V$8:$V$157,"On Time")+COUNTIFS('Invoice & Delivery Log'!$B$8:$B$157,$A27,'Invoice & Delivery Log'!$V$8:$V$157,"Late")),"")) | O27: =IF($A27="","",IFERROR(COUNTIFS('Invoice & Delivery Log'!$B$8:$B$157,$A27,'Invoice & Delivery Log'!$K$8:$K$157,"Received in Full")/$I27,"")) | P27: =IF($A27="","",IFERROR(ROUND(AVERAGEIFS('Payments Log'!$L$8:$L$207,'Payments Log'!$C$8:$C$207,$A27,'Payments Log'!$L$8:$L$207,">=0"),0),"")) | Q27: =IF(OR($A27="",$I27=0),"",Settings!$C$14*IF($N27="",0,$N27)+Settings!$C$15*IF($O27="",0,$O27)) | R27: =IF($Q27="","",IF($Q27>=Settings!$C$17,"A",IF($Q27>=Settings!$C$18,"B",IF($Q27>=Settings!$C$19,"C","D")))) | S27: =IF($A27="","",$L27+ROW()/1000000)
I28: =IF($A28="","",COUNTIFS('Invoice & Delivery Log'!$B$8:$B$157,$A28)) | J28: =IF($A28="","",SUMIFS('Invoice & Delivery Log'!$N$8:$N$157,'Invoice & Delivery Log'!$B$8:$B$157,$A28)) | K28: =IF($A28="","",SUMIFS('Invoice & Delivery Log'!$O$8:$O$157,'Invoice & Delivery Log'!$B$8:$B$157,$A28)) | L28: =IF($A28="","",SUMIFS('Invoice & Delivery Log'!$P$8:$P$157,'Invoice & Delivery Log'!$B$8:$B$157,$A28)) | M28: =IF($A28="","",SUMIFS('Invoice & Delivery Log'!$S$8:$S$157,'Invoice & Delivery Log'!$B$8:$B$157,$A28)) | N28: =IF($A28="","",IFERROR(COUNTIFS('Invoice & Delivery Log'!$B$8:$B$157,$A28,'Invoice & Delivery Log'!$V$8:$V$157,"On Time")/(COUNTIFS('Invoice & Delivery Log'!$B$8:$B$157,$A28,'Invoice & Delivery Log'!$V$8:$V$157,"On Time")+COUNTIFS('Invoice & Delivery Log'!$B$8:$B$157,$A28,'Invoice & Delivery Log'!$V$8:$V$157,"Late")),"")) | O28: =IF($A28="","",IFERROR(COUNTIFS('Invoice & Delivery Log'!$B$8:$B$157,$A28,'Invoice & Delivery Log'!$K$8:$K$157,"Received in Full")/$I28,"")) | P28: =IF($A28="","",IFERROR(ROUND(AVERAGEIFS('Payments Log'!$L$8:$L$207,'Payments Log'!$C$8:$C$207,$A28,'Payments Log'!$L$8:$L$207,">=0"),0),"")) | Q28: =IF(OR($A28="",$I28=0),"",Settings!$C$14*IF($N28="",0,$N28)+Settings!$C$15*IF($O28="",0,$O28)) | R28: =IF($Q28="","",IF($Q28>=Settings!$C$17,"A",IF($Q28>=Settings!$C$18,"B",IF($Q28>=Settings!$C$19,"C","D")))) | S28: =IF($A28="","",$L28+ROW()/1000000)
I29: =IF($A29="","",COUNTIFS('Invoice & Delivery Log'!$B$8:$B$157,$A29)) | J29: =IF($A29="","",SUMIFS('Invoice & Delivery Log'!$N$8:$N$157,'Invoice & Delivery Log'!$B$8:$B$157,$A29)) | K29: =IF($A29="","",SUMIFS('Invoice & Delivery Log'!$O$8:$O$157,'Invoice & Delivery Log'!$B$8:$B$157,$A29)) | L29: =IF($A29="","",SUMIFS('Invoice & Delivery Log'!$P$8:$P$157,'Invoice & Delivery Log'!$B$8:$B$157,$A29)) | M29: =IF($A29="","",SUMIFS('Invoice & Delivery Log'!$S$8:$S$157,'Invoice & Delivery Log'!$B$8:$B$157,$A29)) | N29: =IF($A29="","",IFERROR(COUNTIFS('Invoice & Delivery Log'!$B$8:$B$157,$A29,'Invoice & Delivery Log'!$V$8:$V$157,"On Time")/(COUNTIFS('Invoice & Delivery Log'!$B$8:$B$157,$A29,'Invoice & Delivery Log'!$V$8:$V$157,"On Time")+COUNTIFS('Invoice & Delivery Log'!$B$8:$B$157,$A29,'Invoice & Delivery Log'!$V$8:$V$157,"Late")),"")) | O29: =IF($A29="","",IFERROR(COUNTIFS('Invoice & Delivery Log'!$B$8:$B$157,$A29,'Invoice & Delivery Log'!$K$8:$K$157,"Received in Full")/$I29,"")) | P29: =IF($A29="","",IFERROR(ROUND(AVERAGEIFS('Payments Log'!$L$8:$L$207,'Payments Log'!$C$8:$C$207,$A29,'Payments Log'!$L$8:$L$207,">=0"),0),"")) | Q29: =IF(OR($A29="",$I29=0),"",Settings!$C$14*IF($N29="",0,$N29)+Settings!$C$15*IF($O29="",0,$O29)) | R29: =IF($Q29="","",IF($Q29>=Settings!$C$17,"A",IF($Q29>=Settings!$C$18,"B",IF($Q29>=Settings!$C$19,"C","D")))) | S29: =IF($A29="","",$L29+ROW()/1000000)
I30: =IF($A30="","",COUNTIFS('Invoice & Delivery Log'!$B$8:$B$157,$A30)) | J30: =IF($A30="","",SUMIFS('Invoice & Delivery Log'!$N$8:$N$157,'Invoice & Delivery Log'!$B$8:$B$157,$A30)) | K30: =IF($A30="","",SUMIFS('Invoice & Delivery Log'!$O$8:$O$157,'Invoice & Delivery Log'!$B$8:$B$157,$A30)) | L30: =IF($A30="","",SUMIFS('Invoice & Delivery Log'!$P$8:$P$157,'Invoice & Delivery Log'!$B$8:$B$157,$A30)) | M30: =IF($A30="","",SUMIFS('Invoice & Delivery Log'!$S$8:$S$157,'Invoice & Delivery Log'!$B$8:$B$157,$A30)) | N30: =IF($A30="","",IFERROR(COUNTIFS('Invoice & Delivery Log'!$B$8:$B$157,$A30,'Invoice & Delivery Log'!$V$8:$V$157,"On Time")/(COUNTIFS('Invoice & Delivery Log'!$B$8:$B$157,$A30,'Invoice & Delivery Log'!$V$8:$V$157,"On Time")+COUNTIFS('Invoice & Delivery Log'!$B$8:$B$157,$A30,'Invoice & Delivery Log'!$V$8:$V$157,"Late")),"")) | O30: =IF($A30="","",IFERROR(COUNTIFS('Invoice & Delivery Log'!$B$8:$B$157,$A30,'Invoice & Delivery Log'!$K$8:$K$157,"Received in Full")/$I30,"")) | P30: =IF($A30="","",IFERROR(ROUND(AVERAGEIFS('Payments Log'!$L$8:$L$207,'Payments Log'!$C$8:$C$207,$A30,'Payments Log'!$L$8:$L$207,">=0"),0),"")) | Q30: =IF(OR($A30="",$I30=0),"",Settings!$C$14*IF($N30="",0,$N30)+Settings!$C$15*IF($O30="",0,$O30)) | R30: =IF($Q30="","",IF($Q30>=Settings!$C$17,"A",IF($Q30>=Settings!$C$18,"B",IF($Q30>=Settings!$C$19,"C","D")))) | S30: =IF($A30="","",$L30+ROW()/1000000)
I31: =IF($A31="","",COUNTIFS('Invoice & Delivery Log'!$B$8:$B$157,$A31)) | J31: =IF($A31="","",SUMIFS('Invoice & Delivery Log'!$N$8:$N$157,'Invoice & Delivery Log'!$B$8:$B$157,$A31)) | K31: =IF($A31="","",SUMIFS('Invoice & Delivery Log'!$O$8:$O$157,'Invoice & Delivery Log'!$B$8:$B$157,$A31)) | L31: =IF($A31="","",SUMIFS('Invoice & Delivery Log'!$P$8:$P$157,'Invoice & Delivery Log'!$B$8:$B$157,$A31)) | M31: =IF($A31="","",SUMIFS('Invoice & Delivery Log'!$S$8:$S$157,'Invoice & Delivery Log'!$B$8:$B$157,$A31)) | N31: =IF($A31="","",IFERROR(COUNTIFS('Invoice & Delivery Log'!$B$8:$B$157,$A31,'Invoice & Delivery Log'!$V$8:$V$157,"On Time")/(COUNTIFS('Invoice & Delivery Log'!$B$8:$B$157,$A31,'Invoice & Delivery Log'!$V$8:$V$157,"On Time")+COUNTIFS('Invoice & Delivery Log'!$B$8:$B$157,$A31,'Invoice & Delivery Log'!$V$8:$V$157,"Late")),"")) | O31: =IF($A31="","",IFERROR(COUNTIFS('Invoice & Delivery Log'!$B$8:$B$157,$A31,'Invoice & Delivery Log'!$K$8:$K$157,"Received in Full")/$I31,"")) | P31: =IF($A31="","",IFERROR(ROUND(AVERAGEIFS('Payments Log'!$L$8:$L$207,'Payments Log'!$C$8:$C$207,$A31,'Payments Log'!$L$8:$L$207,">=0"),0),"")) | Q31: =IF(OR($A31="",$I31=0),"",Settings!$C$14*IF($N31="",0,$N31)+Settings!$C$15*IF($O31="",0,$O31)) | R31: =IF($Q31="","",IF($Q31>=Settings!$C$17,"A",IF($Q31>=Settings!$C$18,"B",IF($Q31>=Settings!$C$19,"C","D")))) | S31: =IF($A31="","",$L31+ROW()/1000000)
... I47: =IF($A47="","",COUNTIFS('Invoice & Delivery Log'!$B$8:$B$157,$A47)) | J47: =IF($A47="","",SUMIFS('Invoice & Delivery Log'!$N$8:$N$157,'Invoice & Delivery Log'!$B$8:$B$157,$A47)) | K47: =IF($A47="","",SUMIFS('Invoice & Delivery Log'!$O$8:$O$157,'Invoice & Delivery Log'!$B$8:$B$157,$A47)) | L47: =IF($A47="","",SUMIFS('Invoice & Delivery Log'!$P$8:$P$157,'Invoice & Delivery Log'!$B$8:$B$157,$A47)) | M47: =IF($A47="","",SUMIFS('Invoice & Delivery Log'!$S$8:$S$157,'Invoice & Delivery Log'!$B$8:$B$157,$A47)) | N47: =IF($A47="","",IFERROR(COUNTIFS('Invoice & Delivery Log'!$B$8:$B$157,$A47,'Invoice & Delivery Log'!$V$8:$V$157,"On Time")/(COUNTIFS('Invoice & Delivery Log'!$B$8:$B$157,$A47,'Invoice & Delivery Log'!$V$8:$V$157,"On Time")+COUNTIFS('Invoice & Delivery Log'!$B$8:$B$157,$A47,'Invoice & Delivery Log'!$V$8:$V$157,"Late")),"")) | O47: =IF($A47="","",IFERROR(COUNTIFS('Invoice & Delivery Log'!$B$8:$B$157,$A47,'Invoice & Delivery Log'!$K$8:$K$157,"Received in Full")/$I47,"")) | P47: =IF($A47="","",IFERROR(ROUND(AVERAGEIFS('Payments Log'!$L$8:$L$207,'Payments Log'!$C$8:$C$207,$A47,'Payments Log'!$L$8:$L$207,">=0"),0),"")) | Q47: =IF(OR($A47="",$I47=0),"",Settings!$C$14*IF($N47="",0,$N47)+Settings!$C$15*IF($O47="",0,$O47)) | R47: =IF($Q47="","",IF($Q47>=Settings!$C$17,"A",IF($Q47>=Settings!$C$18,"B",IF($Q47>=Settings!$C$19,"C","D")))) | S47: =IF($A47="","",$L47+ROW()/1000000)

Sheet Invoice & Delivery Log
A1: Invoice & Delivery Log
A2: One row per supplier invoice. Record the delivery and the invoice here; record the money on the Payments Log.
A4: Type only in the yellow columns (A-K, N). Everything from L onwards is calculated.
A5: Due Date = Invoice Date + the payment terms held on Vendor Master. Amount Paid is summed from the Payments Log, so part payments update this sheet automatically.
A7: Invoice ID | B7: Vendor ID | C7: Vendor Name | D7: Supplier Invoice No. | E7: PO Number | F7: Category | G7: Description | H7: Invoice Date | I7: Expected Delivery Date | J7: Actual Delivery Date | K7: Goods Receipt Status | L7: Payment Terms (Days) | M7: Due Date | N7: Invoice Amount | O7: Amount Paid | P7: Outstanding Balance | Q7: Payment Status | R7: Days Overdue | S7: Overdue Amount | T7: Aging Bucket | U7: Last Payment Date | V7: Delivery Performance | W7: Data Check | X7: Issue Details | Y7: Open? | Z7: Priority Rank
A8: INV-1001 | B8: VEN-010 | C8: =IF($B8="","",IFERROR(INDEX('Vendor Master'!$B$8:$B$47,MATCH($B8,'Vendor Master'!$A$8:$A$47,0)),"NOT FOUND")) -> Copperfield Textiles | D8: CFT-2026001 | E8: PO-2026-0001 | F8: =IF($B8="","",IFERROR(INDEX('Vendor Master'!$C$8:$C$47,MATCH($B8,'Vendor Master'!$A$8:$A$47,0)),"")) -> Textiles | G8: Staff uniforms | H8: 46084 | I8: 46084 | J8: 46084 | K8: Received in Full | L8: =IF($B8="","",IFERROR(INDEX('Vendor Master'!$G$8:$G$47,MATCH($B8,'Vendor Master'!$A$8:$A$47,0)),"")) -> 60 | M8: =IF(OR($H8="",$L8=""),"",$H8+$L8) -> 46144 | N8: 4269.92 | O8: =IF($A8="","",SUMIFS('Payments Log'!$F$8:$F$207,'Payments Log'!$B$8:$B$207,$A8)) -> 4782.31 | P8: =IF($A8="","",ROUND($N8-$O8,2)) -> -512.39 | Q8: =IF($A8="","",IF(N($N8)<=0,"Check Amount",IF(ROUND($O8,2)<=0,"Unpaid",IF(ROUND($O8-$N8,2)>0,"Overpaid",IF(ROUND($P8,2)<=0,"Paid","Partially Paid"))))) -> Overpaid | R8: =IF(OR($A8="",$M8=""),"",IF(ROUND($P8,2)<=0,0,MAX(0,Settings!$C$5-$M8-Settings!$C$7))) -> 0 | S8: =IF($A8="","",IF(N($R8)>0,MAX($P8,0),0)) -> 0 | T8: =IF($A8="","",IF(ROUND($P8,2)<0,"Supplier Credit",IF(ROUND($P8,2)=0,"Closed",IF($M8="","No Due Date",IF(N($R8)<=0,"Not Due Yet",IF(N($R8)<=Settings!$C$8,"1-30 Days Overdue",IF(N($R8)<=Settings!$C$9,"31-60 Days Overdue",IF(N($R8)<=Settings!$C$10,"61-90 Days Overdue","90+ Days Overdue")))))))) -> Supplier Credit | U8: =IF($A8="","",IF(COUNTIFS('Payments Log'!$B$8:$B$207,$A8)=0,"",SUMPRODUCT(MAX(('Payments Log'!$B$8:$B$207=$A8)*'Payments Log'!$E$8:$E$207)))) -> 46154 | V8: =IF($A8="","",IF($J8="","Not Delivered",IF($I8="","No Target Date",IF($J8<=$I8,"On Time","Late")))) -> On Time | W8: =IF($A8="","",IF($X8="","OK","REVIEW")) -> REVIEW | X8: =IF($A8="","",TRIM(IF($B8="","Missing vendor ID. ","")&IF($C8="NOT FOUND","Vendor ID not in Vendor Master. ","")&IF(COUNTIFS('Invoice & Delivery Log'!$A$8:$A$157,$A8)>1,"Duplicate invoice ID. ","")&IF(AND($D8<>"",COUNTIFS('Invoice & Delivery Log'!$D$8:$D$157,$D8,'Invoice & Delivery Log'!$B$8:$B$157,$B8)>1),"Duplicate supplier invoice number. ","")&IF($E8="","Missing PO number. ","")&IF($H8="","Missing invoice date. ","")&IF(N($N8)<=0,"Invoice amount must be greater than zero. ","")&IF(AND($H8<>"",$H8>Settings!$C$5),"Invoice date is in the future. ","")&IF(AND($K8="Received in Full",$J8=""),"Missing actual delivery date. ","")&IF(ROUND(N($O8)-N($N8),2)>0,"Payments exceed the invoice amount. ","")&IF(AND($K8="Rejected",N($O8)>0),"Payment made on a rejected delivery. ","")&IF(AND($B8<>"",IFERROR(INDEX('Vendor Master'!$H$8:$H$47,MATCH($B8,'Vendor Master'!$A$8:$A$47,0)),"")="Inactive",ROUND(N($P8),2)>0),"Open balance with an inactive vendor. ",""))) -> Payments exceed the invoice amount. | Y8: =IF($A8="","",IF(ROUND($P8,2)>0.004,"Yes","No")) -> No | Z8: =IF(OR($Y8<>"Yes",$M8=""),"",COUNTIFS('Invoice & Delivery Log'!$Y$8:$Y$157,"Yes",'Invoice & Delivery Log'!$M$8:$M$157,"<"&$M8)+COUNTIFS('Invoice & Delivery Log'!$Y$8:$Y$157,"Yes",'Invoice & Delivery Log'!$M$8:$M$157,$M8,'Invoice & Delivery Log'!$A$8:$A$157,"<"&$A8)+1)
A9: INV-1002 | B9: VEN-006 | C9: =IF($B9="","",IFERROR(INDEX('Vendor Master'!$B$8:$B$47,MATCH($B9,'Vendor Master'!$A$8:$A$47,0)),"NOT FOUND")) -> Harborline Logistics | D9: HLL-2026001 | E9: PO-2026-0002 | F9: =IF($B9="","",IFERROR(INDEX('Vendor Master'!$C$8:$C$47,MATCH($B9,'Vendor Master'!$A$8:$A$47,0)),"")) -> Logistics | G9: Courier services | H9: 46085 | I9: 46084 | J9: 46084 | K9: Received in Full | L9: =IF($B9="","",IFERROR(INDEX('Vendor Master'!$G$8:$G$47,MATCH($B9,'Vendor Master'!$A$8:$A$47,0)),"")) -> 30 | M9: =IF(OR($H9="",$L9=""),"",$H9+$L9) -> 46115 | N9: 5983.69 | O9: =IF($A9="","",SUMIFS('Payments Log'!$F$8:$F$207,'Payments Log'!$B$8:$B$207,$A9)) -> 5983.69 | P9: =IF($A9="","",ROUND($N9-$O9,2)) -> 0 | Q9: =IF($A9="","",IF(N($N9)<=0,"Check Amount",IF(ROUND($O9,2)<=0,"Unpaid",IF(ROUND($O9-$N9,2)>0,"Overpaid",IF(ROUND($P9,2)<=0,"Paid","Partially Paid"))))) -> Paid | R9: =IF(OR($A9="",$M9=""),"",IF(ROUND($P9,2)<=0,0,MAX(0,Settings!$C$5-$M9-Settings!$C$7))) -> 0 | S9: =IF($A9="","",IF(N($R9)>0,MAX($P9,0),0)) -> 0 | T9: =IF($A9="","",IF(ROUND($P9,2)<0,"Supplier Credit",IF(ROUND($P9,2)=0,"Closed",IF($M9="","No Due Date",IF(N($R9)<=0,"Not Due Yet",IF(N($R9)<=Settings!$C$8,"1-30 Days Overdue",IF(N($R9)<=Settings!$C$9,"31-60 Days Overdue",IF(N($R9)<=Settings!$C$10,"61-90 Days Overdue","90+ Days Overdue")))))))) -> Closed | U9: =IF($A9="","",IF(COUNTIFS('Payments Log'!$B$8:$B$207,$A9)=0,"",SUMPRODUCT(MAX(('Payments Log'!$B$8:$B$207=$A9)*'Payments Log'!$E$8:$E$207)))) -> 46098 | V9: =IF($A9="","",IF($J9="","Not Delivered",IF($I9="","No Target Date",IF($J9<=$I9,"On Time","Late")))) -> On Time | W9: =IF($A9="","",IF($X9="","OK","REVIEW")) -> OK | X9: =IF($A9="","",TRIM(IF($B9="","Missing vendor ID. ","")&IF($C9="NOT FOUND","Vendor ID not in Vendor Master. ","")&IF(COUNTIFS('Invoice & Delivery Log'!$A$8:$A$157,$A9)>1,"Duplicate invoice ID. ","")&IF(AND($D9<>"",COUNTIFS('Invoice & Delivery Log'!$D$8:$D$157,$D9,'Invoice & Delivery Log'!$B$8:$B$157,$B9)>1),"Duplicate supplier invoice number. ","")&IF($E9="","Missing PO number. ","")&IF($H9="","Missing invoice date. ","")&IF(N($N9)<=0,"Invoice amount must be greater than zero. ","")&IF(AND($H9<>"",$H9>Settings!$C$5),"Invoice date is in the future. ","")&IF(AND($K9="Received in Full",$J9=""),"Missing actual delivery date. ","")&IF(ROUND(N($O9)-N($N9),2)>0,"Payments exceed the invoice amount. ","")&IF(AND($K9="Rejected",N($O9)>0),"Payment made on a rejected delivery. ","")&IF(AND($B9<>"",IFERROR(INDEX('Vendor Master'!$H$8:$H$47,MATCH($B9,'Vendor Master'!$A$8:$A$47,0)),"")="Inactive",ROUND(N($P9),2)>0),"Open balance with an inactive vendor. ",""))) | Y9: =IF($A9="","",IF(ROUND($P9,2)>0.004,"Yes","No")) -> No | Z9: =IF(OR($Y9<>"Yes",$M9=""),"",COUNTIFS('Invoice & Delivery Log'!$Y$8:$Y$157,"Yes",'Invoice & Delivery Log'!$M$8:$M$157,"<"&$M9)+COUNTIFS('Invoice & Delivery Log'!$Y$8:$Y$157,"Yes",'Invoice & Delivery Log'!$M$8:$M$157,$M9,'Invoice & Delivery Log'!$A$8:$A$157,"<"&$A9)+1)
A10: INV-1003 | B10: VEN-006 | C10: =IF($B10="","",IFERROR(INDEX('Vendor Master'!$B$8:$B$47,MATCH($B10,'Vendor Master'!$A$8:$A$47,0)),"NOT FOUND")) -> Harborline Logistics | D10: HLL-2026002 | E10: PO-2026-0003 | F10: =IF($B10="","",IFERROR(INDEX('Vendor Master'!$C$8:$C$47,MATCH($B10,'Vendor Master'!$A$8:$A$47,0)),"")) -> Logistics | G10: Courier services | H10: 46091 | I10: 46086 | J10: 46091 | K10: Partially Received | L10: =IF($B10="","",IFERROR(INDEX('Vendor Master'!$G$8:$G$47,MATCH($B10,'Vendor Master'!$A$8:$A$47,0)),"")) -> 30 | M10: =IF(OR($H10="",$L10=""),"",$H10+$L10) -> 46121 | N10: 6019.33 | O10: =IF($A10="","",SUMIFS('Payments Log'!$F$8:$F$207,'Payments Log'!$B$8:$B$207,$A10)) -> 0 | P10: =IF($A10="","",ROUND($N10-$O10,2)) -> 6019.33 | Q10: =IF($A10="","",IF(N($N10)<=0,"Check Amount",IF(ROUND($O10,2)<=0,"Unpaid",IF(ROUND($O10-$N10,2)>0,"Overpaid",IF(ROUND($P10,2)<=0,"Paid","Partially Paid"))))) -> Unpaid | R10: =IF(OR($A10="",$M10=""),"",IF(ROUND($P10,2)<=0,0,MAX(0,Settings!$C$5-$M10-Settings!$C$7))) -> 151 | S10: =IF($A10="","",IF(N($R10)>0,MAX($P10,0),0)) -> 6019.33 | T10: =IF($A10="","",IF(ROUND($P10,2)<0,"Supplier Credit",IF(ROUND($P10,2)=0,"Closed",IF($M10="","No Due Date",IF(N($R10)<=0,"Not Due Yet",IF(N($R10)<=Settings!$C$8,"1-30 Days Overdue",IF(N($R10)<=Settings!$C$9,"31-60 Days Overdue",IF(N($R10)<=Settings!$C$10,"61-90 Days Overdue","90+ Days Overdue")))))))) -> 90+ Days Overdue | U10: =IF($A10="","",IF(COUNTIFS('Payments Log'!$B$8:$B$207,$A10)=0,"",SUMPRODUCT(MAX(('Payments Log'!$B$8:$B$207=$A10)*'Payments Log'!$E$8:$E$207)))) | V10: =IF($A10="","",IF($J10="","Not Delivered",IF($I10="","No Target Date",IF($J10<=$I10,"On Time","Late")))) -> Late | W10: =IF($A10="","",IF($X10="","OK","REVIEW")) -> OK | X10: =IF($A10="","",TRIM(IF($B10="","Missing vendor ID. ","")&IF($C10="NOT FOUND","Vendor ID not in Vendor Master. ","")&IF(COUNTIFS('Invoice & Delivery Log'!$A$8:$A$157,$A10)>1,"Duplicate invoice ID. ","")&IF(AND($D10<>"",COUNTIFS('Invoice & Delivery Log'!$D$8:$D$157,$D10,'Invoice & Delivery Log'!$B$8:$B$157,$B10)>1),"Duplicate supplier invoice number. ","")&IF($E10="","Missing PO number. ","")&IF($H10="","Missing invoice date. ","")&IF(N($N10)<=0,"Invoice amount must be greater than zero. ","")&IF(AND($H10<>"",$H10>Settings!$C$5),"Invoice date is in the future. ","")&IF(AND($K10="Received in Full",$J10=""),"Missing actual delivery date. ","")&IF(ROUND(N($O10)-N($N10),2)>0,"Payments exceed the invoice amount. ","")&IF(AND($K10="Rejected",N($O10)>0),"Payment made on a rejected delivery. ","")&IF(AND($B10<>"",IFERROR(INDEX('Vendor Master'!$H$8:$H$47,MATCH($B10,'Vendor Master'!$A$8:$A$47,0)),"")="Inactive",ROUND(N($P10),2)>0),"Open balance with an inactive vendor. ",""))) | Y10: =IF($A10="","",IF(ROUND($P10,2)>0.004,"Yes","No")) -> Yes | Z10: =IF(OR($Y10<>"Yes",$M10=""),"",COUNTIFS('Invoice & Delivery Log'!$Y$8:$Y$157,"Yes",'Invoice & Delivery Log'!$M$8:$M$157,"<"&$M10)+COUNTIFS('Invoice & Delivery Log'!$Y$8:$Y$157,"Yes",'Invoice & Delivery Log'!$M$8:$M$157,$M10,'Invoice & Delivery Log'!$A$8:$A$157,"<"&$A10)+1) -> 1
A11: INV-1004 | B11: VEN-002 | C11: =IF($B11="","",IFERROR(INDEX('Vendor Master'!$B$8:$B$47,MATCH($B11,'Vendor Master'!$A$8:$A$47,0)),"NOT FOUND")) -> Cascade Foods Distribution | D11: CFD-2026001 | E11: PO-2026-0004 | F11: =IF($B11="","",IFERROR(INDEX('Vendor Master'!$C$8:$C$47,MATCH($B11,'Vendor Master'!$A$8:$A$47,0)),"")) -> Food & Beverage | G11: Fresh produce delivery | H11: 46090 | I11: 46090 | J11: 46090 | K11: Partially Received | L11: =IF($B11="","",IFERROR(INDEX('Vendor Master'!$G$8:$G$47,MATCH($B11,'Vendor Master'!$A$8:$A$47,0)),"")) -> 15 | M11: =IF(OR($H11="",$L11=""),"",$H11+$L11) -> 46105 | N11: 3640.26 | O11: =IF($A11="","",SUMIFS('Payments Log'!$F$8:$F$207,'Payments Log'!$B$8:$B$207,$A11)) -> 3640.26 | P11: =IF($A11="","",ROUND($N11-$O11,2)) -> 0 | Q11: =IF($A11="","",IF(N($N11)<=0,"Check Amount",IF(ROUND($O11,2)<=0,"Unpaid",IF(ROUND($O11-$N11,2)>0,"Overpaid",IF(ROUND($P11,2)<=0,"Paid","Partially Paid"))))) -> Paid | R11: =IF(OR($A11="",$M11=""),"",IF(ROUND($P11,2)<=0,0,MAX(0,Settings!$C$5-$M11-Settings!$C$7))) -> 0 | S11: =IF($A11="","",IF(N($R11)>0,MAX($P11,0),0)) -> 0 | T11: =IF($A11="","",IF(ROUND($P11,2)<0,"Supplier Credit",IF(ROUND($P11,2)=0,"Closed",IF($M11="","No Due Date",IF(N($R11)<=0,"Not Due Yet",IF(N($R11)<=Settings!$C$8,"1-30 Days Overdue",IF(N($R11)<=Settings!$C$9,"31-60 Days Overdue",IF(N($R11)<=Settings!$C$10,"61-90 Days Overdue","90+ Days Overdue")))))))) -> Closed | U11: =IF($A11="","",IF(COUNTIFS('Payments Log'!$B$8:$B$207,$A11)=0,"",SUMPRODUCT(MAX(('Payments Log'!$B$8:$B$207=$A11)*'Payments Log'!$E$8:$E$207)))) -> 46107 | V11: =IF($A11="","",IF($J11="","Not Delivered",IF($I11="","No Target Date",IF($J11<=$I11,"On Time","Late")))) -> On Time | W11: =IF($A11="","",IF($X11="","OK","REVIEW")) -> OK | X11: =IF($A11="","",TRIM(IF($B11="","Missing vendor ID. ","")&IF($C11="NOT FOUND","Vendor ID not in Vendor Master. ","")&IF(COUNTIFS('Invoice & Delivery Log'!$A$8:$A$157,$A11)>1,"Duplicate invoice ID. ","")&IF(AND($D11<>"",COUNTIFS('Invoice & Delivery Log'!$D$8:$D$157,$D11,'Invoice & Delivery Log'!$B$8:$B$157,$B11)>1),"Duplicate supplier invoice number. ","")&IF($E11="","Missing PO number. ","")&IF($H11="","Missing invoice date. ","")&IF(N($N11)<=0,"Invoice amount must be greater than zero. ","")&IF(AND($H11<>"",$H11>Settings!$C$5),"Invoice date is in the future. ","")&IF(AND($K11="Received in Full",$J11=""),"Missing actual delivery date. ","")&IF(ROUND(N($O11)-N($N11),2)>0,"Payments exceed the invoice amount. ","")&IF(AND($K11="Rejected",N($O11)>0),"Payment made on a rejected delivery. ","")&IF(AND($B11<>"",IFERROR(INDEX('Vendor Master'!$H$8:$H$47,MATCH($B11,'Vendor Master'!$A$8:$A$47,0)),"")="Inactive",ROUND(N($P11),2)>0),"Open balance with an inactive vendor. ",""))) | Y11: =IF($A11="","",IF(ROUND($P11,2)>0.004,"Yes","No")) -> No | Z11: =IF(OR($Y11<>"Yes",$M11=""),"",COUNTIFS('Invoice & Delivery Log'!$Y$8:$Y$157,"Yes",'Invoice & Delivery Log'!$M$8:$M$157,"<"&$M11)+COUNTIFS('Invoice & Delivery Log'!$Y$8:$Y$157,"Yes",'Invoice & Delivery Log'!$M$8:$M$157,$M11,'Invoice & Delivery Log'!$A$8:$A$157,"<"&$A11)+1)
A12: INV-1005 | B12: VEN-006 | C12: =IF($B12="","",IFERROR(INDEX('Vendor Master'!$B$8:$B$47,MATCH($B12,'Vendor Master'!$A$8:$A$47,0)),"NOT FOUND")) -> Harborline Logistics | D12: HLL-2026003 | E12: PO-2026-0005 | F12: =IF($B12="","",IFERROR(INDEX('Vendor Master'!$C$8:$C$47,MATCH($B12,'Vendor Master'!$A$8:$A$47,0)),"")) -> Logistics | G12: Warehouse transfer | H12: 46094 | I12: 46094 | J12: 46094 | K12: Received in Full | L12: =IF($B12="","",IFERROR(INDEX('Vendor Master'!$G$8:$G$47,MATCH($B12,'Vendor Master'!$A$8:$A$47,0)),"")) -> 30 | M12: =IF(OR($H12="",$L12=""),"",$H12+$L12) -> 46124 | N12: 4496.18 | O12: =IF($A12="","",SUMIFS('Payments Log'!$F$8:$F$207,'Payments Log'!$B$8:$B$207,$A12)) -> 4496.18 | P12: =IF($A12="","",ROUND($N12-$O12,2)) -> 0 | Q12: =IF($A12="","",IF(N($N12)<=0,"Check Amount",IF(ROUND($O12,2)<=0,"Unpaid",IF(ROUND($O12-$N12,2)>0,"Overpaid",IF(ROUND($P12,2)<=0,"Paid","Partially Paid"))))) -> Paid | R12: =IF(OR($A12="",$M12=""),"",IF(ROUND($P12,2)<=0,0,MAX(0,Settings!$C$5-$M12-Settings!$C$7))) -> 0 | S12: =IF($A12="","",IF(N($R12)>0,MAX($P12,0),0)) -> 0 | T12: =IF($A12="","",IF(ROUND($P12,2)<0,"Supplier Credit",IF(ROUND($P12,2)=0,"Closed",IF($M12="","No Due Date",IF(N($R12)<=0,"Not Due Yet",IF(N($R12)<=Settings!$C$8,"1-30 Days Overdue",IF(N($R12)<=Settings!$C$9,"31-60 Days Overdue",IF(N($R12)<=Settings!$C$10,"61-90 Days Overdue","90+ Days Overdue")))))))) -> Closed | U12: =IF($A12="","",IF(COUNTIFS('Payments Log'!$B$8:$B$207,$A12)=0,"",SUMPRODUCT(MAX(('Payments Log'!$B$8:$B$207=$A12)*'Payments Log'!$E$8:$E$207)))) -> 46117 | V12: =IF($A12="","",IF($J12="","Not Delivered",IF($I12="","No Target Date",IF($J12<=$I12,"On Time","Late")))) -> On Time | W12: =IF($A12="","",IF($X12="","OK","REVIEW")) -> OK | X12: =IF($A12="","",TRIM(IF($B12="","Missing vendor ID. ","")&IF($C12="NOT FOUND","Vendor ID not in Vendor Master. ","")&IF(COUNTIFS('Invoice & Delivery Log'!$A$8:$A$157,$A12)>1,"Duplicate invoice ID. ","")&IF(AND($D12<>"",COUNTIFS('Invoice & Delivery Log'!$D$8:$D$157,$D12,'Invoice & Delivery Log'!$B$8:$B$157,$B12)>1),"Duplicate supplier invoice number. ","")&IF($E12="","Missing PO number. ","")&IF($H12="","Missing invoice date. ","")&IF(N($N12)<=0,"Invoice amount must be greater than zero. ","")&IF(AND($H12<>"",$H12>Settings!$C$5),"Invoice date is in the future. ","")&IF(AND($K12="Received in Full",$J12=""),"Missing actual delivery date. ","")&IF(ROUND(N($O12)-N($N12),2)>0,"Payments exceed the invoice amount. ","")&IF(AND($K12="Rejected",N($O12)>0),"Payment made on a rejected delivery. ","")&IF(AND($B12<>"",IFERROR(INDEX('Vendor Master'!$H$8:$H$47,MATCH($B12,'Vendor Master'!$A$8:$A$47,0)),"")="Inactive",ROUND(N($P12),2)>0),"Open balance with an inactive vendor. ",""))) | Y12: =IF($A12="","",IF(ROUND($P12,2)>0.004,"Yes","No")) -> No | Z12: =IF(OR($Y12<>"Yes",$M12=""),"",COUNTIFS('Invoice & Delivery Log'!$Y$8:$Y$157,"Yes",'Invoice & Delivery Log'!$M$8:$M$157,"<"&$M12)+COUNTIFS('Invoice & Delivery Log'!$Y$8:$Y$157,"Yes",'Invoice & Delivery Log'!$M$8:$M$157,$M12,'Invoice & Delivery Log'!$A$8:$A$157,"<"&$A12)+1)
A13: INV-1006 | B13: VEN-005 | C13: =IF($B13="","",IFERROR(INDEX('Vendor Master'!$B$8:$B$47,MATCH($B13,'Vendor Master'!$A$8:$A$47,0)),"NOT FOUND")) -> Summit Cleaning Services | D13: SCS-2026001 | E13: PO-2026-0006 | F13: =IF($B13="","",IFERROR(INDEX('Vendor Master'!$C$8:$C$47,MATCH($B13,'Vendor Master'!$A$8:$A$47,0)),"")) -> Facility Services | G13: Deep clean - warehouse | H13: 46095 | I13: 46095 | J13: 46095 | K13: Received in Full | L13: =IF($B13="","",IFERROR(INDEX('Vendor Master'!$G$8:$G$47,MATCH($B13,'Vendor Master'!$A$8:$A$47,0)),"")) -> 14 | M13: =IF(OR($H13="",$L13=""),"",$H13+$L13) -> 46109 | N13: 1677.01 | O13: =IF($A13="","",SUMIFS('Payments Log'!$F$8:$F$207,'Payments Log'!$B$8:$B$207,$A13)) -> 1677.01 | P13: =IF($A13="","",ROUND($N13-$O13,2)) -> 0 | Q13: =IF($A13="","",IF(N($N13)<=0,"Check Amount",IF(ROUND($O13,2)<=0,"Unpaid",IF(ROUND($O13-$N13,2)>0,"Overpaid",IF(ROUND($P13,2)<=0,"Paid","Partially Paid"))))) -> Paid | R13: =IF(OR($A13="",$M13=""),"",IF(ROUND($P13,2)<=0,0,MAX(0,Settings!$C$5-$M13-Settings!$C$7))) -> 0 | S13: =IF($A13="","",IF(N($R13)>0,MAX($P13,0),0)) -> 0 | T13: =IF($A13="","",IF(ROUND($P13,2)<0,"Supplier Credit",IF(ROUND($P13,2)=0,"Closed",IF($M13="","No Due Date",IF(N($R13)<=0,"Not Due Yet",IF(N($R13)<=Settings!$C$8,"1-30 Days Overdue",IF(N($R13)<=Settings!$C$9,"31-60 Days Overdue",IF(N($R13)<=Settings!$C$10,"61-90 Days Overdue","90+ Days Overdue")))))))) -> Closed | U13: =IF($A13="","",IF(COUNTIFS('Payments Log'!$B$8:$B$207,$A13)=0,"",SUMPRODUCT(MAX(('Payments Log'!$B$8:$B$207=$A13)*'Payments Log'!$E$8:$E$207)))) -> 46106 | V13: =IF($A13="","",IF($J13="","Not Delivered",IF($I13="","No Target Date",IF($J13<=$I13,"On Time","Late")))) -> On Time | W13: =IF($A13="","",IF($X13="","OK","REVIEW")) -> OK | X13: =IF($A13="","",TRIM(IF($B13="","Missing vendor ID. ","")&IF($C13="NOT FOUND","Vendor ID not in Vendor Master. ","")&IF(COUNTIFS('Invoice & Delivery Log'!$A$8:$A$157,$A13)>1,"Duplicate invoice ID. ","")&IF(AND($D13<>"",COUNTIFS('Invoice & Delivery Log'!$D$8:$D$157,$D13,'Invoice & Delivery Log'!$B$8:$B$157,$B13)>1),"Duplicate supplier invoice number. ","")&IF($E13="","Missing PO number. ","")&IF($H13="","Missing invoice date. ","")&IF(N($N13)<=0,"Invoice amount must be greater than zero. ","")&IF(AND($H13<>"",$H13>Settings!$C$5),"Invoice date is in the future. ","")&IF(AND($K13="Received in Full",$J13=""),"Missing actual delivery date. ","")&IF(ROUND(N($O13)-N($N13),2)>0,"Payments exceed the invoice amount. ","")&IF(AND($K13="Rejected",N($O13)>0),"Payment made on a rejected delivery. ","")&IF(AND($B13<>"",IFERROR(INDEX('Vendor Master'!$H$8:$H$47,MATCH($B13,'Vendor Master'!$A$8:$A$47,0)),"")="Inactive",ROUND(N($P13),2)>0),"Open balance with an inactive vendor. ",""))) | Y13: =IF($A13="","",IF(ROUND($P13,2)>0.004,"Yes","No")) -> No | Z13: =IF(OR($Y13<>"Yes",$M13=""),"",COUNTIFS('Invoice & Delivery Log'!$Y$8:$Y$157,"Yes",'Invoice & Delivery Log'!$M$8:$M$157,"<"&$M13)+COUNTIFS('Invoice & Delivery Log'!$Y$8:$Y$157,"Yes",'Invoice & Delivery Log'!$M$8:$M$157,$M13,'Invoice & Delivery Log'!$A$8:$A$157,"<"&$A13)+1)
A14: INV-1007 | B14: VEN-012 | C14: =IF($B14="","",IFERROR(INDEX('Vendor Master'!$B$8:$B$47,MATCH($B14,'Vendor Master'!$A$8:$A$47,0)),"NOT FOUND")) -> Willowbrook Beverage Co. | D14: WBC-2026001 | E14: PO-2026-0007 | F14: =IF($B14="","",IFERROR(INDEX('Vendor Master'!$C$8:$C$47,MATCH($B14,'Vendor Master'!$A$8:$A$47,0)),"")) -> Food & Beverage | G14: Bottled beverage restock | H14: 46099 | I14: 46097 | J14: 46096 | K14: Received in Full | L14: =IF($B14="","",IFERROR(INDEX('Vendor Master'!$G$8:$G$47,MATCH($B14,'Vendor Master'!$A$8:$A$47,0)),"")) -> 15 | M14: =IF(OR($H14="",$L14=""),"",$H14+$L14) -> 46114 | N14: 1812.63 | O14: =IF($A14="","",SUMIFS('Payments Log'!$F$8:$F$207,'Payments Log'!$B$8:$B$207,$A14)) -> 1812.63 | P14: =IF($A14="","",ROUND($N14-$O14,2)) -> 0 | Q14: =IF($A14="","",IF(N($N14)<=0,"Check Amount",IF(ROUND($O14,2)<=0,"Unpaid",IF(ROUND($O14-$N14,2)>0,"Overpaid",IF(ROUND($P14,2)<=0,"Paid","Partially Paid"))))) -> Paid | R14: =IF(OR($A14="",$M14=""),"",IF(ROUND($P14,2)<=0,0,MAX(0,Settings!$C$5-$M14-Settings!$C$7))) -> 0 | S14: =IF($A14="","",IF(N($R14)>0,MAX($P14,0),0)) -> 0 | T14: =IF($A14="","",IF(ROUND($P14,2)<0,"Supplier Credit",IF(ROUND($P14,2)=0,"Closed",IF($M14="","No Due Date",IF(N($R14)<=0,"Not Due Yet",IF(N($R14)<=Settings!$C$8,"1-30 Days Overdue",IF(N($R14)<=Settings!$C$9,"31-60 Days Overdue",IF(N($R14)<=Settings!$C$10,"61-90 Days Overdue","90+ Days Overdue")))))))) -> Closed | U14: =IF($A14="","",IF(COUNTIFS('Payments Log'!$B$8:$B$207,$A14)=0,"",SUMPRODUCT(MAX(('Payments Log'!$B$8:$B$207=$A14)*'Payments Log'!$E$8:$E$207)))) -> 46122 | V14: =IF($A14="","",IF($J14="","Not Delivered",IF($I14="","No Target Date",IF($J14<=$I14,"On Time","Late")))) -> On Time | W14: =IF($A14="","",IF($X14="","OK","REVIEW")) -> OK | X14: =IF($A14="","",TRIM(IF($B14="","Missing vendor ID. ","")&IF($C14="NOT FOUND","Vendor ID not in Vendor Master. ","")&IF(COUNTIFS('Invoice & Delivery Log'!$A$8:$A$157,$A14)>1,"Duplicate invoice ID. ","")&IF(AND($D14<>"",COUNTIFS('Invoice & Delivery Log'!$D$8:$D$157,$D14,'Invoice & Delivery Log'!$B$8:$B$157,$B14)>1),"Duplicate supplier invoice number. ","")&IF($E14="","Missing PO number. ","")&IF($H14="","Missing invoice date. ","")&IF(N($N14)<=0,"Invoice amount must be greater than zero. ","")&IF(AND($H14<>"",$H14>Settings!$C$5),"Invoice date is in the future. ","")&IF(AND($K14="Received in Full",$J14=""),"Missing actual delivery date. ","")&IF(ROUND(N($O14)-N($N14),2)>0,"Payments exceed the invoice amount. ","")&IF(AND($K14="Rejected",N($O14)>0),"Payment made on a rejected delivery. ","")&IF(AND($B14<>"",IFERROR(INDEX('Vendor Master'!$H$8:$H$47,MATCH($B14,'Vendor Master'!$A$8:$A$47,0)),"")="Inactive",ROUND(N($P14),2)>0),"Open balance with an inactive vendor. ",""))) | Y14: =IF($A14="","",IF(ROUND($P14,2)>0.004,"Yes","No")) -> No | Z14: =IF(OR($Y14<>"Yes",$M14=""),"",COUNTIFS('Invoice & Delivery Log'!$Y$8:$Y$157,"Yes",'Invoice & Delivery Log'!$M$8:$M$157,"<"&$M14)+COUNTIFS('Invoice & Delivery Log'!$Y$8:$Y$157,"Yes",'Invoice & Delivery Log'!$M$8:$M$157,$M14,'Invoice & Delivery Log'!$A$8:$A$157,"<"&$A14)+1)
A15: INV-1008 | B15: VEN-001 | C15: =IF($B15="","",IFERROR(INDEX('Vendor Master'!$B$8:$B$47,MATCH($B15,'Vendor Master'!$A$8:$A$47,0)),"NOT FOUND")) -> Northwind Paper Supply | D15: NWP-2026001 | E15: PO-2026-0008 | F15: =IF($B15="","",IFERROR(INDEX('Vendor Master'!$C$8:$C$47,MATCH($B15,'Vendor Master'!$A$8:$A$47,0)),"")) -> Office Supplies | G15: Printer consumables | H15: 46101 | I15: 46098 | J15: 46098 | K15: Received in Full | L15: =IF($B15="","",IFERROR(INDEX('Vendor Master'!$G$8:$G$47,MATCH($B15,'Vendor Master'!$A$8:$A$47,0)),"")) -> 30 | M15: =IF(OR($H15="",$L15=""),"",$H15+$L15) -> 46131 | N15: 1767.46 | O15: =IF($A15="","",SUMIFS('Payments Log'!$F$8:$F$207,'Payments Log'!$B$8:$B$207,$A15)) -> 1767.46 | P15: =IF($A15="","",ROUND($N15-$O15,2)) -> 0 | Q15: =IF($A15="","",IF(N($N15)<=0,"Check Amount",IF(ROUND($O15,2)<=0,"Unpaid",IF(ROUND($O15-$N15,2)>0,"Overpaid",IF(ROUND($P15,2)<=0,"Paid","Partially Paid"))))) -> Paid | R15: =IF(OR($A15="",$M15=""),"",IF(ROUND($P15,2)<=0,0,MAX(0,Settings!$C$5-$M15-Settings!$C$7))) -> 0 | S15: =IF($A15="","",IF(N($R15)>0,MAX($P15,0),0)) -> 0 | T15: =IF($A15="","",IF(ROUND($P15,2)<0,"Supplier Credit",IF(ROUND($P15,2)=0,"Closed",IF($M15="","No Due Date",IF(N($R15)<=0,"Not Due Yet",IF(N($R15)<=Settings!$C$8,"1-30 Days Overdue",IF(N($R15)<=Settings!$C$9,"31-60 Days Overdue",IF(N($R15)<=Settings!$C$10,"61-90 Days Overdue","90+ Days Overdue")))))))) -> Closed | U15: =IF($A15="","",IF(COUNTIFS('Payments Log'!$B$8:$B$207,$A15)=0,"",SUMPRODUCT(MAX(('Payments Log'!$B$8:$B$207=$A15)*'Payments Log'!$E$8:$E$207)))) -> 46131 | V15: =IF($A15="","",IF($J15="","Not Delivered",IF($I15="","No Target Date",IF($J15<=$I15,"On Time","Late")))) -> On Time | W15: =IF($A15="","",IF($X15="","OK","REVIEW")) -> OK | X15: =IF($A15="","",TRIM(IF($B15="","Missing vendor ID. ","")&IF($C15="NOT FOUND","Vendor ID not in Vendor Master. ","")&IF(COUNTIFS('Invoice & Delivery Log'!$A$8:$A$157,$A15)>1,"Duplicate invoice ID. ","")&IF(AND($D15<>"",COUNTIFS('Invoice & Delivery Log'!$D$8:$D$157,$D15,'Invoice & Delivery Log'!$B$8:$B$157,$B15)>1),"Duplicate supplier invoice number. ","")&IF($E15="","Missing PO number. ","")&IF($H15="","Missing invoice date. ","")&IF(N($N15)<=0,"Invoice amount must be greater than zero. ","")&IF(AND($H15<>"",$H15>Settings!$C$5),"Invoice date is in the future. ","")&IF(AND($K15="Received in Full",$J15=""),"Missing actual delivery date. ","")&IF(ROUND(N($O15)-N($N15),2)>0,"Payments exceed the invoice amount. ","")&IF(AND($K15="Rejected",N($O15)>0),"Payment made on a rejected delivery. ","")&IF(AND($B15<>"",IFERROR(INDEX('Vendor Master'!$H$8:$H$47,MATCH($B15,'Vendor Master'!$A$8:$A$47,0)),"")="Inactive",ROUND(N($P15),2)>0),"Open balance with an inactive vendor. ",""))) | Y15: =IF($A15="","",IF(ROUND($P15,2)>0.004,"Yes","No")) -> No | Z15: =IF(OR($Y15<>"Yes",$M15=""),"",COUNTIFS('Invoice & Delivery Log'!$Y$8:$Y$157,"Yes",'Invoice & Delivery Log'!$M$8:$M$157,"<"&$M15)+COUNTIFS('Invoice & Delivery Log'!$Y$8:$Y$157,"Yes",'Invoice & Delivery Log'!$M$8:$M$157,$M15,'Invoice & Delivery Log'!$A$8:$A$157,"<"&$A15)+1)
A16: INV-1009 | B16: VEN-011 | C16: =IF($B16="","",IFERROR(INDEX('Vendor Master'!$B$8:$B$47,MATCH($B16,'Vendor Master'!$A$8:$A$47,0)),"NOT FOUND")) -> Redstone Safety Equipment | D16: RSE-2026001 | E16: PO-2026-0009 | F16: =IF($B16="","",IFERROR(INDEX('Vendor Master'!$C$8:$C$47,MATCH($B16,'Vendor Master'!$A$8:$A$47,0)),"")) -> Safety & PPE | G16: First aid restock | H16: 46106 | I16: 46105 | J16: 46105 | K16: Received in Full | L16: =IF($B16="","",IFERROR(INDEX('Vendor Master'!$G$8:$G$47,MATCH($B16,'Vendor Master'!$A$8:$A$47,0)),"")) -> 30 | M16: =IF(OR($H16="",$L16=""),"",$H16+$L16) -> 46136 | N16: 2891.99 | O16: =IF($A16="","",SUMIFS('Payments Log'!$F$8:$F$207,'Payments Log'!$B$8:$B$207,$A16)) -> 2891.99 | P16: =IF($A16="","",ROUND($N16-$O16,2)) -> 0 | Q16: =IF($A16="","",IF(N($N16)<=0,"Check Amount",IF(ROUND($O16,2)<=0,"Unpaid",IF(ROUND($O16-$N16,2)>0,"Overpaid",IF(ROUND($P16,2)<=0,"Paid","Partially Paid"))))) -> Paid | R16: =IF(OR($A16="",$M16=""),"",IF(ROUND($P16,2)<=0,0,MAX(0,Settings!$C$5-$M16-Settings!$C$7))) -> 0 | S16: =IF($A16="","",IF(N($R16)>0,MAX($P16,0),0)) -> 0 | T16: =IF($A16="","",IF(ROUND($P16,2)<0,"Supplier Credit",IF(ROUND($P16,2)=0,"Closed",IF($M16="","No Due Date",IF(N($R16)<=0,"Not Due Yet",IF(N($R16)<=Settings!$C$8,"1-30 Days Overdue",IF(N($R16)<=Settings!$C$9,"31-60 Days Overdue",IF(N($R16)<=Settings!$C$10,"61-90 Days Overdue","90+ Days Overdue")))))))) -> Closed | U16: =IF($A16="","",IF(COUNTIFS('Payments Log'!$B$8:$B$207,$A16)=0,"",SUMPRODUCT(MAX(('Payments Log'!$B$8:$B$207=$A16)*'Payments Log'!$E$8:$E$207)))) -> 46119 | V16: =IF($A16="","",IF($J16="","Not Delivered",IF($I16="","No Target Date",IF($J16<=$I16,"On Time","Late")))) -> On Time | W16: =IF($A16="","",IF($X16="","OK","REVIEW")) -> OK | X16: =IF($A16="","",TRIM(IF($B16="","Missing vendor ID. ","")&IF($C16="NOT FOUND","Vendor ID not in Vendor Master. ","")&IF(COUNTIFS('Invoice & Delivery Log'!$A$8:$A$157,$A16)>1,"Duplicate invoice ID. ","")&IF(AND($D16<>"",COUNTIFS('Invoice & Delivery Log'!$D$8:$D$157,$D16,'Invoice & Delivery Log'!$B$8:$B$157,$B16)>1),"Duplicate supplier invoice number. ","")&IF($E16="","Missing PO number. ","")&IF($H16="","Missing invoice date. ","")&IF(N($N16)<=0,"Invoice amount must be greater than zero. ","")&IF(AND($H16<>"",$H16>Settings!$C$5),"Invoice date is in the future. ","")&IF(AND($K16="Received in Full",$J16=""),"Missing actual delivery date. ","")&IF(ROUND(N($O16)-N($N16),2)>0,"Payments exceed the invoice amount. ","")&IF(AND($K16="Rejected",N($O16)>0),"Payment made on a rejected delivery. ","")&IF(AND($B16<>"",IFERROR(INDEX('Vendor Master'!$H$8:$H$47,MATCH($B16,'Vendor Master'!$A$8:$A$47,0)),"")="Inactive",ROUND(N($P16),2)>0),"Open balance with an inactive vendor. ",""))) | Y16: =IF($A16="","",IF(ROUND($P16,2)>0.004,"Yes","No")) -> No | Z16: =IF(OR($Y16<>"Yes",$M16=""),"",COUNTIFS('Invoice & Delivery Log'!$Y$8:$Y$157,"Yes",'Invoice & Delivery Log'!$M$8:$M$157,"<"&$M16)+COUNTIFS('Invoice & Delivery Log'!$Y$8:$Y$157,"Yes",'Invoice & Delivery Log'!$M$8:$M$157,$M16,'Invoice & Delivery Log'!$A$8:$A$157,"<"&$A16)+1)
A17: INV-1010 | B17: VEN-010 | C17: =IF($B17="","",IFERROR(INDEX('Vendor Master'!$B$8:$B$47,MATCH($B17,'Vendor Master'!$A$8:$A$47,0)),"NOT FOUND")) -> Copperfield Textiles | D17: CFT-2026002 | E17: PO-2026-0010 | F17: =IF($B17="","",IFERROR(INDEX('Vendor Master'!$C$8:$C$47,MATCH($B17,'Vendor Master'!$A$8:$A$47,0)),"")) -> Textiles | G17: Uniform fabric order | H17: 46107 | I17: 46106 | J17: 46106 | K17: Rejected | L17: =IF($B17="","",IFERROR(INDEX('Vendor Master'!$G$8:$G$47,MATCH($B17,'Vendor Master'!$A$8:$A$47,0)),"")) -> 60 | M17: =IF(OR($H17="",$L17=""),"",$H17+$L17) -> 46167 | N17: 9042.96 | O17: =IF($A17="","",SUMIFS('Payments Log'!$F$8:$F$207,'Payments Log'!$B$8:$B$207,$A17)) -> 0 | P17: =IF($A17="","",ROUND($N17-$O17,2)) -> 9042.96 | Q17: =IF($A17="","",IF(N($N17)<=0,"Check Amount",IF(ROUND($O17,2)<=0,"Unpaid",IF(ROUND($O17-$N17,2)>0,"Overpaid",IF(ROUND($P17,2)<=0,"Paid","Partially Paid"))))) -> Unpaid | R17: =IF(OR($A17="",$M17=""),"",IF(ROUND($P17,2)<=0,0,MAX(0,Settings!$C$5-$M17-Settings!$C$7))) -> 105 | S17: =IF($A17="","",IF(N($R17)>0,MAX($P17,0),0)) -> 9042.96 | T17: =IF($A17="","",IF(ROUND($P17,2)<0,"Supplier Credit",IF(ROUND($P17,2)=0,"Closed",IF($M17="","No Due Date",IF(N($R17)<=0,"Not Due Yet",IF(N($R17)<=Settings!$C$8,"1-30 Days Overdue",IF(N($R17)<=Settings!$C$9,"31-60 Days Overdue",IF(N($R17)<=Settings!$C$10,"61-90 Days Overdue","90+ Days Overdue")))))))) -> 90+ Days Overdue | U17: =IF($A17="","",IF(COUNTIFS('Payments Log'!$B$8:$B$207,$A17)=0,"",SUMPRODUCT(MAX(('Payments Log'!$B$8:$B$207=$A17)*'Payments Log'!$E$8:$E$207)))) | V17: =IF($A17="","",IF($J17="","Not Delivered",IF($I17="","No Target Date",IF($J17<=$I17,"On Time","Late")))) -> On Time | W17: =IF($A17="","",IF($X17="","OK","REVIEW")) -> OK | X17: =IF($A17="","",TRIM(IF($B17="","Missing vendor ID. ","")&IF($C17="NOT FOUND","Vendor ID not in Vendor Master. ","")&IF(COUNTIFS('Invoice & Delivery Log'!$A$8:$A$157,$A17)>1,"Duplicate invoice ID. ","")&IF(AND($D17<>"",COUNTIFS('Invoice & Delivery Log'!$D$8:$D$157,$D17,'Invoice & Delivery Log'!$B$8:$B$157,$B17)>1),"Duplicate supplier invoice number. ","")&IF($E17="","Missing PO number. ","")&IF($H17="","Missing invoice date. ","")&IF(N($N17)<=0,"Invoice amount must be greater than zero. ","")&IF(AND($H17<>"",$H17>Settings!$C$5),"Invoice date is in the future. ","")&IF(AND($K17="Received in Full",$J17=""),"Missing actual delivery date. ","")&IF(ROUND(N($O17)-N($N17),2)>0,"Payments exceed the invoice amount. ","")&IF(AND($K17="Rejected",N($O17)>0),"Payment made on a rejected delivery. ","")&IF(AND($B17<>"",IFERROR(INDEX('Vendor Master'!$H$8:$H$47,MATCH($B17,'Vendor Master'!$A$8:$A$47,0)),"")="Inactive",ROUND(N($P17),2)>0),"Open balance with an inactive vendor. ",""))) | Y17: =IF($A17="","",IF(ROUND($P17,2)>0.004,"Yes","No")) -> Yes | Z17: =IF(OR($Y17<>"Yes",$M17=""),"",COUNTIFS('Invoice & Delivery Log'!$Y$8:$Y$157,"Yes",'Invoice & Delivery Log'!$M$8:$M$157,"<"&$M17)+COUNTIFS('Invoice & Delivery Log'!$Y$8:$Y$157,"Yes",'Invoice & Delivery Log'!$M$8:$M$157,$M17,'Invoice & Delivery Log'!$A$8:$A$157,"<"&$A17)+1) -> 3
A18: INV-1011 | B18: VEN-006 | C18: =IF($B18="","",IFERROR(INDEX('Vendor Master'!$B$8:$B$47,MATCH($B18,'Vendor Master'!$A$8:$A$47,0)),"NOT FOUND")) -> Harborline Logistics | D18: HLL-2026004 | E18: PO-2026-0011 | F18: =IF($B18="","",IFERROR(INDEX('Vendor Master'!$C$8:$C$47,MATCH($B18,'Vendor Master'!$A$8:$A$47,0)),"")) -> Logistics | G18: Warehouse transfer | H18: 46106 | I18: 46106 | J18: 46106 | K18: Received in Full | L18: =IF($B18="","",IFERROR(INDEX('Vendor Master'!$G$8:$G$47,MATCH($B18,'Vendor Master'!$A$8:$A$47,0)),"")) -> 30 | M18: =IF(OR($H18="",$L18=""),"",$H18+$L18) -> 46136 | N18: 3312.21 | O18: =IF($A18="","",SUMIFS('Payments Log'!$F$8:$F$207,'Payments Log'!$B$8:$B$207,$A18)) -> 3312.21 | P18: =IF($A18="","",ROUND($N18-$O18,2)) -> 0 | Q18: =IF($A18="","",IF(N($N18)<=0,"Check Amount",IF(ROUND($O18,2)<=0,"Unpaid",IF(ROUND($O18-$N18,2)>0,"Overpaid",IF(ROUND($P18,2)<=0,"Paid","Partially Paid"))))) -> Paid | R18: =IF(OR($A18="",$M18=""),"",IF(ROUND($P18,2)<=0,0,MAX(0,Settings!$C$5-$M18-Settings!$C$7))) -> 0 | S18: =IF($A18="","",IF(N($R18)>0,MAX($P18,0),0)) -> 0 | T18: =IF($A18="","",IF(ROUND($P18,2)<0,"Supplier Credit",IF(ROUND($P18,2)=0,"Closed",IF($M18="","No Due Date",IF(N($R18)<=0,"Not Due Yet",IF(N($R18)<=Settings!$C$8,"1-30 Days Overdue",IF(N($R18)<=Settings!$C$9,"31-60 Days Overdue",IF(N($R18)<=Settings!$C$10,"61-90 Days Overdue","90+ Days Overdue")))))))) -> Closed | U18: =IF($A18="","",IF(COUNTIFS('Payments Log'!$B$8:$B$207,$A18)=0,"",SUMPRODUCT(MAX(('Payments Log'!$B$8:$B$207=$A18)*'Payments Log'!$E$8:$E$207)))) -> 46149 | V18: =IF($A18="","",IF($J18="","Not Delivered",IF($I18="","No Target Date",IF($J18<=$I18,"On Time","Late")))) -> On Time | W18: =IF($A18="","",IF($X18="","OK","REVIEW")) -> OK | X18: =IF($A18="","",TRIM(IF($B18="","Missing vendor ID. ","")&IF($C18="NOT FOUND","Vendor ID not in Vendor Master. ","")&IF(COUNTIFS('Invoice & Delivery Log'!$A$8:$A$157,$A18)>1,"Duplicate invoice ID. ","")&IF(AND($D18<>"",COUNTIFS('Invoice & Delivery Log'!$D$8:$D$157,$D18,'Invoice & Delivery Log'!$B$8:$B$157,$B18)>1),"Duplicate supplier invoice number. ","")&IF($E18="","Missing PO number. ","")&IF($H18="","Missing invoice date. ","")&IF(N($N18)<=0,"Invoice amount must be greater than zero. ","")&IF(AND($H18<>"",$H18>Settings!$C$5),"Invoice date is in the future. ","")&IF(AND($K18="Received in Full",$J18=""),"Missing actual delivery date. ","")&IF(ROUND(N($O18)-N($N18),2)>0,"Payments exceed the invoice amount. ","")&IF(AND($K18="Rejected",N($O18)>0),"Payment made on a rejected delivery. ","")&IF(AND($B18<>"",IFERROR(INDEX('Vendor Master'!$H$8:$H$47,MATCH($B18,'Vendor Master'!$A$8:$A$47,0)),"")="Inactive",ROUND(N($P18),2)>0),"Open balance with an inactive vendor. ",""))) | Y18: =IF($A18="","",IF(ROUND($P18,2)>0.004,"Yes","No")) -> No | Z18: =IF(OR($Y18<>"Yes",$M18=""),"",COUNTIFS('Invoice & Delivery Log'!$Y$8:$Y$157,"Yes",'Invoice & Delivery Log'!$M$8:$M$157,"<"&$M18)+COUNTIFS('Invoice & Delivery Log'!$Y$8:$Y$157,"Yes",'Invoice & Delivery Log'!$M$8:$M$157,$M18,'Invoice & Delivery Log'!$A$8:$A$157,"<"&$A18)+1)
A19: INV-1012 | B19: VEN-005 | C19: =IF($B19="","",IFERROR(INDEX('Vendor Master'!$B$8:$B$47,MATCH($B19,'Vendor Master'!$A$8:$A$47,0)),"NOT FOUND")) -> Summit Cleaning Services | D19: SCS-2026002 | E19: PO-2026-0012 | F19: =IF($B19="","",IFERROR(INDEX('Vendor Master'!$C$8:$C$47,MATCH($B19,'Vendor Master'!$A$8:$A$47,0)),"")) -> Facility Services | G19: Sanitation supplies | H19: 46115 | I19: 46107 | J19: 46112 | K19: Received in Full | L19: =IF($B19="","",IFERROR(INDEX('Vendor Master'!$G$8:$G$47,MATCH($B19,'Vendor Master'!$A$8:$A$47,0)),"")) -> 14 | M19: =IF(OR($H19="",$L19=""),"",$H19+$L19) -> 46129 | N19: 1754.8 | O19: =IF($A19="","",SUMIFS('Payments Log'!$F$8:$F$207,'Payments Log'!$B$8:$B$207,$A19)) -> 1754.8 | P19: =IF($A19="","",ROUND($N19-$O19,2)) -> 0 | Q19: =IF($A19="","",IF(N($N19)<=0,"Check Amount",IF(ROUND($O19,2)<=0,"Unpaid",IF(ROUND($O19-$N19,2)>0,"Overpaid",IF(ROUND($P19,2)<=0,"Paid","Partially Paid"))))) -> Paid | R19: =IF(OR($A19="",$M19=""),"",IF(ROUND($P19,2)<=0,0,MAX(0,Settings!$C$5-$M19-Settings!$C$7))) -> 0 | S19: =IF($A19="","",IF(N($R19)>0,MAX($P19,0),0)) -> 0 | T19: =IF($A19="","",IF(ROUND($P19,2)<0,"Supplier Credit",IF(ROUND($P19,2)=0,"Closed",IF($M19="","No Due Date",IF(N($R19)<=0,"Not Due Yet",IF(N($R19)<=Settings!$C$8,"1-30 Days Overdue",IF(N($R19)<=Settings!$C$9,"31-60 Days Overdue",IF(N($R19)<=Settings!$C$10,"61-90 Days Overdue","90+ Days Overdue")))))))) -> Closed | U19: =IF($A19="","",IF(COUNTIFS('Payments Log'!$B$8:$B$207,$A19)=0,"",SUMPRODUCT(MAX(('Payments Log'!$B$8:$B$207=$A19)*'Payments Log'!$E$8:$E$207)))) -> 46140 | V19: =IF($A19="","",IF($J19="","Not Delivered",IF($I19="","No Target Date",IF($J19<=$I19,"On Time","Late")))) -> Late | W19: =IF($A19="","",IF($X19="","OK","REVIEW")) -> OK | X19: =IF($A19="","",TRIM(IF($B19="","Missing vendor ID. ","")&IF($C19="NOT FOUND","Vendor ID not in Vendor Master. ","")&IF(COUNTIFS('Invoice & Delivery Log'!$A$8:$A$157,$A19)>1,"Duplicate invoice ID. ","")&IF(AND($D19<>"",COUNTIFS('Invoice & Delivery Log'!$D$8:$D$157,$D19,'Invoice & Delivery Log'!$B$8:$B$157,$B19)>1),"Duplicate supplier invoice number. ","")&IF($E19="","Missing PO number. ","")&IF($H19="","Missing invoice date. ","")&IF(N($N19)<=0,"Invoice amount must be greater than zero. ","")&IF(AND($H19<>"",$H19>Settings!$C$5),"Invoice date is in the future. ","")&IF(AND($K19="Received in Full",$J19=""),"Missing actual delivery date. ","")&IF(ROUND(N($O19)-N($N19),2)>0,"Payments exceed the invoice amount. ","")&IF(AND($K19="Rejected",N($O19)>0),"Payment made on a rejected delivery. ","")&IF(AND($B19<>"",IFERROR(INDEX('Vendor Master'!$H$8:$H$47,MATCH($B19,'Vendor Master'!$A$8:$A$47,0)),"")="Inactive",ROUND(N($P19),2)>0),"Open balance with an inactive vendor. ",""))) | Y19: =IF($A19="","",IF(ROUND($P19,2)>0.004,"Yes","No")) -> No | Z19: =IF(OR($Y19<>"Yes",$M19=""),"",COUNTIFS('Invoice & Delivery Log'!$Y$8:$Y$157,"Yes",'Invoice & Delivery Log'!$M$8:$M$157,"<"&$M19)+COUNTIFS('Invoice & Delivery Log'!$Y$8:$Y$157,"Yes",'Invoice & Delivery Log'!$M$8:$M$157,$M19,'Invoice & Delivery Log'!$A$8:$A$157,"<"&$A19)+1)
... A24: INV-1017 | B24: VEN-009 | C24: =IF($B24="","",IFERROR(INDEX('Vendor Master'!$B$8:$B$47,MATCH($B24,'Vendor Master'!$A$8:$A$47,0)),"NOT FOUND")) -> Vertex IT Solutions | D24: VIT-2026002 | E24: PO-2026-0017 | F24: =IF($B24="","",IFERROR(INDEX('Vendor Master'!$C$8:$C$47,MATCH($B24,'Vendor Master'!$A$8:$A$47,0)),"")) -> IT & Software | G24: IT support retainer | H24: 46116 | I24: 46114 | J24: 46114 | K24: Received in Full | L24: =IF($B24="","",IFERROR(INDEX('Vendor Master'!$G$8:$G$47,MATCH($B24,'Vendor Master'!$A$8:$A$47,0)),"")) -> 30 | M24: =IF(OR($H24="",$L24=""),"",$H24+$L24) -> 46146 | N24: 9228.89 | O24: =IF($A24="","",SUMIFS('Payments Log'!$F$8:$F$207,'Payments Log'!$B$8:$B$207,$A24)) -> 9228.89 | P24: =IF($A24="","",ROUND($N24-$O24,2)) -> 0 | Q24: =IF($A24="","",IF(N($N24)<=0,"Check Amount",IF(ROUND($O24,2)<=0,"Unpaid",IF(ROUND($O24-$N24,2)>0,"Overpaid",IF(ROUND($P24,2)<=0,"Paid","Partially Paid"))))) -> Paid | R24: =IF(OR($A24="",$M24=""),"",IF(ROUND($P24,2)<=0,0,MAX(0,Settings!$C$5-$M24-Settings!$C$7))) -> 0 | S24: =IF($A24="","",IF(N($R24)>0,MAX($P24,0),0)) -> 0 | T24: =IF($A24="","",IF(ROUND($P24,2)<0,"Supplier Credit",IF(ROUND($P24,2)=0,"Closed",IF($M24="","No Due Date",IF(N($R24)<=0,"Not Due Yet",IF(N($R24)<=Settings!$C$8,"1-30 Days Overdue",IF(N($R24)<=Settings!$C$9,"31-60 Days Overdue",IF(N($R24)<=Settings!$C$10,"61-90 Days Overdue","90+ Days Overdue")))))))) -> Closed | U24: =IF($A24="","",IF(COUNTIFS('Payments Log'!$B$8:$B$207,$A24)=0,"",SUMPRODUCT(MAX(('Payments Log'!$B$8:$B$207=$A24)*'Payments Log'!$E$8:$E$207)))) -> 46136 | V24: =IF($A24="","",IF($J24="","Not Delivered",IF($I24="","No Target Date",IF($J24<=$I24,"On Time","Late")))) -> On Time | W24: =IF($A24="","",IF($X24="","OK","REVIEW")) -> OK | X24: =IF($A24="","",TRIM(IF($B24="","Missing vendor ID. ","")&IF($C24="NOT FOUND","Vendor ID not in Vendor Master. ","")&IF(COUNTIFS('Invoice & Delivery Log'!$A$8:$A$157,$A24)>1,"Duplicate invoice ID. ","")&IF(AND($D24<>"",COUNTIFS('Invoice & Delivery Log'!$D$8:$D$157,$D24,'Invoice & Delivery Log'!$B$8:$B$157,$B24)>1),"Duplicate supplier invoice number. ","")&IF($E24="","Missing PO number. ","")&IF($H24="","Missing invoice date. ","")&IF(N($N24)<=0,"Invoice amount must be greater than zero. ","")&IF(AND($H24<>"",$H24>Settings!$C$5),"Invoice date is in the future. ","")&IF(AND($K24="Received in Full",$J24=""),"Missing actual delivery date. ","")&IF(ROUND(N($O24)-N($N24),2)>0,"Payments exceed the invoice amount. ","")&IF(AND($K24="Rejected",N($O24)>0),"Payment made on a rejected delivery. ","")&IF(AND($B24<>"",IFERROR(INDEX('Vendor Master'!$H$8:$H$47,MATCH($B24,'Vendor Master'!$A$8:$A$47,0)),"")="Inactive",ROUND(N($P24),2)>0),"Open balance with an inactive vendor. ",""))) | Y24: =IF($A24="","",IF(ROUND($P24,2)>0.004,"Yes","No")) -> No | Z24: =IF(OR($Y24<>"Yes",$M24=""),"",COUNTIFS('Invoice & Delivery Log'!$Y$8:$Y$157,"Yes",'Invoice & Delivery Log'!$M$8:$M$157,"<"&$M24)+COUNTIFS('Invoice & Delivery Log'!$Y$8:$Y$157,"Yes",'Invoice & Delivery Log'!$M$8:$M$157,$M24,'Invoice & Delivery Log'!$A$8:$A$157,"<"&$A24)+1)
A25: INV-1018 | B25: VEN-002 | C25: =IF($B25="","",IFERROR(INDEX('Vendor Master'!$B$8:$B$47,MATCH($B25,'Vendor Master'!$A$8:$A$47,0)),"NOT FOUND")) -> Cascade Foods Distribution | D25: CFD-2026002 | F25: =IF($B25="","",IFERROR(INDEX('Vendor Master'!$C$8:$C$47,MATCH($B25,'Vendor Master'!$A$8:$A$47,0)),"")) -> Food & Beverage | G25: Fresh produce delivery | H25: 46120 | I25: 46115 | J25: 46119 | K25: Partially Received | L25: =IF($B25="","",IFERROR(INDEX('Vendor Master'!$G$8:$G$47,MATCH($B25,'Vendor Master'!$A$8:$A$47,0)),"")) -> 15 | M25: =IF(OR($H25="",$L25=""),"",$H25+$L25) -> 46135 | N25: 1852.04 | O25: =IF($A25="","",SUMIFS('Payments Log'!$F$8:$F$207,'Payments Log'!$B$8:$B$207,$A25)) -> 1852.04 | P25: =IF($A25="","",ROUND($N25-$O25,2)) -> 0 | Q25: =IF($A25="","",IF(N($N25)<=0,"Check Amount",IF(ROUND($O25,2)<=0,"Unpaid",IF(ROUND($O25-$N25,2)>0,"Overpaid",IF(ROUND($P25,2)<=0,"Paid","Partially Paid"))))) -> Paid | R25: =IF(OR($A25="",$M25=""),"",IF(ROUND($P25,2)<=0,0,MAX(0,Settings!$C$5-$M25-Settings!$C$7))) -> 0 | S25: =IF($A25="","",IF(N($R25)>0,MAX($P25,0),0)) -> 0 | T25: =IF($A25="","",IF(ROUND($P25,2)<0,"Supplier Credit",IF(ROUND($P25,2)=0,"Closed",IF($M25="","No Due Date",IF(N($R25)<=0,"Not Due Yet",IF(N($R25)<=Settings!$C$8,"1-30 Days Overdue",IF(N($R25)<=Settings!$C$9,"31-60 Days Overdue",IF(N($R25)<=Settings!$C$10,"61-90 Days Overdue","90+ Days Overdue")))))))) -> Closed | U25: =IF($A25="","",IF(COUNTIFS('Payments Log'!$B$8:$B$207,$A25)=0,"",SUMPRODUCT(MAX(('Payments Log'!$B$8:$B$207=$A25)*'Payments Log'!$E$8:$E$207)))) -> 46135 | V25: =IF($A25="","",IF($J25="","Not Delivered",IF($I25="","No Target Date",IF($J25<=$I25,"On Time","Late")))) -> Late | W25: =IF($A25="","",IF($X25="","OK","REVIEW")) -> REVIEW | X25: =IF($A25="","",TRIM(IF($B25="","Missing vendor ID. ","")&IF($C25="NOT FOUND","Vendor ID not in Vendor Master. ","")&IF(COUNTIFS('Invoice & Delivery Log'!$A$8:$A$157,$A25)>1,"Duplicate invoice ID. ","")&IF(AND($D25<>"",COUNTIFS('Invoice & Delivery Log'!$D$8:$D$157,$D25,'Invoice & Delivery Log'!$B$8:$B$157,$B25)>1),"Duplicate supplier invoice number. ","")&IF($E25="","Missing PO number. ","")&IF($H25="","Missing invoice date. ","")&IF(N($N25)<=0,"Invoice amount must be greater than zero. ","")&IF(AND($H25<>"",$H25>Settings!$C$5),"Invoice date is in the future. ","")&IF(AND($K25="Received in Full",$J25=""),"Missing actual delivery date. ","")&IF(ROUND(N($O25)-N($N25),2)>0,"Payments exceed the invoice amount. ","")&IF(AND($K25="Rejected",N($O25)>0),"Payment made on a rejected delivery. ","")&IF(AND($B25<>"",IFERROR(INDEX('Vendor Master'!$H$8:$H$47,MATCH($B25,'Vendor Master'!$A$8:$A$47,0)),"")="Inactive",ROUND(N($P25),2)>0),"Open balance with an inactive vendor. ",""))) -> Missing PO number. | Y25: =IF($A25="","",IF(ROUND($P25,2)>0.004,"Yes","No")) -> No | Z25: =IF(OR($Y25<>"Yes",$M25=""),"",COUNTIFS('Invoice & Delivery Log'!$Y$8:$Y$157,"Yes",'Invoice & Delivery Log'!$M$8:$M$157,"<"&$M25)+COUNTIFS('Invoice & Delivery Log'!$Y$8:$Y$157,"Yes",'Invoice & Delivery Log'!$M$8:$M$157,$M25,'Invoice & Delivery Log'!$A$8:$A$157,"<"&$A25)+1)
A26: INV-1019 | B26: VEN-006 | C26: =IF($B26="","",IFERROR(INDEX('Vendor Master'!$B$8:$B$47,MATCH($B26,'Vendor Master'!$A$8:$A$47,0)),"NOT FOUND")) -> Harborline Logistics | D26: HLL-2026005 | E26: PO-2026-0019 | F26: =IF($B26="","",IFERROR(INDEX('Vendor Master'!$C$8:$C$47,MATCH($B26,'Vendor Master'!$A$8:$A$47,0)),"")) -> Logistics | G26: Warehouse transfer | H26: 46138 | I26: 46123 | J26: 46135 | K26: Received in Full | L26: =IF($B26="","",IFERROR(INDEX('Vendor Master'!$G$8:$G$47,MATCH($B26,'Vendor Master'!$A$8:$A$47,0)),"")) -> 30 | M26: =IF(OR($H26="",$L26=""),"",$H26+$L26) -> 46168 | N26: 1723.89 | O26: =IF($A26="","",SUMIFS('Payments Log'!$F$8:$F$207,'Payments Log'!$B$8:$B$207,$A26)) -> 956.19 | P26: =IF($A26="","",ROUND($N26-$O26,2)) -> 767.7 | Q26: =IF($A26="","",IF(N($N26)<=0,"Check Amount",IF(ROUND($O26,2)<=0,"Unpaid",IF(ROUND($O26-$N26,2)>0,"Overpaid",IF(ROUND($P26,2)<=0,"Paid","Partially Paid"))))) -> Partially Paid | R26: =IF(OR($A26="",$M26=""),"",IF(ROUND($P26,2)<=0,0,MAX(0,Settings!$C$5-$M26-Settings!$C$7))) -> 104 | S26: =IF($A26="","",IF(N($R26)>0,MAX($P26,0),0)) -> 767.7 | T26: =IF($A26="","",IF(ROUND($P26,2)<0,"Supplier Credit",IF(ROUND($P26,2)=0,"Closed",IF($M26="","No Due Date",IF(N($R26)<=0,"Not Due Yet",IF(N($R26)<=Settings!$C$8,"1-30 Days Overdue",IF(N($R26)<=Settings!$C$9,"31-60 Days Overdue",IF(N($R26)<=Settings!$C$10,"61-90 Days Overdue","90+ Days Overdue")))))))) -> 90+ Days Overdue | U26: =IF($A26="","",IF(COUNTIFS('Payments Log'!$B$8:$B$207,$A26)=0,"",SUMPRODUCT(MAX(('Payments Log'!$B$8:$B$207=$A26)*'Payments Log'!$E$8:$E$207)))) -> 46162 | V26: =IF($A26="","",IF($J26="","Not Delivered",IF($I26="","No Target Date",IF($J26<=$I26,"On Time","Late")))) -> Late | W26: =IF($A26="","",IF($X26="","OK","REVIEW")) -> OK | X26: =IF($A26="","",TRIM(IF($B26="","Missing vendor ID. ","")&IF($C26="NOT FOUND","Vendor ID not in Vendor Master. ","")&IF(COUNTIFS('Invoice & Delivery Log'!$A$8:$A$157,$A26)>1,"Duplicate invoice ID. ","")&IF(AND($D26<>"",COUNTIFS('Invoice & Delivery Log'!$D$8:$D$157,$D26,'Invoice & Delivery Log'!$B$8:$B$157,$B26)>1),"Duplicate supplier invoice number. ","")&IF($E26="","Missing PO number. ","")&IF($H26="","Missing invoice date. ","")&IF(N($N26)<=0,"Invoice amount must be greater than zero. ","")&IF(AND($H26<>"",$H26>Settings!$C$5),"Invoice date is in the future. ","")&IF(AND($K26="Received in Full",$J26=""),"Missing actual delivery date. ","")&IF(ROUND(N($O26)-N($N26),2)>0,"Payments exceed the invoice amount. ","")&IF(AND($K26="Rejected",N($O26)>0),"Payment made on a rejected delivery. ","")&IF(AND($B26<>"",IFERROR(INDEX('Vendor Master'!$H$8:$H$47,MATCH($B26,'Vendor Master'!$A$8:$A$47,0)),"")="Inactive",ROUND(N($P26),2)>0),"Open balance with an inactive vendor. ",""))) | Y26: =IF($A26="","",IF(ROUND($P26,2)>0.004,"Yes","No")) -> Yes | Z26: =IF(OR($Y26<>"Yes",$M26=""),"",COUNTIFS('Invoice & Delivery Log'!$Y$8:$Y$157,"Yes",'Invoice & Delivery Log'!$M$8:$M$157,"<"&$M26)+COUNTIFS('Invoice & Delivery Log'!$Y$8:$Y$157,"Yes",'Invoice & Delivery Log'!$M$8:$M$157,$M26,'Invoice & Delivery Log'!$A$8:$A$157,"<"&$A26)+1) -> 4
A27: INV-1020 | B27: VEN-004 | C27: =IF($B27="","",IFERROR(INDEX('Vendor Master'!$B$8:$B$47,MATCH($B27,'Vendor Master'!$A$8:$A$47,0)),"NOT FOUND")) -> Lakeshore Packaging Group | D27: LPG-2026001 | E27: PO-2026-0020 | F27: =IF($B27="","",IFERROR(INDEX('Vendor Master'!$C$8:$C$47,MATCH($B27,'Vendor Master'!$A$8:$A$47,0)),"")) -> Packaging | G27: Pallet wrap | H27: 46125 | I27: 46125 | J27: 46125 | K27: Received in Full | L27: =IF($B27="","",IFERROR(INDEX('Vendor Master'!$G$8:$G$47,MATCH($B27,'Vendor Master'!$A$8:$A$47,0)),"")) -> 30 | M27: =IF(OR($H27="",$L27=""),"",$H27+$L27) -> 46155 | N27: 4971.12 | O27: =IF($A27="","",SUMIFS('Payments Log'!$F$8:$F$207,'Payments Log'!$B$8:$B$207,$A27)) -> 4971.12 | P27: =IF($A27="","",ROUND($N27-$O27,2)) -> 0 | Q27: =IF($A27="","",IF(N($N27)<=0,"Check Amount",IF(ROUND($O27,2)<=0,"Unpaid",IF(ROUND($O27-$N27,2)>0,"Overpaid",IF(ROUND($P27,2)<=0,"Paid","Partially Paid"))))) -> Paid | R27: =IF(OR($A27="",$M27=""),"",IF(ROUND($P27,2)<=0,0,MAX(0,Settings!$C$5-$M27-Settings!$C$7))) -> 0 | S27: =IF($A27="","",IF(N($R27)>0,MAX($P27,0),0)) -> 0 | T27: =IF($A27="","",IF(ROUND($P27,2)<0,"Supplier Credit",IF(ROUND($P27,2)=0,"Closed",IF($M27="","No Due Date",IF(N($R27)<=0,"Not Due Yet",IF(N($R27)<=Settings!$C$8,"1-30 Days Overdue",IF(N($R27)<=Settings!$C$9,"31-60 Days Overdue",IF(N($R27)<=Settings!$C$10,"61-90 Days Overdue","90+ Days Overdue")))))))) -> Closed | U27: =IF($A27="","",IF(COUNTIFS('Payments Log'!$B$8:$B$207,$A27)=0,"",SUMPRODUCT(MAX(('Payments Log'!$B$8:$B$207=$A27)*'Payments Log'!$E$8:$E$207)))) -> 46138 | V27: =IF($A27="","",IF($J27="","Not Delivered",IF($I27="","No Target Date",IF($J27<=$I27,"On Time","Late")))) -> On Time | W27: =IF($A27="","",IF($X27="","OK","REVIEW")) -> REVIEW | X27: =IF($A27="","",TRIM(IF($B27="","Missing vendor ID. ","")&IF($C27="NOT FOUND","Vendor ID not in Vendor Master. ","")&IF(COUNTIFS('Invoice & Delivery Log'!$A$8:$A$157,$A27)>1,"Duplicate invoice ID. ","")&IF(AND($D27<>"",COUNTIFS('Invoice & Delivery Log'!$D$8:$D$157,$D27,'Invoice & Delivery Log'!$B$8:$B$157,$B27)>1),"Duplicate supplier invoice number. ","")&IF($E27="","Missing PO number. ","")&IF($H27="","Missing invoice date. ","")&IF(N($N27)<=0,"Invoice amount must be greater than zero. ","")&IF(AND($H27<>"",$H27>Settings!$C$5),"Invoice date is in the future. ","")&IF(AND($K27="Received in Full",$J27=""),"Missing actual delivery date. ","")&IF(ROUND(N($O27)-N($N27),2)>0,"Payments exceed the invoice amount. ","")&IF(AND($K27="Rejected",N($O27)>0),"Payment made on a rejected delivery. ","")&IF(AND($B27<>"",IFERROR(INDEX('Vendor Master'!$H$8:$H$47,MATCH($B27,'Vendor Master'!$A$8:$A$47,0)),"")="Inactive",ROUND(N($P27),2)>0),"Open balance with an inactive vendor. ",""))) -> Duplicate supplier invoice number. | Y27: =IF($A27="","",IF(ROUND($P27,2)>0.004,"Yes","No")) -> No | Z27: =IF(OR($Y27<>"Yes",$M27=""),"",COUNTIFS('Invoice & Delivery Log'!$Y$8:$Y$157,"Yes",'Invoice & Delivery Log'!$M$8:$M$157,"<"&$M27)+COUNTIFS('Invoice & Delivery Log'!$Y$8:$Y$157,"Yes",'Invoice & Delivery Log'!$M$8:$M$157,$M27,'Invoice & Delivery Log'!$A$8:$A$157,"<"&$A27)+1)
A28: INV-1021 | B28: VEN-007 | C28: =IF($B28="","",IFERROR(INDEX('Vendor Master'!$B$8:$B$47,MATCH($B28,'Vendor Master'!$A$8:$A$47,0)),"NOT FOUND")) -> Bluepoint Electrical Supply | D28: BES-2026001 | E28: PO-2026-0021 | F28: =IF($B28="","",IFERROR(INDEX('Vendor Master'!$C$8:$C$47,MATCH($B28,'Vendor Master'!$A$8:$A$47,0)),"")) -> Electrical | G28: Electrical panel parts | H28: 46139 | I28: 46128 | J28: 46136 | K28: Received in Full | L28: =IF($B28="","",IFERROR(INDEX('Vendor Master'!$G$8:$G$47,MATCH($B28,'Vendor Master'!$A$8:$A$47,0)),"")) -> 30 | M28: =IF(OR($H28="",$L28=""),"",$H28+$L28) -> 46169 | N28: 2112.2 | O28: =IF($A28="","",SUMIFS('Payments Log'!$F$8:$F$207,'Payments Log'!$B$8:$B$207,$A28)) -> 2112.2 | P28: =IF($A28="","",ROUND($N28-$O28,2)) -> 0 | Q28: =IF($A28="","",IF(N($N28)<=0,"Check Amount",IF(ROUND($O28,2)<=0,"Unpaid",IF(ROUND($O28-$N28,2)>0,"Overpaid",IF(ROUND($P28,2)<=0,"Paid","Partially Paid"))))) -> Paid | R28: =IF(OR($A28="",$M28=""),"",IF(ROUND($P28,2)<=0,0,MAX(0,Settings!$C$5-$M28-Settings!$C$7))) -> 0 | S28: =IF($A28="","",IF(N($R28)>0,MAX($P28,0),0)) -> 0 | T28: =IF($A28="","",IF(ROUND($P28,2)<0,"Supplier Credit",IF(ROUND($P28,2)=0,"Closed",IF($M28="","No Due Date",IF(N($R28)<=0,"Not Due Yet",IF(N($R28)<=Settings!$C$8,"1-30 Days Overdue",IF(N($R28)<=Settings!$C$9,"31-60 Days Overdue",IF(N($R28)<=Settings!$C$10,"61-90 Days Overdue","90+ Days Overdue")))))))) -> Closed | U28: =IF($A28="","",IF(COUNTIFS('Payments Log'!$B$8:$B$207,$A28)=0,"",SUMPRODUCT(MAX(('Payments Log'!$B$8:$B$207=$A28)*'Payments Log'!$E$8:$E$207)))) -> 46163 | V28: =IF($A28="","",IF($J28="","Not Delivered",IF($I28="","No Target Date",IF($J28<=$I28,"On Time","Late")))) -> Late | W28: =IF($A28="","",IF($X28="","OK","REVIEW")) -> OK | X28: =IF($A28="","",TRIM(IF($B28="","Missing vendor ID. ","")&IF($C28="NOT FOUND","Vendor ID not in Vendor Master. ","")&IF(COUNTIFS('Invoice & Delivery Log'!$A$8:$A$157,$A28)>1,"Duplicate invoice ID. ","")&IF(AND($D28<>"",COUNTIFS('Invoice & Delivery Log'!$D$8:$D$157,$D28,'Invoice & Delivery Log'!$B$8:$B$157,$B28)>1),"Duplicate supplier invoice number. ","")&IF($E28="","Missing PO number. ","")&IF($H28="","Missing invoice date. ","")&IF(N($N28)<=0,"Invoice amount must be greater than zero. ","")&IF(AND($H28<>"",$H28>Settings!$C$5),"Invoice date is in the future. ","")&IF(AND($K28="Received in Full",$J28=""),"Missing actual delivery date. ","")&IF(ROUND(N($O28)-N($N28),2)>0,"Payments exceed the invoice amount. ","")&IF(AND($K28="Rejected",N($O28)>0),"Payment made on a rejected delivery. ","")&IF(AND($B28<>"",IFERROR(INDEX('Vendor Master'!$H$8:$H$47,MATCH($B28,'Vendor Master'!$A$8:$A$47,0)),"")="Inactive",ROUND(N($P28),2)>0),"Open balance with an inactive vendor. ",""))) | Y28: =IF($A28="","",IF(ROUND($P28,2)>0.004,"Yes","No")) -> No | Z28: =IF(OR($Y28<>"Yes",$M28=""),"",COUNTIFS('Invoice & Delivery Log'!$Y$8:$Y$157,"Yes",'Invoice & Delivery Log'!$M$8:$M$157,"<"&$M28)+COUNTIFS('Invoice & Delivery Log'!$Y$8:$Y$157,"Yes",'Invoice & Delivery Log'!$M$8:$M$157,$M28,'Invoice & Delivery Log'!$A$8:$A$157,"<"&$A28)+1)
A29: INV-1022 | B29: VEN-010 | C29: =IF($B29="","",IFERROR(INDEX('Vendor Master'!$B$8:$B$47,MATCH($B29,'Vendor Master'!$A$8:$A$47,0)),"NOT FOUND")) -> Copperfield Textiles | D29: CFT-2026003 | E29: PO-2026-0022 | F29: =IF($B29="","",IFERROR(INDEX('Vendor Master'!$C$8:$C$47,MATCH($B29,'Vendor Master'!$A$8:$A$47,0)),"")) -> Textiles | G29: Textile bulk order | H29: 46131 | I29: 46129 | J29: 46129 | K29: Received in Full | L29: =IF($B29="","",IFERROR(INDEX('Vendor Master'!$G$8:$G$47,MATCH($B29,'Vendor Master'!$A$8:$A$47,0)),"")) -> 60 | M29: =IF(OR($H29="",$L29=""),"",$H29+$L29) -> 46191 | N29: 8539.35 | O29: =IF($A29="","",SUMIFS('Payments Log'!$F$8:$F$207,'Payments Log'!$B$8:$B$207,$A29)) -> 8539.35 | P29: =IF($A29="","",ROUND($N29-$O29,2)) -> 0 | Q29: =IF($A29="","",IF(N($N29)<=0,"Check Amount",IF(ROUND($O29,2)<=0,"Unpaid",IF(ROUND($O29-$N29,2)>0,"Overpaid",IF(ROUND($P29,2)<=0,"Paid","Partially Paid"))))) -> Paid | R29: =IF(OR($A29="",$M29=""),"",IF(ROUND($P29,2)<=0,0,MAX(0,Settings!$C$5-$M29-Settings!$C$7))) -> 0 | S29: =IF($A29="","",IF(N($R29)>0,MAX($P29,0),0)) -> 0 | T29: =IF($A29="","",IF(ROUND($P29,2)<0,"Supplier Credit",IF(ROUND($P29,2)=0,"Closed",IF($M29="","No Due Date",IF(N($R29)<=0,"Not Due Yet",IF(N($R29)<=Settings!$C$8,"1-30 Days Overdue",IF(N($R29)<=Settings!$C$9,"31-60 Days Overdue",IF(N($R29)<=Settings!$C$10,"61-90 Days Overdue","90+ Days Overdue")))))))) -> Closed | U29: =IF($A29="","",IF(COUNTIFS('Payments Log'!$B$8:$B$207,$A29)=0,"",SUMPRODUCT(MAX(('Payments Log'!$B$8:$B$207=$A29)*'Payments Log'!$E$8:$E$207)))) -> 46161 | V29: =IF($A29="","",IF($J29="","Not Delivered",IF($I29="","No Target Date",IF($J29<=$I29,"On Time","Late")))) -> On Time | W29: =IF($A29="","",IF($X29="","OK","REVIEW")) -> OK | X29: =IF($A29="","",TRIM(IF($B29="","Missing vendor ID. ","")&IF($C29="NOT FOUND","Vendor ID not in Vendor Master. ","")&IF(COUNTIFS('Invoice & Delivery Log'!$A$8:$A$157,$A29)>1,"Duplicate invoice ID. ","")&IF(AND($D29<>"",COUNTIFS('Invoice & Delivery Log'!$D$8:$D$157,$D29,'Invoice & Delivery Log'!$B$8:$B$157,$B29)>1),"Duplicate supplier invoice number. ","")&IF($E29="","Missing PO number. ","")&IF($H29="","Missing invoice date. ","")&IF(N($N29)<=0,"Invoice amount must be greater than zero. ","")&IF(AND($H29<>"",$H29>Settings!$C$5),"Invoice date is in the future. ","")&IF(AND($K29="Received in Full",$J29=""),"Missing actual delivery date. ","")&IF(ROUND(N($O29)-N($N29),2)>0,"Payments exceed the invoice amount. ","")&IF(AND($K29="Rejected",N($O29)>0),"Payment made on a rejected delivery. ","")&IF(AND($B29<>"",IFERROR(INDEX('Vendor Master'!$H$8:$H$47,MATCH($B29,'Vendor Master'!$A$8:$A$47,0)),"")="Inactive",ROUND(N($P29),2)>0),"Open balance with an inactive vendor. ",""))) | Y29: =IF($A29="","",IF(ROUND($P29,2)>0.004,"Yes","No")) -> No | Z29: =IF(OR($Y29<>"Yes",$M29=""),"",COUNTIFS('Invoice & Delivery Log'!$Y$8:$Y$157,"Yes",'Invoice & Delivery Log'!$M$8:$M$157,"<"&$M29)+COUNTIFS('Invoice & Delivery Log'!$Y$8:$Y$157,"Yes",'Invoice & Delivery Log'!$M$8:$M$157,$M29,'Invoice & Delivery Log'!$A$8:$A$157,"<"&$A29)+1)
A30: INV-1023 | B30: VEN-004 | C30: =IF($B30="","",IFERROR(INDEX('Vendor Master'!$B$8:$B$47,MATCH($B30,'Vendor Master'!$A$8:$A$47,0)),"NOT FOUND")) -> Lakeshore Packaging Group | D30: LPG-2026001 | E30: PO-2026-0023 | F30: =IF($B30="","",IFERROR(INDEX('Vendor Master'!$C$8:$C$47,MATCH($B30,'Vendor Master'!$A$8:$A$47,0)),"")) -> Packaging | G30: Pallet wrap | H30: 46139 | I30: 46138 | J30: 46137 | K30: Received in Full | L30: =IF($B30="","",IFERROR(INDEX('Vendor Master'!$G$8:$G$47,MATCH($B30,'Vendor Master'!$A$8:$A$47,0)),"")) -> 30 | M30: =IF(OR($H30="",$L30=""),"",$H30+$L30) -> 46169 | N30: 3190.52 | O30: =IF($A30="","",SUMIFS('Payments Log'!$F$8:$F$207,'Payments Log'!$B$8:$B$207,$A30)) -> 3190.52 | P30: =IF($A30="","",ROUND($N30-$O30,2)) -> 0 | Q30: =IF($A30="","",IF(N($N30)<=0,"Check Amount",IF(ROUND($O30,2)<=0,"Unpaid",IF(ROUND($O30-$N30,2)>0,"Overpaid",IF(ROUND($P30,2)<=0,"Paid","Partially Paid"))))) -> Paid | R30: =IF(OR($A30="",$M30=""),"",IF(ROUND($P30,2)<=0,0,MAX(0,Settings!$C$5-$M30-Settings!$C$7))) -> 0 | S30: =IF($A30="","",IF(N($R30)>0,MAX($P30,0),0)) -> 0 | T30: =IF($A30="","",IF(ROUND($P30,2)<0,"Supplier Credit",IF(ROUND($P30,2)=0,"Closed",IF($M30="","No Due Date",IF(N($R30)<=0,"Not Due Yet",IF(N($R30)<=Settings!$C$8,"1-30 Days Overdue",IF(N($R30)<=Settings!$C$9,"31-60 Days Overdue",IF(N($R30)<=Settings!$C$10,"61-90 Days Overdue","90+ Days Overdue")))))))) -> Closed | U30: =IF($A30="","",IF(COUNTIFS('Payments Log'!$B$8:$B$207,$A30)=0,"",SUMPRODUCT(MAX(('Payments Log'!$B$8:$B$207=$A30)*'Payments Log'!$E$8:$E$207)))) -> 46157 | V30: =IF($A30="","",IF($J30="","Not Delivered",IF($I30="","No Target Date",IF($J30<=$I30,"On Time","Late")))) -> On Time | W30: =IF($A30="","",IF($X30="","OK","REVIEW")) -> REVIEW | X30: =IF($A30="","",TRIM(IF($B30="","Missing vendor ID. ","")&IF($C30="NOT FOUND","Vendor ID not in Vendor Master. ","")&IF(COUNTIFS('Invoice & Delivery Log'!$A$8:$A$157,$A30)>1,"Duplicate invoice ID. ","")&IF(AND($D30<>"",COUNTIFS('Invoice & Delivery Log'!$D$8:$D$157,$D30,'Invoice & Delivery Log'!$B$8:$B$157,$B30)>1),"Duplicate supplier invoice number. ","")&IF($E30="","Missing PO number. ","")&IF($H30="","Missing invoice date. ","")&IF(N($N30)<=0,"Invoice amount must be greater than zero. ","")&IF(AND($H30<>"",$H30>Settings!$C$5),"Invoice date is in the future. ","")&IF(AND($K30="Received in Full",$J30=""),"Missing actual delivery date. ","")&IF(ROUND(N($O30)-N($N30),2)>0,"Payments exceed the invoice amount. ","")&IF(AND($K30="Rejected",N($O30)>0),"Payment made on a rejected delivery. ","")&IF(AND($B30<>"",IFERROR(INDEX('Vendor Master'!$H$8:$H$47,MATCH($B30,'Vendor Master'!$A$8:$A$47,0)),"")="Inactive",ROUND(N($P30),2)>0),"Open balance with an inactive vendor. ",""))) -> Duplicate supplier invoice number. | Y30: =IF($A30="","",IF(ROUND($P30,2)>0.004,"Yes","No")) -> No | Z30: =IF(OR($Y30<>"Yes",$M30=""),"",COUNTIFS('Invoice & Delivery Log'!$Y$8:$Y$157,"Yes",'Invoice & Delivery Log'!$M$8:$M$157,"<"&$M30)+COUNTIFS('Invoice & Delivery Log'!$Y$8:$Y$157,"Yes",'Invoice & Delivery Log'!$M$8:$M$157,$M30,'Invoice & Delivery Log'!$A$8:$A$157,"<"&$A30)+1)
A31: INV-1024 | B31: VEN-003 | C31: =IF($B31="","",IFERROR(INDEX('Vendor Master'!$B$8:$B$47,MATCH($B31,'Vendor Master'!$A$8:$A$47,0)),"NOT FOUND")) -> Ironbridge Hardware Co. | D31: IBH-2026003 | E31: PO-2026-0024 | F31: =IF($B31="","",IFERROR(INDEX('Vendor Master'!$C$8:$C$47,MATCH($B31,'Vendor Master'!$A$8:$A$47,0)),"")) -> Maintenance & Repair | G31: HVAC spare parts | H31: 46141 | I31: 46139 | J31: 46139 | K31: Received in Full | L31: =IF($B31="","",IFERROR(INDEX('Vendor Master'!$G$8:$G$47,MATCH($B31,'Vendor Master'!$A$8:$A$47,0)),"")) -> 45 | M31: =IF(OR($H31="",$L31=""),"",$H31+$L31) -> 46186 | N31: 4198.12 | O31: =IF($A31="","",SUMIFS('Payments Log'!$F$8:$F$207,'Payments Log'!$B$8:$B$207,$A31)) -> 0 | P31: =IF($A31="","",ROUND($N31-$O31,2)) -> 4198.12 | Q31: =IF($A31="","",IF(N($N31)<=0,"Check Amount",IF(ROUND($O31,2)<=0,"Unpaid",IF(ROUND($O31-$N31,2)>0,"Overpaid",IF(ROUND($P31,2)<=0,"Paid","Partially Paid"))))) -> Unpaid | R31: =IF(OR($A31="",$M31=""),"",IF(ROUND($P31,2)<=0,0,MAX(0,Settings!$C$5-$M31-Settings!$C$7))) -> 86 | S31: =IF($A31="","",IF(N($R31)>0,MAX($P31,0),0)) -> 4198.12 | T31: =IF($A31="","",IF(ROUND($P31,2)<0,"Supplier Credit",IF(ROUND($P31,2)=0,"Closed",IF($M31="","No Due Date",IF(N($R31)<=0,"Not Due Yet",IF(N($R31)<=Settings!$C$8,"1-30 Days Overdue",IF(N($R31)<=Settings!$C$9,"31-60 Days Overdue",IF(N($R31)<=Settings!$C$10,"61-90 Days Overdue","90+ Days Overdue")))))))) -> 61-90 Days Overdue | U31: =IF($A31="","",IF(COUNTIFS('Payments Log'!$B$8:$B$207,$A31)=0,"",SUMPRODUCT(MAX(('Payments Log'!$B$8:$B$207=$A31)*'Payments Log'!$E$8:$E$207)))) | V31: =IF($A31="","",IF($J31="","Not Delivered",IF($I31="","No Target Date",IF($J31<=$I31,"On Time","Late")))) -> On Time | W31: =IF($A31="","",IF($X31="","OK","REVIEW")) -> OK | X31: =IF($A31="","",TRIM(IF($B31="","Missing vendor ID. ","")&IF($C31="NOT FOUND","Vendor ID not in Vendor Master. ","")&IF(COUNTIFS('Invoice & Delivery Log'!$A$8:$A$157,$A31)>1,"Duplicate invoice ID. ","")&IF(AND($D31<>"",COUNTIFS('Invoice & Delivery Log'!$D$8:$D$157,$D31,'Invoice & Delivery Log'!$B$8:$B$157,$B31)>1),"Duplicate supplier invoice number. ","")&IF($E31="","Missing PO number. ","")&IF($H31="","Missing invoice date. ","")&IF(N($N31)<=0,"Invoice amount must be greater than zero. ","")&IF(AND($H31<>"",$H31>Settings!$C$5),"Invoice date is in the future. ","")&IF(AND($K31="Received in Full",$J31=""),"Missing actual delivery date. ","")&IF(ROUND(N($O31)-N($N31),2)>0,"Payments exceed the invoice amount. ","")&IF(AND($K31="Rejected",N($O31)>0),"Payment made on a rejected delivery. ","")&IF(AND($B31<>"",IFERROR(INDEX('Vendor Master'!$H$8:$H$47,MATCH($B31,'Vendor Master'!$A$8:$A$47,0)),"")="Inactive",ROUND(N($P31),2)>0),"Open balance with an inactive vendor. ",""))) | Y31: =IF($A31="","",IF(ROUND($P31,2)>0.004,"Yes","No")) -> Yes | Z31: =IF(OR($Y31<>"Yes",$M31=""),"",COUNTIFS('Invoice & Delivery Log'!$Y$8:$Y$157,"Yes",'Invoice & Delivery Log'!$M$8:$M$157,"<"&$M31)+COUNTIFS('Invoice & Delivery Log'!$Y$8:$Y$157,"Yes",'Invoice & Delivery Log'!$M$8:$M$157,$M31,'Invoice & Delivery Log'!$A$8:$A$157,"<"&$A31)+1) -> 5
A32: INV-1025 | B32: VEN-012 | C32: =IF($B32="","",IFERROR(INDEX('Vendor Master'!$B$8:$B$47,MATCH($B32,'Vendor Master'!$A$8:$A$47,0)),"NOT FOUND")) -> Willowbrook Beverage Co. | D32: WBC-2026002 | E32: PO-2026-0025 | F32: =IF($B32="","",IFERROR(INDEX('Vendor Master'!$C$8:$C$47,MATCH($B32,'Vendor Master'!$A$8:$A$47,0)),"")) -> Food & Beverage | G32: Bottled beverage restock | H32: 46143 | I32: 46141 | J32: 46141 | K32: Received in Full | L32: =IF($B32="","",IFERROR(INDEX('Vendor Master'!$G$8:$G$47,MATCH($B32,'Vendor Master'!$A$8:$A$47,0)),"")) -> 15 | M32: =IF(OR($H32="",$L32=""),"",$H32+$L32) -> 46158 | N32: 979.51 | O32: =IF($A32="","",SUMIFS('Payments Log'!$F$8:$F$207,'Payments Log'!$B$8:$B$207,$A32)) -> 979.51 | P32: =IF($A32="","",ROUND($N32-$O32,2)) -> 0 | Q32: =IF($A32="","",IF(N($N32)<=0,"Check Amount",IF(ROUND($O32,2)<=0,"Unpaid",IF(ROUND($O32-$N32,2)>0,"Overpaid",IF(ROUND($P32,2)<=0,"Paid","Partially Paid"))))) -> Paid | R32: =IF(OR($A32="",$M32=""),"",IF(ROUND($P32,2)<=0,0,MAX(0,Settings!$C$5-$M32-Settings!$C$7))) -> 0 | S32: =IF($A32="","",IF(N($R32)>0,MAX($P32,0),0)) -> 0 | T32: =IF($A32="","",IF(ROUND($P32,2)<0,"Supplier Credit",IF(ROUND($P32,2)=0,"Closed",IF($M32="","No Due Date",IF(N($R32)<=0,"Not Due Yet",IF(N($R32)<=Settings!$C$8,"1-30 Days Overdue",IF(N($R32)<=Settings!$C$9,"31-60 Days Overdue",IF(N($R32)<=Settings!$C$10,"61-90 Days Overdue","90+ Days Overdue")))))))) -> Closed | U32: =IF($A32="","",IF(COUNTIFS('Payments Log'!$B$8:$B$207,$A32)=0,"",SUMPRODUCT(MAX(('Payments Log'!$B$8:$B$207=$A32)*'Payments Log'!$E$8:$E$207)))) -> 46156 | V32: =IF($A32="","",IF($J32="","Not Delivered",IF($I32="","No Target Date",IF($J32<=$I32,"On Time","Late")))) -> On Time | W32: =IF($A32="","",IF($X32="","OK","REVIEW")) -> OK | X32: =IF($A32="","",TRIM(IF($B32="","Missing vendor ID. ","")&IF($C32="NOT FOUND","Vendor ID not in Vendor Master. ","")&IF(COUNTIFS('Invoice & Delivery Log'!$A$8:$A$157,$A32)>1,"Duplicate invoice ID. ","")&IF(AND($D32<>"",COUNTIFS('Invoice & Delivery Log'!$D$8:$D$157,$D32,'Invoice & Delivery Log'!$B$8:$B$157,$B32)>1),"Duplicate supplier invoice number. ","")&IF($E32="","Missing PO number. ","")&IF($H32="","Missing invoice date. ","")&IF(N($N32)<=0,"Invoice amount must be greater than zero. ","")&IF(AND($H32<>"",$H32>Settings!$C$5),"Invoice date is in the future. ","")&IF(AND($K32="Received in Full",$J32=""),"Missing actual delivery date. ","")&IF(ROUND(N($O32)-N($N32),2)>0,"Payments exceed the invoice amount. ","")&IF(AND($K32="Rejected",N($O32)>0),"Payment made on a rejected delivery. ","")&IF(AND($B32<>"",IFERROR(INDEX('Vendor Master'!$H$8:$H$47,MATCH($B32,'Vendor Master'!$A$8:$A$47,0)),"")="Inactive",ROUND(N($P32),2)>0),"Open balance with an inactive vendor. ",""))) | Y32: =IF($A32="","",IF(ROUND($P32,2)>0.004,"Yes","No")) -> No | Z32: =IF(OR($Y32<>"Yes",$M32=""),"",COUNTIFS('Invoice & Delivery Log'!$Y$8:$Y$157,"Yes",'Invoice & Delivery Log'!$M$8:$M$157,"<"&$M32)+COUNTIFS('Invoice & Delivery Log'!$Y$8:$Y$157,"Yes",'Invoice & Delivery Log'!$M$8:$M$157,$M32,'Invoice & Delivery Log'!$A$8:$A$157,"<"&$A32)+1)
A33: INV-1026 | B33: VEN-012 | C33: =IF($B33="","",IFERROR(INDEX('Vendor Master'!$B$8:$B$47,MATCH($B33,'Vendor Master'!$A$8:$A$47,0)),"NOT FOUND")) -> Willowbrook Beverage Co. | D33: WBC-2026003 | E33: PO-2026-0026 | F33: =IF($B33="","",IFERROR(INDEX('Vendor Master'!$C$8:$C$47,MATCH($B33,'Vendor Master'!$A$8:$A$47,0)),"")) -> Food & Beverage | G33: Seasonal drinks order | H33: 46146 | I33: 46142 | K33: Received in Full | L33: =IF($B33="","",IFERROR(INDEX('Vendor Master'!$G$8:$G$47,MATCH($B33,'Vendor Master'!$A$8:$A$47,0)),"")) -> 15 | M33: =IF(OR($H33="",$L33=""),"",$H33+$L33) -> 46161 | N33: 1262.57 | O33: =IF($A33="","",SUMIFS('Payments Log'!$F$8:$F$207,'Payments Log'!$B$8:$B$207,$A33)) -> 1262.57 | P33: =IF($A33="","",ROUND($N33-$O33,2)) -> 0 | Q33: =IF($A33="","",IF(N($N33)<=0,"Check Amount",IF(ROUND($O33,2)<=0,"Unpaid",IF(ROUND($O33-$N33,2)>0,"Overpaid",IF(ROUND($P33,2)<=0,"Paid","Partially Paid"))))) -> Paid | R33: =IF(OR($A33="",$M33=""),"",IF(ROUND($P33,2)<=0,0,MAX(0,Settings!$C$5-$M33-Settings!$C$7))) -> 0 | S33: =IF($A33="","",IF(N($R33)>0,MAX($P33,0),0)) -> 0 | T33: =IF($A33="","",IF(ROUND($P33,2)<0,"Supplier Credit",IF(ROUND($P33,2)=0,"Closed",IF($M33="","No Due Date",IF(N($R33)<=0,"Not Due Yet",IF(N($R33)<=Settings!$C$8,"1-30 Days Overdue",IF(N($R33)<=Settings!$C$9,"31-60 Days Overdue",IF(N($R33)<=Settings!$C$10,"61-90 Days Overdue","90+ Days Overdue")))))))) -> Closed | U33: =IF($A33="","",IF(COUNTIFS('Payments Log'!$B$8:$B$207,$A33)=0,"",SUMPRODUCT(MAX(('Payments Log'!$B$8:$B$207=$A33)*'Payments Log'!$E$8:$E$207)))) -> 46151 | V33: =IF($A33="","",IF($J33="","Not Delivered",IF($I33="","No Target Date",IF($J33<=$I33,"On Time","Late")))) -> Not Delivered | W33: =IF($A33="","",IF($X33="","OK","REVIEW")) -> REVIEW | X33: =IF($A33="","",TRIM(IF($B33="","Missing vendor ID. ","")&IF($C33="NOT FOUND","Vendor ID not in Vendor Master. ","")&IF(COUNTIFS('Invoice & Delivery Log'!$A$8:$A$157,$A33)>1,"Duplicate invoice ID. ","")&IF(AND($D33<>"",COUNTIFS('Invoice & Delivery Log'!$D$8:$D$157,$D33,'Invoice & Delivery Log'!$B$8:$B$157,$B33)>1),"Duplicate supplier invoice number. ","")&IF($E33="","Missing PO number. ","")&IF($H33="","Missing invoice date. ","")&IF(N($N33)<=0,"Invoice amount must be greater than zero. ","")&IF(AND($H33<>"",$H33>Settings!$C$5),"Invoice date is in the future. ","")&IF(AND($K33="Received in Full",$J33=""),"Missing actual delivery date. ","")&IF(ROUND(N($O33)-N($N33),2)>0,"Payments exceed the invoice amount. ","")&IF(AND($K33="Rejected",N($O33)>0),"Payment made on a rejected delivery. ","")&IF(AND($B33<>"",IFERROR(INDEX('Vendor Master'!$H$8:$H$47,MATCH($B33,'Vendor Master'!$A$8:$A$47,0)),"")="Inactive",ROUND(N($P33),2)>0),"Open balance with an inactive vendor. ",""))) -> Missing actual delivery date. | Y33: =IF($A33="","",IF(ROUND($P33,2)>0.004,"Yes","No")) -> No | Z33: =IF(OR($Y33<>"Yes",$M33=""),"",COUNTIFS('Invoice & Delivery Log'!$Y$8:$Y$157,"Yes",'Invoice & Delivery Log'!$M$8:$M$157,"<"&$M33)+COUNTIFS('Invoice & Delivery Log'!$Y$8:$Y$157,"Yes",'Invoice & Delivery Log'!$M$8:$M$157,$M33,'Invoice & Delivery Log'!$A$8:$A$157,"<"&$A33)+1)
A34: INV-1027 | B34: VEN-010 | C34: =IF($B34="","",IFERROR(INDEX('Vendor Master'!$B$8:$B$47,MATCH($B34,'Vendor Master'!$A$8:$A$47,0)),"NOT FOUND")) -> Copperfield Textiles | D34: CFT-2026004 | E34: PO-2026-0027 | F34: =IF($B34="","",IFERROR(INDEX('Vendor Master'!$C$8:$C$47,MATCH($B34,'Vendor Master'!$A$8:$A$47,0)),"")) -> Textiles | G34: Uniform fabric order | H34: 46146 | I34: 46146 | J34: 46145 | K34: Received in Full | L34: =IF($B34="","",IFERROR(INDEX('Vendor Master'!$G$8:$G$47,MATCH($B34,'Vendor Master'!$A$8:$A$47,0)),"")) -> 60 | M34: =IF(OR($H34="",$L34=""),"",$H34+$L34) -> 46206 | N34: 4959.04 | O34: =IF($A34="","",SUMIFS('Payments Log'!$F$8:$F$207,'Payments Log'!$B$8:$B$207,$A34)) -> 4959.04 | P34: =IF($A34="","",ROUND($N34-$O34,2)) -> 0 | Q34: =IF($A34="","",IF(N($N34)<=0,"Check Amount",IF(ROUND($O34,2)<=0,"Unpaid",IF(ROUND($O34-$N34,2)>0,"Overpaid",IF(ROUND($P34,2)<=0,"Paid","Partially Paid"))))) -> Paid | R34: =IF(OR($A34="",$M34=""),"",IF(ROUND($P34,2)<=0,0,MAX(0,Settings!$C$5-$M34-Settings!$C$7))) -> 0 | S34: =IF($A34="","",IF(N($R34)>0,MAX($P34,0),0)) -> 0 | T34: =IF($A34="","",IF(ROUND($P34,2)<0,"Supplier Credit",IF(ROUND($P34,2)=0,"Closed",IF($M34="","No Due Date",IF(N($R34)<=0,"Not Due Yet",IF(N($R34)<=Settings!$C$8,"1-30 Days Overdue",IF(N($R34)<=Settings!$C$9,"31-60 Days Overdue",IF(N($R34)<=Settings!$C$10,"61-90 Days Overdue","90+ Days Overdue")))))))) -> Closed | U34: =IF($A34="","",IF(COUNTIFS('Payments Log'!$B$8:$B$207,$A34)=0,"",SUMPRODUCT(MAX(('Payments Log'!$B$8:$B$207=$A34)*'Payments Log'!$E$8:$E$207)))) -> 46197 | V34: =IF($A34="","",IF($J34="","Not Delivered",IF($I34="","No Target Date",IF($J34<=$I34,"On Time","Late")))) -> On Time | W34: =IF($A34="","",IF($X34="","OK","REVIEW")) -> OK | X34: =IF($A34="","",TRIM(IF($B34="","Missing vendor ID. ","")&IF($C34="NOT FOUND","Vendor ID not in Vendor Master. ","")&IF(COUNTIFS('Invoice & Delivery Log'!$A$8:$A$157,$A34)>1,"Duplicate invoice ID. ","")&IF(AND($D34<>"",COUNTIFS('Invoice & Delivery Log'!$D$8:$D$157,$D34,'Invoice & Delivery Log'!$B$8:$B$157,$B34)>1),"Duplicate supplier invoice number. ","")&IF($E34="","Missing PO number. ","")&IF($H34="","Missing invoice date. ","")&IF(N($N34)<=0,"Invoice amount must be greater than zero. ","")&IF(AND($H34<>"",$H34>Settings!$C$5),"Invoice date is in the future. ","")&IF(AND($K34="Received in Full",$J34=""),"Missing actual delivery date. ","")&IF(ROUND(N($O34)-N($N34),2)>0,"Payments exceed the invoice amount. ","")&IF(AND($K34="Rejected",N($O34)>0),"Payment made on a rejected delivery. ","")&IF(AND($B34<>"",IFERROR(INDEX('Vendor Master'!$H$8:$H$47,MATCH($B34,'Vendor Master'!$A$8:$A$47,0)),"")="Inactive",ROUND(N($P34),2)>0),"Open balance with an inactive vendor. ",""))) | Y34: =IF($A34="","",IF(ROUND($P34,2)>0.004,"Yes","No")) -> No | Z34: =IF(OR($Y34<>"Yes",$M34=""),"",COUNTIFS('Invoice & Delivery Log'!$Y$8:$Y$157,"Yes",'Invoice & Delivery Log'!$M$8:$M$157,"<"&$M34)+COUNTIFS('Invoice & Delivery Log'!$Y$8:$Y$157,"Yes",'Invoice & Delivery Log'!$M$8:$M$157,$M34,'Invoice & Delivery Log'!$A$8:$A$157,"<"&$A34)+1)
A35: INV-1028 | B35: VEN-008 | C35: =IF($B35="","",IFERROR(INDEX('Vendor Master'!$B$8:$B$47,MATCH($B35,'Vendor Master'!$A$8:$A$47,0)),"NOT FOUND")) -> Prairie Print & Signage | D35: PPS-2026001 | E35: PO-2026-0028 | F35: =IF($B35="","",IFERROR(INDEX('Vendor Master'!$C$8:$C$47,MATCH($B35,'Vendor Master'!$A$8:$A$47,0)),"")) -> Marketing & Print | G35: Branded packaging print | H35: 46150 | I35: 46148 | J35: 46148 | K35: Received in Full | L35: =IF($B35="","",IFERROR(INDEX('Vendor Master'!$G$8:$G$47,MATCH($B35,'Vendor Master'!$A$8:$A$47,0)),"")) -> 21 | M35: =IF(OR($H35="",$L35=""),"",$H35+$L35) -> 46171 | N35: 672.92 | O35: =IF($A35="","",SUMIFS('Payments Log'!$F$8:$F$207,'Payments Log'!$B$8:$B$207,$A35)) -> 672.92 | P35: =IF($A35="","",ROUND($N35-$O35,2)) -> 0 | Q35: =IF($A35="","",IF(N($N35)<=0,"Check Amount",IF(ROUND($O35,2)<=0,"Unpaid",IF(ROUND($O35-$N35,2)>0,"Overpaid",IF(ROUND($P35,2)<=0,"Paid","Partially Paid"))))) -> Paid | R35: =IF(OR($A35="",$M35=""),"",IF(ROUND($P35,2)<=0,0,MAX(0,Settings!$C$5-$M35-Settings!$C$7))) -> 0 | S35: =IF($A35="","",IF(N($R35)>0,MAX($P35,0),0)) -> 0 | T35: =IF($A35="","",IF(ROUND($P35,2)<0,"Supplier Credit",IF(ROUND($P35,2)=0,"Closed",IF($M35="","No Due Date",IF(N($R35)<=0,"Not Due Yet",IF(N($R35)<=Settings!$C$8,"1-30 Days Overdue",IF(N($R35)<=Settings!$C$9,"31-60 Days Overdue",IF(N($R35)<=Settings!$C$10,"61-90 Days Overdue","90+ Days Overdue")))))))) -> Closed | U35: =IF($A35="","",IF(COUNTIFS('Payments Log'!$B$8:$B$207,$A35)=0,"",SUMPRODUCT(MAX(('Payments Log'!$B$8:$B$207=$A35)*'Payments Log'!$E$8:$E$207)))) -> 46158 | V35: =IF($A35="","",IF($J35="","Not Delivered",IF($I35="","No Target Date",IF($J35<=$I35,"On Time","Late")))) -> On Time | W35: =IF($A35="","",IF($X35="","OK","REVIEW")) -> OK | X35: =IF($A35="","",TRIM(IF($B35="","Missing vendor ID. ","")&IF($C35="NOT FOUND","Vendor ID not in Vendor Master. ","")&IF(COUNTIFS('Invoice & Delivery Log'!$A$8:$A$157,$A35)>1,"Duplicate invoice ID. ","")&IF(AND($D35<>"",COUNTIFS('Invoice & Delivery Log'!$D$8:$D$157,$D35,'Invoice & Delivery Log'!$B$8:$B$157,$B35)>1),"Duplicate supplier invoice number. ","")&IF($E35="","Missing PO number. ","")&IF($H35="","Missing invoice date. ","")&IF(N($N35)<=0,"Invoice amount must be greater than zero. ","")&IF(AND($H35<>"",$H35>Settings!$C$5),"Invoice date is in the future. ","")&IF(AND($K35="Received in Full",$J35=""),"Missing actual delivery date. ","")&IF(ROUND(N($O35)-N($N35),2)>0,"Payments exceed the invoice amount. ","")&IF(AND($K35="Rejected",N($O35)>0),"Payment made on a rejected delivery. ","")&IF(AND($B35<>"",IFERROR(INDEX('Vendor Master'!$H$8:$H$47,MATCH($B35,'Vendor Master'!$A$8:$A$47,0)),"")="Inactive",ROUND(N($P35),2)>0),"Open balance with an inactive vendor. ",""))) | Y35: =IF($A35="","",IF(ROUND($P35,2)>0.004,"Yes","No")) -> No | Z35: =IF(OR($Y35<>"Yes",$M35=""),"",COUNTIFS('Invoice & Delivery Log'!$Y$8:$Y$157,"Yes",'Invoice & Delivery Log'!$M$8:$M$157,"<"&$M35)+COUNTIFS('Invoice & Delivery Log'!$Y$8:$Y$157,"Yes",'Invoice & Delivery Log'!$M$8:$M$157,$M35,'Invoice & Delivery Log'!$A$8:$A$157,"<"&$A35)+1)
A36: INV-1029 | B36: VEN-010 | C36: =IF($B36="","",IFERROR(INDEX('Vendor Master'!$B$8:$B$47,MATCH($B36,'Vendor Master'!$A$8:$A$47,0)),"NOT FOUND")) -> Copperfield Textiles | D36: CFT-2026005 | E36: PO-2026-0029 | F36: =IF($B36="","",IFERROR(INDEX('Vendor Master'!$C$8:$C$47,MATCH($B36,'Vendor Master'!$A$8:$A$47,0)),"")) -> Textiles | G36: Textile bulk order | H36: 46152 | I36: 46149 | J36: 46152 | K36: Received in Full | L36: =IF($B36="","",IFERROR(INDEX('Vendor Master'!$G$8:$G$47,MATCH($B36,'Vendor Master'!$A$8:$A$47,0)),"")) -> 60 | M36: =IF(OR($H36="",$L36=""),"",$H36+$L36) -> 46212 | N36: 10842.29 | O36: =IF($A36="","",SUMIFS('Payments Log'!$F$8:$F$207,'Payments Log'!$B$8:$B$207,$A36)) -> 10842.29 | P36: =IF($A36="","",ROUND($N36-$O36,2)) -> 0 | Q36: =IF($A36="","",IF(N($N36)<=0,"Check Amount",IF(ROUND($O36,2)<=0,"Unpaid",IF(ROUND($O36-$N36,2)>0,"Overpaid",IF(ROUND($P36,2)<=0,"Paid","Partially Paid"))))) -> Paid | R36: =IF(OR($A36="",$M36=""),"",IF(ROUND($P36,2)<=0,0,MAX(0,Settings!$C$5-$M36-Settings!$C$7))) -> 0 | S36: =IF($A36="","",IF(N($R36)>0,MAX($P36,0),0)) -> 0 | T36: =IF($A36="","",IF(ROUND($P36,2)<0,"Supplier Credit",IF(ROUND($P36,2)=0,"Closed",IF($M36="","No Due Date",IF(N($R36)<=0,"Not Due Yet",IF(N($R36)<=Settings!$C$8,"1-30 Days Overdue",IF(N($R36)<=Settings!$C$9,"31-60 Days Overdue",IF(N($R36)<=Settings!$C$10,"61-90 Days Overdue","90+ Days Overdue")))))))) -> Closed | U36: =IF($A36="","",IF(COUNTIFS('Payments Log'!$B$8:$B$207,$A36)=0,"",SUMPRODUCT(MAX(('Payments Log'!$B$8:$B$207=$A36)*'Payments Log'!$E$8:$E$207)))) -> 46177 | V36: =IF($A36="","",IF($J36="","Not Delivered",IF($I36="","No Target Date",IF($J36<=$I36,"On Time","Late")))) -> Late | W36: =IF($A36="","",IF($X36="","OK","REVIEW")) -> OK | X36: =IF($A36="","",TRIM(IF($B36="","Missing vendor ID. ","")&IF($C36="NOT FOUND","Vendor ID not in Vendor Master. ","")&IF(COUNTIFS('Invoice & Delivery Log'!$A$8:$A$157,$A36)>1,"Duplicate invoice ID. ","")&IF(AND($D36<>"",COUNTIFS('Invoice & Delivery Log'!$D$8:$D$157,$D36,'Invoice & Delivery Log'!$B$8:$B$157,$B36)>1),"Duplicate supplier invoice number. ","")&IF($E36="","Missing PO number. ","")&IF($H36="","Missing invoice date. ","")&IF(N($N36)<=0,"Invoice amount must be greater than zero. ","")&IF(AND($H36<>"",$H36>Settings!$C$5),"Invoice date is in the future. ","")&IF(AND($K36="Received in Full",$J36=""),"Missing actual delivery date. ","")&IF(ROUND(N($O36)-N($N36),2)>0,"Payments exceed the invoice amount. ","")&IF(AND($K36="Rejected",N($O36)>0),"Payment made on a rejected delivery. ","")&IF(AND($B36<>"",IFERROR(INDEX('Vendor Master'!$H$8:$H$47,MATCH($B36,'Vendor Master'!$A$8:$A$47,0)),"")="Inactive",ROUND(N($P36),2)>0),"Open balance with an inactive vendor. ",""))) | Y36: =IF($A36="","",IF(ROUND($P36,2)>0.004,"Yes","No")) -> No | Z36: =IF(OR($Y36<>"Yes",$M36=""),"",COUNTIFS('Invoice & Delivery Log'!$Y$8:$Y$157,"Yes",'Invoice & Delivery Log'!$M$8:$M$157,"<"&$M36)+COUNTIFS('Invoice & Delivery Log'!$Y$8:$Y$157,"Yes",'Invoice & Delivery Log'!$M$8:$M$157,$M36,'Invoice & Delivery Log'!$A$8:$A$157,"<"&$A36)+1)
A37: INV-1030 | B37: VEN-009 | C37: =IF($B37="","",IFERROR(INDEX('Vendor Master'!$B$8:$B$47,MATCH($B37,'Vendor Master'!$A$8:$A$47,0)),"NOT FOUND")) -> Vertex IT Solutions | D37: VIT-2026003 | E37: PO-2026-0030 | F37: =IF($B37="","",IFERROR(INDEX('Vendor Master'!$C$8:$C$47,MATCH($B37,'Vendor Master'!$A$8:$A$47,0)),"")) -> IT & Software | G37: Laptop hardware | H37: 46153 | I37: 46152 | J37: 46150 | K37: Received in Full | L37: =IF($B37="","",IFERROR(INDEX('Vendor Master'!$G$8:$G$47,MATCH($B37,'Vendor Master'!$A$8:$A$47,0)),"")) -> 30 | M37: =IF(OR($H37="",$L37=""),"",$H37+$L37) -> 46183 | N37: 8642.41 | O37: =IF($A37="","",SUMIFS('Payments Log'!$F$8:$F$207,'Payments Log'!$B$8:$B$207,$A37)) -> 8642.41 | P37: =IF($A37="","",ROUND($N37-$O37,2)) -> 0 | Q37: =IF($A37="","",IF(N($N37)<=0,"Check Amount",IF(ROUND($O37,2)<=0,"Unpaid",IF(ROUND($O37-$N37,2)>0,"Overpaid",IF(ROUND($P37,2)<=0,"Paid","Partially Paid"))))) -> Paid | R37: =IF(OR($A37="",$M37=""),"",IF(ROUND($P37,2)<=0,0,MAX(0,Settings!$C$5-$M37-Settings!$C$7))) -> 0 | S37: =IF($A37="","",IF(N($R37)>0,MAX($P37,0),0)) -> 0 | T37: =IF($A37="","",IF(ROUND($P37,2)<0,"Supplier Credit",IF(ROUND($P37,2)=0,"Closed",IF($M37="","No Due Date",IF(N($R37)<=0,"Not Due Yet",IF(N($R37)<=Settings!$C$8,"1-30 Days Overdue",IF(N($R37)<=Settings!$C$9,"31-60 Days Overdue",IF(N($R37)<=Settings!$C$10,"61-90 Days Overdue","90+ Days Overdue")))))))) -> Closed | U37: =IF($A37="","",IF(COUNTIFS('Payments Log'!$B$8:$B$207,$A37)=0,"",SUMPRODUCT(MAX(('Payments Log'!$B$8:$B$207=$A37)*'Payments Log'!$E$8:$E$207)))) -> 46183 | V37: =IF($A37="","",IF($J37="","Not Delivered",IF($I37="","No Target Date",IF($J37<=$I37,"On Time","Late")))) -> On Time | W37: =IF($A37="","",IF($X37="","OK","REVIEW")) -> OK | X37: =IF($A37="","",TRIM(IF($B37="","Missing vendor ID. ","")&IF($C37="NOT FOUND","Vendor ID not in Vendor Master. ","")&IF(COUNTIFS('Invoice & Delivery Log'!$A$8:$A$157,$A37)>1,"Duplicate invoice ID. ","")&IF(AND($D37<>"",COUNTIFS('Invoice & Delivery Log'!$D$8:$D$157,$D37,'Invoice & Delivery Log'!$B$8:$B$157,$B37)>1),"Duplicate supplier invoice number. ","")&IF($E37="","Missing PO number. ","")&IF($H37="","Missing invoice date. ","")&IF(N($N37)<=0,"Invoice amount must be greater than zero. ","")&IF(AND($H37<>"",$H37>Settings!$C$5),"Invoice date is in the future. ","")&IF(AND($K37="Received in Full",$J37=""),"Missing actual delivery date. ","")&IF(ROUND(N($O37)-N($N37),2)>0,"Payments exceed the invoice amount. ","")&IF(AND($K37="Rejected",N($O37)>0),"Payment made on a rejected delivery. ","")&IF(AND($B37<>"",IFERROR(INDEX('Vendor Master'!$H$8:$H$47,MATCH($B37,'Vendor Master'!$A$8:$A$47,0)),"")="Inactive",ROUND(N($P37),2)>0),"Open balance with an inactive vendor. ",""))) | Y37: =IF($A37="","",IF(ROUND($P37,2)>0.004,"Yes","No")) -> No | Z37: =IF(OR($Y37<>"Yes",$M37=""),"",COUNTIFS('Invoice & Delivery Log'!$Y$8:$Y$157,"Yes",'Invoice & Delivery Log'!$M$8:$M$157,"<"&$M37)+COUNTIFS('Invoice & Delivery Log'!$Y$8:$Y$157,"Yes",'Invoice & Delivery Log'!$M$8:$M$157,$M37,'Invoice & Delivery Log'!$A$8:$A$157,"<"&$A37)+1)
A38: INV-1031 | B38: VEN-004 | C38: =IF($B38="","",IFERROR(INDEX('Vendor Master'!$B$8:$B$47,MATCH($B38,'Vendor Master'!$A$8:$A$47,0)),"NOT FOUND")) -> Lakeshore Packaging Group | D38: LPG-2026003 | E38: PO-2026-0031 | F38: =IF($B38="","",IFERROR(INDEX('Vendor Master'!$C$8:$C$47,MATCH($B38,'Vendor Master'!$A$8:$A$47,0)),"")) -> Packaging | G38: Pallet wrap | H38: 46172 | I38: 46169 | J38: 46169 | K38: Received in Full | L38: =IF($B38="","",IFERROR(INDEX('Vendor Master'!$G$8:$G$47,MATCH($B38,'Vendor Master'!$A$8:$A$47,0)),"")) -> 30 | M38: =IF(OR($H38="",$L38=""),"",$H38+$L38) -> 46202 | N38: 4695.58 | O38: =IF($A38="","",SUMIFS('Payments Log'!$F$8:$F$207,'Payments Log'!$B$8:$B$207,$A38)) -> 4695.58 | P38: =IF($A38="","",ROUND($N38-$O38,2)) -> 0 | Q38: =IF($A38="","",IF(N($N38)<=0,"Check Amount",IF(ROUND($O38,2)<=0,"Unpaid",IF(ROUND($O38-$N38,2)>0,"Overpaid",IF(ROUND($P38,2)<=0,"Paid","Partially Paid"))))) -> Paid | R38: =IF(OR($A38="",$M38=""),"",IF(ROUND($P38,2)<=0,0,MAX(0,Settings!$C$5-$M38-Settings!$C$7))) -> 0 | S38: =IF($A38="","",IF(N($R38)>0,MAX($P38,0),0)) -> 0 | T38: =IF($A38="","",IF(ROUND($P38,2)<0,"Supplier Credit",IF(ROUND($P38,2)=0,"Closed",IF($M38="","No Due Date",IF(N($R38)<=0,"Not Due Yet",IF(N($R38)<=Settings!$C$8,"1-30 Days Overdue",IF(N($R38)<=Settings!$C$9,"31-60 Days Overdue",IF(N($R38)<=Settings!$C$10,"61-90 Days Overdue","90+ Days Overdue")))))))) -> Closed | U38: =IF($A38="","",IF(COUNTIFS('Payments Log'!$B$8:$B$207,$A38)=0,"",SUMPRODUCT(MAX(('Payments Log'!$B$8:$B$207=$A38)*'Payments Log'!$E$8:$E$207)))) -> 46192 | V38: =IF($A38="","",IF($J38="","Not Delivered",IF($I38="","No Target Date",IF($J38<=$I38,"On Time","Late")))) -> On Time | W38: =IF($A38="","",IF($X38="","OK","REVIEW")) -> OK | X38: =IF($A38="","",TRIM(IF($B38="","Missing vendor ID. ","")&IF($C38="NOT FOUND","Vendor ID not in Vendor Master. ","")&IF(COUNTIFS('Invoice & Delivery Log'!$A$8:$A$157,$A38)>1,"Duplicate invoice ID. ","")&IF(AND($D38<>"",COUNTIFS('Invoice & Delivery Log'!$D$8:$D$157,$D38,'Invoice & Delivery Log'!$B$8:$B$157,$B38)>1),"Duplicate supplier invoice number. ","")&IF($E38="","Missing PO number. ","")&IF($H38="","Missing invoice date. ","")&IF(N($N38)<=0,"Invoice amount must be greater than zero. ","")&IF(AND($H38<>"",$H38>Settings!$C$5),"Invoice date is in the future. ","")&IF(AND($K38="Received in Full",$J38=""),"Missing actual delivery date. ","")&IF(ROUND(N($O38)-N($N38),2)>0,"Payments exceed the invoice amount. ","")&IF(AND($K38="Rejected",N($O38)>0),"Payment made on a rejected delivery. ","")&IF(AND($B38<>"",IFERROR(INDEX('Vendor Master'!$H$8:$H$47,MATCH($B38,'Vendor Master'!$A$8:$A$47,0)),"")="Inactive",ROUND(N($P38),2)>0),"Open balance with an inactive vendor. ",""))) | Y38: =IF($A38="","",IF(ROUND($P38,2)>0.004,"Yes","No")) -> No | Z38: =IF(OR($Y38<>"Yes",$M38=""),"",COUNTIFS('Invoice & Delivery Log'!$Y$8:$Y$157,"Yes",'Invoice & Delivery Log'!$M$8:$M$157,"<"&$M38)+COUNTIFS('Invoice & Delivery Log'!$Y$8:$Y$157,"Yes",'Invoice & Delivery Log'!$M$8:$M$157,$M38,'Invoice & Delivery Log'!$A$8:$A$157,"<"&$A38)+1)
A39: INV-1032 | B39: VEN-009 | C39: =IF($B39="","",IFERROR(INDEX('Vendor Master'!$B$8:$B$47,MATCH($B39,'Vendor Master'!$A$8:$A$47,0)),"NOT FOUND")) -> Vertex IT Solutions | D39: VIT-2026004 | E39: PO-2026-0032 | F39: =IF($B39="","",IFERROR(INDEX('Vendor Master'!$C$8:$C$47,MATCH($B39,'Vendor Master'!$A$8:$A$47,0)),"")) -> IT & Software | G39: Software licence renewal | H39: 46174 | I39: 46172 | J39: 46171 | K39: Received in Full | L39: =IF($B39="","",IFERROR(INDEX('Vendor Master'!$G$8:$G$47,MATCH($B39,'Vendor Master'!$A$8:$A$47,0)),"")) -> 30 | M39: =IF(OR($H39="",$L39=""),"",$H39+$L39) -> 46204 | N39: 2099.34 | O39: =IF($A39="","",SUMIFS('Payments Log'!$F$8:$F$207,'Payments Log'!$B$8:$B$207,$A39)) -> 2099.34 | P39: =IF($A39="","",ROUND($N39-$O39,2)) -> 0 | Q39: =IF($A39="","",IF(N($N39)<=0,"Check Amount",IF(ROUND($O39,2)<=0,"Unpaid",IF(ROUND($O39-$N39,2)>0,"Overpaid",IF(ROUND($P39,2)<=0,"Paid","Partially Paid"))))) -> Paid | R39: =IF(OR($A39="",$M39=""),"",IF(ROUND($P39,2)<=0,0,MAX(0,Settings!$C$5-$M39-Settings!$C$7))) -> 0 | S39: =IF($A39="","",IF(N($R39)>0,MAX($P39,0),0)) -> 0 | T39: =IF($A39="","",IF(ROUND($P39,2)<0,"Supplier Credit",IF(ROUND($P39,2)=0,"Closed",IF($M39="","No Due Date",IF(N($R39)<=0,"Not Due Yet",IF(N($R39)<=Settings!$C$8,"1-30 Days Overdue",IF(N($R39)<=Settings!$C$9,"31-60 Days Overdue",IF(N($R39)<=Settings!$C$10,"61-90 Days Overdue","90+ Days Overdue")))))))) -> Closed | U39: =IF($A39="","",IF(COUNTIFS('Payments Log'!$B$8:$B$207,$A39)=0,"",SUMPRODUCT(MAX(('Payments Log'!$B$8:$B$207=$A39)*'Payments Log'!$E$8:$E$207)))) -> 46207 | V39: =IF($A39="","",IF($J39="","Not Delivered",IF($I39="","No Target Date",IF($J39<=$I39,"On Time","Late")))) -> On Time | W39: =IF($A39="","",IF($X39="","OK","REVIEW")) -> OK | X39: =IF($A39="","",TRIM(IF($B39="","Missing vendor ID. ","")&IF($C39="NOT FOUND","Vendor ID not in Vendor Master. ","")&IF(COUNTIFS('Invoice & Delivery Log'!$A$8:$A$157,$A39)>1,"Duplicate invoice ID. ","")&IF(AND($D39<>"",COUNTIFS('Invoice & Delivery Log'!$D$8:$D$157,$D39,'Invoice & Delivery Log'!$B$8:$B$157,$B39)>1),"Duplicate supplier invoice number. ","")&IF($E39="","Missing PO number. ","")&IF($H39="","Missing invoice date. ","")&IF(N($N39)<=0,"Invoice amount must be greater than zero. ","")&IF(AND($H39<>"",$H39>Settings!$C$5),"Invoice date is in the future. ","")&IF(AND($K39="Received in Full",$J39=""),"Missing actual delivery date. ","")&IF(ROUND(N($O39)-N($N39),2)>0,"Payments exceed the invoice amount. ","")&IF(AND($K39="Rejected",N($O39)>0),"Payment made on a rejected delivery. ","")&IF(AND($B39<>"",IFERROR(INDEX('Vendor Master'!$H$8:$H$47,MATCH($B39,'Vendor Master'!$A$8:$A$47,0)),"")="Inactive",ROUND(N($P39),2)>0),"Open balance with an inactive vendor. ",""))) | Y39: =IF($A39="","",IF(ROUND($P39,2)>0.004,"Yes","No")) -> No | Z39: =IF(OR($Y39<>"Yes",$M39=""),"",COUNTIFS('Invoice & Delivery Log'!$Y$8:$Y$157,"Yes",'Invoice & Delivery Log'!$M$8:$M$157,"<"&$M39)+COUNTIFS('Invoice & Delivery Log'!$Y$8:$Y$157,"Yes",'Invoice & Delivery Log'!$M$8:$M$157,$M39,'Invoice & Delivery Log'!$A$8:$A$157,"<"&$A39)+1)
A40: INV-1033 | B40: VEN-005 | C40: =IF($B40="","",IFERROR(INDEX('Vendor Master'!$B$8:$B$47,MATCH($B40,'Vendor Master'!$A$8:$A$47,0)),"NOT FOUND")) -> Summit Cleaning Services | D40: SCS-2026003 | E40: PO-2026-0033 | F40: =IF($B40="","",IFERROR(INDEX('Vendor Master'!$C$8:$C$47,MATCH($B40,'Vendor Master'!$A$8:$A$47,0)),"")) -> Facility Services | G40: Sanitation supplies | H40: 46172 | I40: 46172 | J40: 46172 | K40: Received in Full | L40: =IF($B40="","",IFERROR(INDEX('Vendor Master'!$G$8:$G$47,MATCH($B40,'Vendor Master'!$A$8:$A$47,0)),"")) -> 14 | M40: =IF(OR($H40="",$L40=""),"",$H40+$L40) -> 46186 | N40: 1862.49 | O40: =IF($A40="","",SUMIFS('Payments Log'!$F$8:$F$207,'Payments Log'!$B$8:$B$207,$A40)) -> 1862.49 | P40: =IF($A40="","",ROUND($N40-$O40,2)) -> 0 | Q40: =IF($A40="","",IF(N($N40)<=0,"Check Amount",IF(ROUND($O40,2)<=0,"Unpaid",IF(ROUND($O40-$N40,2)>0,"Overpaid",IF(ROUND($P40,2)<=0,"Paid","Partially Paid"))))) -> Paid | R40: =IF(OR($A40="",$M40=""),"",IF(ROUND($P40,2)<=0,0,MAX(0,Settings!$C$5-$M40-Settings!$C$7))) -> 0 | S40: =IF($A40="","",IF(N($R40)>0,MAX($P40,0),0)) -> 0 | T40: =IF($A40="","",IF(ROUND($P40,2)<0,"Supplier Credit",IF(ROUND($P40,2)=0,"Closed",IF($M40="","No Due Date",IF(N($R40)<=0,"Not Due Yet",IF(N($R40)<=Settings!$C$8,"1-30 Days Overdue",IF(N($R40)<=Settings!$C$9,"31-60 Days Overdue",IF(N($R40)<=Settings!$C$10,"61-90 Days Overdue","90+ Days Overdue")))))))) -> Closed | U40: =IF($A40="","",IF(COUNTIFS('Payments Log'!$B$8:$B$207,$A40)=0,"",SUMPRODUCT(MAX(('Payments Log'!$B$8:$B$207=$A40)*'Payments Log'!$E$8:$E$207)))) -> 46179 | V40: =IF($A40="","",IF($J40="","Not Delivered",IF($I40="","No Target Date",IF($J40<=$I40,"On Time","Late")))) -> On Time | W40: =IF($A40="","",IF($X40="","OK","REVIEW")) -> OK | X40: =IF($A40="","",TRIM(IF($B40="","Missing vendor ID. ","")&IF($C40="NOT FOUND","Vendor ID not in Vendor Master. ","")&IF(COUNTIFS('Invoice & Delivery Log'!$A$8:$A$157,$A40)>1,"Duplicate invoice ID. ","")&IF(AND($D40<>"",COUNTIFS('Invoice & Delivery Log'!$D$8:$D$157,$D40,'Invoice & Delivery Log'!$B$8:$B$157,$B40)>1),"Duplicate supplier invoice number. ","")&IF($E40="","Missing PO number. ","")&IF($H40="","Missing invoice date. ","")&IF(N($N40)<=0,"Invoice amount must be greater than zero. ","")&IF(AND($H40<>"",$H40>Settings!$C$5),"Invoice date is in the future. ","")&IF(AND($K40="Received in Full",$J40=""),"Missing actual delivery date. ","")&IF(ROUND(N($O40)-N($N40),2)>0,"Payments exceed the invoice amount. ","")&IF(AND($K40="Rejected",N($O40)>0),"Payment made on a rejected delivery. ","")&IF(AND($B40<>"",IFERROR(INDEX('Vendor Master'!$H$8:$H$47,MATCH($B40,'Vendor Master'!$A$8:$A$47,0)),"")="Inactive",ROUND(N($P40),2)>0),"Open balance with an inactive vendor. ",""))) | Y40: =IF($A40="","",IF(ROUND($P40,2)>0.004,"Yes","No")) -> No | Z40: =IF(OR($Y40<>"Yes",$M40=""),"",COUNTIFS('Invoice & Delivery Log'!$Y$8:$Y$157,"Yes",'Invoice & Delivery Log'!$M$8:$M$157,"<"&$M40)+COUNTIFS('Invoice & Delivery Log'!$Y$8:$Y$157,"Yes",'Invoice & Delivery Log'!$M$8:$M$157,$M40,'Invoice & Delivery Log'!$A$8:$A$157,"<"&$A40)+1)
A41: INV-1034 | B41: VEN-002 | C41: =IF($B41="","",IFERROR(INDEX('Vendor Master'!$B$8:$B$47,MATCH($B41,'Vendor Master'!$A$8:$A$47,0)),"NOT FOUND")) -> Cascade Foods Distribution | D41: CFD-2026003 | E41: PO-2026-0034 | F41: =IF($B41="","",IFERROR(INDEX('Vendor Master'!$C$8:$C$47,MATCH($B41,'Vendor Master'!$A$8:$A$47,0)),"")) -> Food & Beverage | G41: Fresh produce delivery | H41: 46178 | I41: 46177 | J41: 46177 | K41: Received in Full | L41: =IF($B41="","",IFERROR(INDEX('Vendor Master'!$G$8:$G$47,MATCH($B41,'Vendor Master'!$A$8:$A$47,0)),"")) -> 15 | M41: =IF(OR($H41="",$L41=""),"",$H41+$L41) -> 46193 | N41: 1471.09 | O41: =IF($A41="","",SUMIFS('Payments Log'!$F$8:$F$207,'Payments Log'!$B$8:$B$207,$A41)) -> 829.81 | P41: =IF($A41="","",ROUND($N41-$O41,2)) -> 641.28 | Q41: =IF($A41="","",IF(N($N41)<=0,"Check Amount",IF(ROUND($O41,2)<=0,"Unpaid",IF(ROUND($O41-$N41,2)>0,"Overpaid",IF(ROUND($P41,2)<=0,"Paid","Partially Paid"))))) -> Partially Paid | R41: =IF(OR($A41="",$M41=""),"",IF(ROUND($P41,2)<=0,0,MAX(0,Settings!$C$5-$M41-Settings!$C$7))) -> 79 | S41: =IF($A41="","",IF(N($R41)>0,MAX($P41,0),0)) -> 641.28 | T41: =IF($A41="","",IF(ROUND($P41,2)<0,"Supplier Credit",IF(ROUND($P41,2)=0,"Closed",IF($M41="","No Due Date",IF(N($R41)<=0,"Not Due Yet",IF(N($R41)<=Settings!$C$8,"1-30 Days Overdue",IF(N($R41)<=Settings!$C$9,"31-60 Days Overdue",IF(N($R41)<=Settings!$C$10,"61-90 Days Overdue","90+ Days Overdue")))))))) -> 61-90 Days Overdue | U41: =IF($A41="","",IF(COUNTIFS('Payments Log'!$B$8:$B$207,$A41)=0,"",SUMPRODUCT(MAX(('Payments Log'!$B$8:$B$207=$A41)*'Payments Log'!$E$8:$E$207)))) -> 46183 | V41: =IF($A41="","",IF($J41="","Not Delivered",IF($I41="","No Target Date",IF($J41<=$I41,"On Time","Late")))) -> On Time | W41: =IF($A41="","",IF($X41="","OK","REVIEW")) -> OK | X41: =IF($A41="","",TRIM(IF($B41="","Missing vendor ID. ","")&IF($C41="NOT FOUND","Vendor ID not in Vendor Master. ","")&IF(COUNTIFS('Invoice & Delivery Log'!$A$8:$A$157,$A41)>1,"Duplicate invoice ID. ","")&IF(AND($D41<>"",COUNTIFS('Invoice & Delivery Log'!$D$8:$D$157,$D41,'Invoice & Delivery Log'!$B$8:$B$157,$B41)>1),"Duplicate supplier invoice number. ","")&IF($E41="","Missing PO number. ","")&IF($H41="","Missing invoice date. ","")&IF(N($N41)<=0,"Invoice amount must be greater than zero. ","")&IF(AND($H41<>"",$H41>Settings!$C$5),"Invoice date is in the future. ","")&IF(AND($K41="Received in Full",$J41=""),"Missing actual delivery date. ","")&IF(ROUND(N($O41)-N($N41),2)>0,"Payments exceed the invoice amount. ","")&IF(AND($K41="Rejected",N($O41)>0),"Payment made on a rejected delivery. ","")&IF(AND($B41<>"",IFERROR(INDEX('Vendor Master'!$H$8:$H$47,MATCH($B41,'Vendor Master'!$A$8:$A$47,0)),"")="Inactive",ROUND(N($P41),2)>0),"Open balance with an inactive vendor. ",""))) | Y41: =IF($A41="","",IF(ROUND($P41,2)>0.004,"Yes","No")) -> Yes | Z41: =IF(OR($Y41<>"Yes",$M41=""),"",COUNTIFS('Invoice & Delivery Log'!$Y$8:$Y$157,"Yes",'Invoice & Delivery Log'!$M$8:$M$157,"<"&$M41)+COUNTIFS('Invoice & Delivery Log'!$Y$8:$Y$157,"Yes",'Invoice & Delivery Log'!$M$8:$M$157,$M41,'Invoice & Delivery Log'!$A$8:$A$157,"<"&$A41)+1) -> 6
A42: INV-1035 | B42: VEN-004 | C42: =IF($B42="","",IFERROR(INDEX('Vendor Master'!$B$8:$B$47,MATCH($B42,'Vendor Master'!$A$8:$A$47,0)),"NOT FOUND")) -> Lakeshore Packaging Group | D42: LPG-2026004 | E42: PO-2026-0035 | F42: =IF($B42="","",IFERROR(INDEX('Vendor Master'!$C$8:$C$47,MATCH($B42,'Vendor Master'!$A$8:$A$47,0)),"")) -> Packaging | G42: Corrugated boxes | H42: 46178 | I42: 46178 | J42: 46178 | K42: Received in Full | L42: =IF($B42="","",IFERROR(INDEX('Vendor Master'!$G$8:$G$47,MATCH($B42,'Vendor Master'!$A$8:$A$47,0)),"")) -> 30 | M42: =IF(OR($H42="",$L42=""),"",$H42+$L42) -> 46208 | N42: 6907.1 | O42: =IF($A42="","",SUMIFS('Payments Log'!$F$8:$F$207,'Payments Log'!$B$8:$B$207,$A42)) -> 6907.1 | P42: =IF($A42="","",ROUND($N42-$O42,2)) -> 0 | Q42: =IF($A42="","",IF(N($N42)<=0,"Check Amount",IF(ROUND($O42,2)<=0,"Unpaid",IF(ROUND($O42-$N42,2)>0,"Overpaid",IF(ROUND($P42,2)<=0,"Paid","Partially Paid"))))) -> Paid | R42: =IF(OR($A42="",$M42=""),"",IF(ROUND($P42,2)<=0,0,MAX(0,Settings!$C$5-$M42-Settings!$C$7))) -> 0 | S42: =IF($A42="","",IF(N($R42)>0,MAX($P42,0),0)) -> 0 | T42: =IF($A42="","",IF(ROUND($P42,2)<0,"Supplier Credit",IF(ROUND($P42,2)=0,"Closed",IF($M42="","No Due Date",IF(N($R42)<=0,"Not Due Yet",IF(N($R42)<=Settings!$C$8,"1-30 Days Overdue",IF(N($R42)<=Settings!$C$9,"31-60 Days Overdue",IF(N($R42)<=Settings!$C$10,"61-90 Days Overdue","90+ Days Overdue")))))))) -> Closed | U42: =IF($A42="","",IF(COUNTIFS('Payments Log'!$B$8:$B$207,$A42)=0,"",SUMPRODUCT(MAX(('Payments Log'!$B$8:$B$207=$A42)*'Payments Log'!$E$8:$E$207)))) -> 46204 | V42: =IF($A42="","",IF($J42="","Not Delivered",IF($I42="","No Target Date",IF($J42<=$I42,"On Time","Late")))) -> On Time | W42: =IF($A42="","",IF($X42="","OK","REVIEW")) -> OK | X42: =IF($A42="","",TRIM(IF($B42="","Missing vendor ID. ","")&IF($C42="NOT FOUND","Vendor ID not in Vendor Master. ","")&IF(COUNTIFS('Invoice & Delivery Log'!$A$8:$A$157,$A42)>1,"Duplicate invoice ID. ","")&IF(AND($D42<>"",COUNTIFS('Invoice & Delivery Log'!$D$8:$D$157,$D42,'Invoice & Delivery Log'!$B$8:$B$157,$B42)>1),"Duplicate supplier invoice number. ","")&IF($E42="","Missing PO number. ","")&IF($H42="","Missing invoice date. ","")&IF(N($N42)<=0,"Invoice amount must be greater than zero. ","")&IF(AND($H42<>"",$H42>Settings!$C$5),"Invoice date is in the future. ","")&IF(AND($K42="Received in Full",$J42=""),"Missing actual delivery date. ","")&IF(ROUND(N($O42)-N($N42),2)>0,"Payments exceed the invoice amount. ","")&IF(AND($K42="Rejected",N($O42)>0),"Payment made on a rejected delivery. ","")&IF(AND($B42<>"",IFERROR(INDEX('Vendor Master'!$H$8:$H$47,MATCH($B42,'Vendor Master'!$A$8:$A$47,0)),"")="Inactive",ROUND(N($P42),2)>0),"Open balance with an inactive vendor. ",""))) | Y42: =IF($A42="","",IF(ROUND($P42,2)>0.004,"Yes","No")) -> No | Z42: =IF(OR($Y42<>"Yes",$M42=""),"",COUNTIFS('Invoice & Delivery Log'!$Y$8:$Y$157,"Yes",'Invoice & Delivery Log'!$M$8:$M$157,"<"&$M42)+COUNTIFS('Invoice & Delivery Log'!$Y$8:$Y$157,"Yes",'Invoice & Delivery Log'!$M$8:$M$157,$M42,'Invoice & Delivery Log'!$A$8:$A$157,"<"&$A42)+1)
A43: INV-1036 | B43: VEN-007 | C43: =IF($B43="","",IFERROR(INDEX('Vendor Master'!$B$8:$B$47,MATCH($B43,'Vendor Master'!$A$8:$A$47,0)),"NOT FOUND")) -> Bluepoint Electrical Supply | D43: BES-2026002 | E43: PO-2026-0036 | F43: =IF($B43="","",IFERROR(INDEX('Vendor Master'!$C$8:$C$47,MATCH($B43,'Vendor Master'!$A$8:$A$47,0)),"")) -> Electrical | G43: Electrical panel parts | H43: 46178 | I43: 46179 | J43: 46177 | K43: Received in Full | L43: =IF($B43="","",IFERROR(INDEX('Vendor Master'!$G$8:$G$47,MATCH($B43,'Vendor Master'!$A$8:$A$47,0)),"")) -> 30 | M43: =IF(OR($H43="",$L43=""),"",$H43+$L43) -> 46208 | N43: 1655.25 | O43: =IF($A43="","",SUMIFS('Payments Log'!$F$8:$F$207,'Payments Log'!$B$8:$B$207,$A43)) -> 1655.25 | P43: =IF($A43="","",ROUND($N43-$O43,2)) -> 0 | Q43: =IF($A43="","",IF(N($N43)<=0,"Check Amount",IF(ROUND($O43,2)<=0,"Unpaid",IF(ROUND($O43-$N43,2)>0,"Overpaid",IF(ROUND($P43,2)<=0,"Paid","Partially Paid"))))) -> Paid | R43: =IF(OR($A43="",$M43=""),"",IF(ROUND($P43,2)<=0,0,MAX(0,Settings!$C$5-$M43-Settings!$C$7))) -> 0 | S43: =IF($A43="","",IF(N($R43)>0,MAX($P43,0),0)) -> 0 | T43: =IF($A43="","",IF(ROUND($P43,2)<0,"Supplier Credit",IF(ROUND($P43,2)=0,"Closed",IF($M43="","No Due Date",IF(N($R43)<=0,"Not Due Yet",IF(N($R43)<=Settings!$C$8,"1-30 Days Overdue",IF(N($R43)<=Settings!$C$9,"31-60 Days Overdue",IF(N($R43)<=Settings!$C$10,"61-90 Days Overdue","90+ Days Overdue")))))))) -> Closed | U43: =IF($A43="","",IF(COUNTIFS('Payments Log'!$B$8:$B$207,$A43)=0,"",SUMPRODUCT(MAX(('Payments Log'!$B$8:$B$207=$A43)*'Payments Log'!$E$8:$E$207)))) -> 46191 | V43: =IF($A43="","",IF($J43="","Not Delivered",IF($I43="","No Target Date",IF($J43<=$I43,"On Time","Late")))) -> On Time | W43: =IF($A43="","",IF($X43="","OK","REVIEW")) -> OK | X43: =IF($A43="","",TRIM(IF($B43="","Missing vendor ID. ","")&IF($C43="NOT FOUND","Vendor ID not in Vendor Master. ","")&IF(COUNTIFS('Invoice & Delivery Log'!$A$8:$A$157,$A43)>1,"Duplicate invoice ID. ","")&IF(AND($D43<>"",COUNTIFS('Invoice & Delivery Log'!$D$8:$D$157,$D43,'Invoice & Delivery Log'!$B$8:$B$157,$B43)>1),"Duplicate supplier invoice number. ","")&IF($E43="","Missing PO number. ","")&IF($H43="","Missing invoice date. ","")&IF(N($N43)<=0,"Invoice amount must be greater than zero. ","")&IF(AND($H43<>"",$H43>Settings!$C$5),"Invoice date is in the future. ","")&IF(AND($K43="Received in Full",$J43=""),"Missing actual delivery date. ","")&IF(ROUND(N($O43)-N($N43),2)>0,"Payments exceed the invoice amount. ","")&IF(AND($K43="Rejected",N($O43)>0),"Payment made on a rejected delivery. ","")&IF(AND($B43<>"",IFERROR(INDEX('Vendor Master'!$H$8:$H$47,MATCH($B43,'Vendor Master'!$A$8:$A$47,0)),"")="Inactive",ROUND(N($P43),2)>0),"Open balance with an inactive vendor. ",""))) | Y43: =IF($A43="","",IF(ROUND($P43,2)>0.004,"Yes","No")) -> No | Z43: =IF(OR($Y43<>"Yes",$M43=""),"",COUNTIFS('Invoice & Delivery Log'!$Y$8:$Y$157,"Yes",'Invoice & Delivery Log'!$M$8:$M$157,"<"&$M43)+COUNTIFS('Invoice & Delivery Log'!$Y$8:$Y$157,"Yes",'Invoice & Delivery Log'!$M$8:$M$157,$M43,'Invoice & Delivery Log'!$A$8:$A$157,"<"&$A43)+1)
A44: INV-1037 | B44: VEN-004 | C44: =IF($B44="","",IFERROR(INDEX('Vendor Master'!$B$8:$B$47,MATCH($B44,'Vendor Master'!$A$8:$A$47,0)),"NOT FOUND")) -> Lakeshore Packaging Group | D44: LPG-2026005 | E44: PO-2026-0037 | F44: =IF($B44="","",IFERROR(INDEX('Vendor Master'!$C$8:$C$47,MATCH($B44,'Vendor Master'!$A$8:$A$47,0)),"")) -> Packaging | G44: Shipping labels and tape | H44: 46189 | I44: 46188 | J44: 46186 | K44: Received in Full | L44: =IF($B44="","",IFERROR(INDEX('Vendor Master'!$G$8:$G$47,MATCH($B44,'Vendor Master'!$A$8:$A$47,0)),"")) -> 30 | M44: =IF(OR($H44="",$L44=""),"",$H44+$L44) -> 46219 | N44: 4413.48 | O44: =IF($A44="","",SUMIFS('Payments Log'!$F$8:$F$207,'Payments Log'!$B$8:$B$207,$A44)) -> 2472.37 | P44: =IF($A44="","",ROUND($N44-$O44,2)) -> 1941.11 | Q44: =IF($A44="","",IF(N($N44)<=0,"Check Amount",IF(ROUND($O44,2)<=0,"Unpaid",IF(ROUND($O44-$N44,2)>0,"Overpaid",IF(ROUND($P44,2)<=0,"Paid","Partially Paid"))))) -> Partially Paid | R44: =IF(OR($A44="",$M44=""),"",IF(ROUND($P44,2)<=0,0,MAX(0,Settings!$C$5-$M44-Settings!$C$7))) -> 53 | S44: =IF($A44="","",IF(N($R44)>0,MAX($P44,0),0)) -> 1941.11 | T44: =IF($A44="","",IF(ROUND($P44,2)<0,"Supplier Credit",IF(ROUND($P44,2)=0,"Closed",IF($M44="","No Due Date",IF(N($R44)<=0,"Not Due Yet",IF(N($R44)<=Settings!$C$8,"1-30 Days Overdue",IF(N($R44)<=Settings!$C$9,"31-60 Days Overdue",IF(N($R44)<=Settings!$C$10,"61-90 Days Overdue","90+ Days Overdue")))))))) -> 31-60 Days Overdue | U44: =IF($A44="","",IF(COUNTIFS('Payments Log'!$B$8:$B$207,$A44)=0,"",SUMPRODUCT(MAX(('Payments Log'!$B$8:$B$207=$A44)*'Payments Log'!$E$8:$E$207)))) -> 46202 | V44: =IF($A44="","",IF($J44="","Not Delivered",IF($I44="","No Target Date",IF($J44<=$I44,"On Time","Late")))) -> On Time | W44: =IF($A44="","",IF($X44="","OK","REVIEW")) -> OK | X44: =IF($A44="","",TRIM(IF($B44="","Missing vendor ID. ","")&IF($C44="NOT FOUND","Vendor ID not in Vendor Master. ","")&IF(COUNTIFS('Invoice & Delivery Log'!$A$8:$A$157,$A44)>1,"Duplicate invoice ID. ","")&IF(AND($D44<>"",COUNTIFS('Invoice & Delivery Log'!$D$8:$D$157,$D44,'Invoice & Delivery Log'!$B$8:$B$157,$B44)>1),"Duplicate supplier invoice number. ","")&IF($E44="","Missing PO number. ","")&IF($H44="","Missing invoice date. ","")&IF(N($N44)<=0,"Invoice amount must be greater than zero. ","")&IF(AND($H44<>"",$H44>Settings!$C$5),"Invoice date is in the future. ","")&IF(AND($K44="Received in Full",$J44=""),"Missing actual delivery date. ","")&IF(ROUND(N($O44)-N($N44),2)>0,"Payments exceed the invoice amount. ","")&IF(AND($K44="Rejected",N($O44)>0),"Payment made on a rejected delivery. ","")&IF(AND($B44<>"",IFERROR(INDEX('Vendor Master'!$H$8:$H$47,MATCH($B44,'Vendor Master'!$A$8:$A$47,0)),"")="Inactive",ROUND(N($P44),2)>0),"Open balance with an inactive vendor. ",""))) | Y44: =IF($A44="","",IF(ROUND($P44,2)>0.004,"Yes","No")) -> Yes | Z44: =IF(OR($Y44<>"Yes",$M44=""),"",COUNTIFS('Invoice & Delivery Log'!$Y$8:$Y$157,"Yes",'Invoice & Delivery Log'!$M$8:$M$157,"<"&$M44)+COUNTIFS('Invoice & Delivery Log'!$Y$8:$Y$157,"Yes",'Invoice & Delivery Log'!$M$8:$M$157,$M44,'Invoice & Delivery Log'!$A$8:$A$157,"<"&$A44)+1) -> 7
A45: INV-1038 | B45: VEN-005 | C45: =IF($B45="","",IFERROR(INDEX('Vendor Master'!$B$8:$B$47,MATCH($B45,'Vendor Master'!$A$8:$A$47,0)),"NOT FOUND")) -> Summit Cleaning Services | D45: SCS-2026004 | E45: PO-2026-0038 | F45: =IF($B45="","",IFERROR(INDEX('Vendor Master'!$C$8:$C$47,MATCH($B45,'Vendor Master'!$A$8:$A$47,0)),"")) -> Facility Services | G45: Deep clean - warehouse | H45: 46195 | I45: 46192 | J45: 46192 | K45: Received in Full | L45: =IF($B45="","",IFERROR(INDEX('Vendor Master'!$G$8:$G$47,MATCH($B45,'Vendor Master'!$A$8:$A$47,0)),"")) -> 14 | M45: =IF(OR($H45="",$L45=""),"",$H45+$L45) -> 46209 | N45: 1862.04 | O45: =IF($A45="","",SUMIFS('Payments Log'!$F$8:$F$207,'Payments Log'!$B$8:$B$207,$A45)) -> 1862.04 | P45: =IF($A45="","",ROUND($N45-$O45,2)) -> 0 | Q45: =IF($A45="","",IF(N($N45)<=0,"Check Amount",IF(ROUND($O45,2)<=0,"Unpaid",IF(ROUND($O45-$N45,2)>0,"Overpaid",IF(ROUND($P45,2)<=0,"Paid","Partially Paid"))))) -> Paid | R45: =IF(OR($A45="",$M45=""),"",IF(ROUND($P45,2)<=0,0,MAX(0,Settings!$C$5-$M45-Settings!$C$7))) -> 0 | S45: =IF($A45="","",IF(N($R45)>0,MAX($P45,0),0)) -> 0 | T45: =IF($A45="","",IF(ROUND($P45,2)<0,"Supplier Credit",IF(ROUND($P45,2)=0,"Closed",IF($M45="","No Due Date",IF(N($R45)<=0,"Not Due Yet",IF(N($R45)<=Settings!$C$8,"1-30 Days Overdue",IF(N($R45)<=Settings!$C$9,"31-60 Days Overdue",IF(N($R45)<=Settings!$C$10,"61-90 Days Overdue","90+ Days Overdue")))))))) -> Closed | U45: =IF($A45="","",IF(COUNTIFS('Payments Log'!$B$8:$B$207,$A45)=0,"",SUMPRODUCT(MAX(('Payments Log'!$B$8:$B$207=$A45)*'Payments Log'!$E$8:$E$207)))) -> 46201 | V45: =IF($A45="","",IF($J45="","Not Delivered",IF($I45="","No Target Date",IF($J45<=$I45,"On Time","Late")))) -> On Time | W45: =IF($A45="","",IF($X45="","OK","REVIEW")) -> OK | X45: =IF($A45="","",TRIM(IF($B45="","Missing vendor ID. ","")&IF($C45="NOT FOUND","Vendor ID not in Vendor Master. ","")&IF(COUNTIFS('Invoice & Delivery Log'!$A$8:$A$157,$A45)>1,"Duplicate invoice ID. ","")&IF(AND($D45<>"",COUNTIFS('Invoice & Delivery Log'!$D$8:$D$157,$D45,'Invoice & Delivery Log'!$B$8:$B$157,$B45)>1),"Duplicate supplier invoice number. ","")&IF($E45="","Missing PO number. ","")&IF($H45="","Missing invoice date. ","")&IF(N($N45)<=0,"Invoice amount must be greater than zero. ","")&IF(AND($H45<>"",$H45>Settings!$C$5),"Invoice date is in the future. ","")&IF(AND($K45="Received in Full",$J45=""),"Missing actual delivery date. ","")&IF(ROUND(N($O45)-N($N45),2)>0,"Payments exceed the invoice amount. ","")&IF(AND($K45="Rejected",N($O45)>0),"Payment made on a rejected delivery. ","")&IF(AND($B45<>"",IFERROR(INDEX('Vendor Master'!$H$8:$H$47,MATCH($B45,'Vendor Master'!$A$8:$A$47,0)),"")="Inactive",ROUND(N($P45),2)>0),"Open balance with an inactive vendor. ",""))) | Y45: =IF($A45="","",IF(ROUND($P45,2)>0.004,"Yes","No")) -> No | Z45: =IF(OR($Y45<>"Yes",$M45=""),"",COUNTIFS('Invoice & Delivery Log'!$Y$8:$Y$157,"Yes",'Invoice & Delivery Log'!$M$8:$M$157,"<"&$M45)+COUNTIFS('Invoice & Delivery Log'!$Y$8:$Y$157,"Yes",'Invoice & Delivery Log'!$M$8:$M$157,$M45,'Invoice & Delivery Log'!$A$8:$A$157,"<"&$A45)+1)
... A67: INV-1060 | B67: VEN-004 | C67: =IF($B67="","",IFERROR(INDEX('Vendor Master'!$B$8:$B$47,MATCH($B67,'Vendor Master'!$A$8:$A$47,0)),"NOT FOUND")) -> Lakeshore Packaging Group | D67: LPG-2026007 | E67: PO-2026-0060 | F67: =IF($B67="","",IFERROR(INDEX('Vendor Master'!$C$8:$C$47,MATCH($B67,'Vendor Master'!$A$8:$A$47,0)),"")) -> Packaging | G67: Pallet wrap | H67: 46271 | I67: 46269 | J67: 46269 | K67: Received in Full | L67: =IF($B67="","",IFERROR(INDEX('Vendor Master'!$G$8:$G$47,MATCH($B67,'Vendor Master'!$A$8:$A$47,0)),"")) -> 30 | M67: =IF(OR($H67="",$L67=""),"",$H67+$L67) -> 46301 | N67: 1791.7 | O67: =IF($A67="","",SUMIFS('Payments Log'!$F$8:$F$207,'Payments Log'!$B$8:$B$207,$A67)) -> 0 | P67: =IF($A67="","",ROUND($N67-$O67,2)) -> 1791.7 | Q67: =IF($A67="","",IF(N($N67)<=0,"Check Amount",IF(ROUND($O67,2)<=0,"Unpaid",IF(ROUND($O67-$N67,2)>0,"Overpaid",IF(ROUND($P67,2)<=0,"Paid","Partially Paid"))))) -> Unpaid | R67: =IF(OR($A67="",$M67=""),"",IF(ROUND($P67,2)<=0,0,MAX(0,Settings!$C$5-$M67-Settings!$C$7))) -> 0 | S67: =IF($A67="","",IF(N($R67)>0,MAX($P67,0),0)) -> 0 | T67: =IF($A67="","",IF(ROUND($P67,2)<0,"Supplier Credit",IF(ROUND($P67,2)=0,"Closed",IF($M67="","No Due Date",IF(N($R67)<=0,"Not Due Yet",IF(N($R67)<=Settings!$C$8,"1-30 Days Overdue",IF(N($R67)<=Settings!$C$9,"31-60 Days Overdue",IF(N($R67)<=Settings!$C$10,"61-90 Days Overdue","90+ Days Overdue")))))))) -> Not Due Yet | U67: =IF($A67="","",IF(COUNTIFS('Payments Log'!$B$8:$B$207,$A67)=0,"",SUMPRODUCT(MAX(('Payments Log'!$B$8:$B$207=$A67)*'Payments Log'!$E$8:$E$207)))) | V67: =IF($A67="","",IF($J67="","Not Delivered",IF($I67="","No Target Date",IF($J67<=$I67,"On Time","Late")))) -> On Time | W67: =IF($A67="","",IF($X67="","OK","REVIEW")) -> OK | X67: =IF($A67="","",TRIM(IF($B67="","Missing vendor ID. ","")&IF($C67="NOT FOUND","Vendor ID not in Vendor Master. ","")&IF(COUNTIFS('Invoice & Delivery Log'!$A$8:$A$157,$A67)>1,"Duplicate invoice ID. ","")&IF(AND($D67<>"",COUNTIFS('Invoice & Delivery Log'!$D$8:$D$157,$D67,'Invoice & Delivery Log'!$B$8:$B$157,$B67)>1),"Duplicate supplier invoice number. ","")&IF($E67="","Missing PO number. ","")&IF($H67="","Missing invoice date. ","")&IF(N($N67)<=0,"Invoice amount must be greater than zero. ","")&IF(AND($H67<>"",$H67>Settings!$C$5),"Invoice date is in the future. ","")&IF(AND($K67="Received in Full",$J67=""),"Missing actual delivery date. ","")&IF(ROUND(N($O67)-N($N67),2)>0,"Payments exceed the invoice amount. ","")&IF(AND($K67="Rejected",N($O67)>0),"Payment made on a rejected delivery. ","")&IF(AND($B67<>"",IFERROR(INDEX('Vendor Master'!$H$8:$H$47,MATCH($B67,'Vendor Master'!$A$8:$A$47,0)),"")="Inactive",ROUND(N($P67),2)>0),"Open balance with an inactive vendor. ",""))) | Y67: =IF($A67="","",IF(ROUND($P67,2)>0.004,"Yes","No")) -> Yes | Z67: =IF(OR($Y67<>"Yes",$M67=""),"",COUNTIFS('Invoice & Delivery Log'!$Y$8:$Y$157,"Yes",'Invoice & Delivery Log'!$M$8:$M$157,"<"&$M67)+COUNTIFS('Invoice & Delivery Log'!$Y$8:$Y$157,"Yes",'Invoice & Delivery Log'!$M$8:$M$157,$M67,'Invoice & Delivery Log'!$A$8:$A$157,"<"&$A67)+1) -> 17
C68: =IF($B68="","",IFERROR(INDEX('Vendor Master'!$B$8:$B$47,MATCH($B68,'Vendor Master'!$A$8:$A$47,0)),"NOT FOUND")) | F68: =IF($B68="","",IFERROR(INDEX('Vendor Master'!$C$8:$C$47,MATCH($B68,'Vendor Master'!$A$8:$A$47,0)),"")) | L68: =IF($B68="","",IFERROR(INDEX('Vendor Master'!$G$8:$G$47,MATCH($B68,'Vendor Master'!$A$8:$A$47,0)),"")) | M68: =IF(OR($H68="",$L68=""),"",$H68+$L68) | O68: =IF($A68="","",SUMIFS('Payments Log'!$F$8:$F$207,'Payments Log'!$B$8:$B$207,$A68)) | P68: =IF($A68="","",ROUND($N68-$O68,2)) | Q68: =IF($A68="","",IF(N($N68)<=0,"Check Amount",IF(ROUND($O68,2)<=0,"Unpaid",IF(ROUND($O68-$N68,2)>0,"Overpaid",IF(ROUND($P68,2)<=0,"Paid","Partially Paid"))))) | R68: =IF(OR($A68="",$M68=""),"",IF(ROUND($P68,2)<=0,0,MAX(0,Settings!$C$5-$M68-Settings!$C$7))) | S68: =IF($A68="","",IF(N($R68)>0,MAX($P68,0),0)) | T68: =IF($A68="","",IF(ROUND($P68,2)<0,"Supplier Credit",IF(ROUND($P68,2)=0,"Closed",IF($M68="","No Due Date",IF(N($R68)<=0,"Not Due Yet",IF(N($R68)<=Settings!$C$8,"1-30 Days Overdue",IF(N($R68)<=Settings!$C$9,"31-60 Days Overdue",IF(N($R68)<=Settings!$C$10,"61-90 Days Overdue","90+ Days Overdue")))))))) | U68: =IF($A68="","",IF(COUNTIFS('Payments Log'!$B$8:$B$207,$A68)=0,"",SUMPRODUCT(MAX(('Payments Log'!$B$8:$B$207=$A68)*'Payments Log'!$E$8:$E$207)))) | V68: =IF($A68="","",IF($J68="","Not Delivered",IF($I68="","No Target Date",IF($J68<=$I68,"On Time","Late")))) | W68: =IF($A68="","",IF($X68="","OK","REVIEW")) | X68: =IF($A68="","",TRIM(IF($B68="","Missing vendor ID. ","")&IF($C68="NOT FOUND","Vendor ID not in Vendor Master. ","")&IF(COUNTIFS('Invoice & Delivery Log'!$A$8:$A$157,$A68)>1,"Duplicate invoice ID. ","")&IF(AND($D68<>"",COUNTIFS('Invoice & Delivery Log'!$D$8:$D$157,$D68,'Invoice & Delivery Log'!$B$8:$B$157,$B68)>1),"Duplicate supplier invoice number. ","")&IF($E68="","Missing PO number. ","")&IF($H68="","Missing invoice date. ","")&IF(N($N68)<=0,"Invoice amount must be greater than zero. ","")&IF(AND($H68<>"",$H68>Settings!$C$5),"Invoice date is in the future. ","")&IF(AND($K68="Received in Full",$J68=""),"Missing actual delivery date. ","")&IF(ROUND(N($O68)-N($N68),2)>0,"Payments exceed the invoice amount. ","")&IF(AND($K68="Rejected",N($O68)>0),"Payment made on a rejected delivery. ","")&IF(AND($B68<>"",IFERROR(INDEX('Vendor Master'!$H$8:$H$47,MATCH($B68,'Vendor Master'!$A$8:$A$47,0)),"")="Inactive",ROUND(N($P68),2)>0),"Open balance with an inactive vendor. ",""))) | Y68: =IF($A68="","",IF(ROUND($P68,2)>0.004,"Yes","No")) | Z68: =IF(OR($Y68<>"Yes",$M68=""),"",COUNTIFS('Invoice & Delivery Log'!$Y$8:$Y$157,"Yes",'Invoice & Delivery Log'!$M$8:$M$157,"<"&$M68)+COUNTIFS('Invoice & Delivery Log'!$Y$8:$Y$157,"Yes",'Invoice & Delivery Log'!$M$8:$M$157,$M68,'Invoice & Delivery Log'!$A$8:$A$157,"<"&$A68)+1)
C69: =IF($B69="","",IFERROR(INDEX('Vendor Master'!$B$8:$B$47,MATCH($B69,'Vendor Master'!$A$8:$A$47,0)),"NOT FOUND")) | F69: =IF($B69="","",IFERROR(INDEX('Vendor Master'!$C$8:$C$47,MATCH($B69,'Vendor Master'!$A$8:$A$47,0)),"")) | L69: =IF($B69="","",IFERROR(INDEX('Vendor Master'!$G$8:$G$47,MATCH($B69,'Vendor Master'!$A$8:$A$47,0)),"")) | M69: =IF(OR($H69="",$L69=""),"",$H69+$L69) | O69: =IF($A69="","",SUMIFS('Payments Log'!$F$8:$F$207,'Payments Log'!$B$8:$B$207,$A69)) | P69: =IF($A69="","",ROUND($N69-$O69,2)) | Q69: =IF($A69="","",IF(N($N69)<=0,"Check Amount",IF(ROUND($O69,2)<=0,"Unpaid",IF(ROUND($O69-$N69,2)>0,"Overpaid",IF(ROUND($P69,2)<=0,"Paid","Partially Paid"))))) | R69: =IF(OR($A69="",$M69=""),"",IF(ROUND($P69,2)<=0,0,MAX(0,Settings!$C$5-$M69-Settings!$C$7))) | S69: =IF($A69="","",IF(N($R69)>0,MAX($P69,0),0)) | T69: =IF($A69="","",IF(ROUND($P69,2)<0,"Supplier Credit",IF(ROUND($P69,2)=0,"Closed",IF($M69="","No Due Date",IF(N($R69)<=0,"Not Due Yet",IF(N($R69)<=Settings!$C$8,"1-30 Days Overdue",IF(N($R69)<=Settings!$C$9,"31-60 Days Overdue",IF(N($R69)<=Settings!$C$10,"61-90 Days Overdue","90+ Days Overdue")))))))) | U69: =IF($A69="","",IF(COUNTIFS('Payments Log'!$B$8:$B$207,$A69)=0,"",SUMPRODUCT(MAX(('Payments Log'!$B$8:$B$207=$A69)*'Payments Log'!$E$8:$E$207)))) | V69: =IF($A69="","",IF($J69="","Not Delivered",IF($I69="","No Target Date",IF($J69<=$I69,"On Time","Late")))) | W69: =IF($A69="","",IF($X69="","OK","REVIEW")) | X69: =IF($A69="","",TRIM(IF($B69="","Missing vendor ID. ","")&IF($C69="NOT FOUND","Vendor ID not in Vendor Master. ","")&IF(COUNTIFS('Invoice & Delivery Log'!$A$8:$A$157,$A69)>1,"Duplicate invoice ID. ","")&IF(AND($D69<>"",COUNTIFS('Invoice & Delivery Log'!$D$8:$D$157,$D69,'Invoice & Delivery Log'!$B$8:$B$157,$B69)>1),"Duplicate supplier invoice number. ","")&IF($E69="","Missing PO number. ","")&IF($H69="","Missing invoice date. ","")&IF(N($N69)<=0,"Invoice amount must be greater than zero. ","")&IF(AND($H69<>"",$H69>Settings!$C$5),"Invoice date is in the future. ","")&IF(AND($K69="Received in Full",$J69=""),"Missing actual delivery date. ","")&IF(ROUND(N($O69)-N($N69),2)>0,"Payments exceed the invoice amount. ","")&IF(AND($K69="Rejected",N($O69)>0),"Payment made on a rejected delivery. ","")&IF(AND($B69<>"",IFERROR(INDEX('Vendor Master'!$H$8:$H$47,MATCH($B69,'Vendor Master'!$A$8:$A$47,0)),"")="Inactive",ROUND(N($P69),2)>0),"Open balance with an inactive vendor. ",""))) | Y69: =IF($A69="","",IF(ROUND($P69,2)>0.004,"Yes","No")) | Z69: =IF(OR($Y69<>"Yes",$M69=""),"",COUNTIFS('Invoice & Delivery Log'!$Y$8:$Y$157,"Yes",'Invoice & Delivery Log'!$M$8:$M$157,"<"&$M69)+COUNTIFS('Invoice & Delivery Log'!$Y$8:$Y$157,"Yes",'Invoice & Delivery Log'!$M$8:$M$157,$M69,'Invoice & Delivery Log'!$A$8:$A$157,"<"&$A69)+1)
C70: =IF($B70="","",IFERROR(INDEX('Vendor Master'!$B$8:$B$47,MATCH($B70,'Vendor Master'!$A$8:$A$47,0)),"NOT FOUND")) | F70: =IF($B70="","",IFERROR(INDEX('Vendor Master'!$C$8:$C$47,MATCH($B70,'Vendor Master'!$A$8:$A$47,0)),"")) | L70: =IF($B70="","",IFERROR(INDEX('Vendor Master'!$G$8:$G$47,MATCH($B70,'Vendor Master'!$A$8:$A$47,0)),"")) | M70: =IF(OR($H70="",$L70=""),"",$H70+$L70) | O70: =IF($A70="","",SUMIFS('Payments Log'!$F$8:$F$207,'Payments Log'!$B$8:$B$207,$A70)) | P70: =IF($A70="","",ROUND($N70-$O70,2)) | Q70: =IF($A70="","",IF(N($N70)<=0,"Check Amount",IF(ROUND($O70,2)<=0,"Unpaid",IF(ROUND($O70-$N70,2)>0,"Overpaid",IF(ROUND($P70,2)<=0,"Paid","Partially Paid"))))) | R70: =IF(OR($A70="",$M70=""),"",IF(ROUND($P70,2)<=0,0,MAX(0,Settings!$C$5-$M70-Settings!$C$7))) | S70: =IF($A70="","",IF(N($R70)>0,MAX($P70,0),0)) | T70: =IF($A70="","",IF(ROUND($P70,2)<0,"Supplier Credit",IF(ROUND($P70,2)=0,"Closed",IF($M70="","No Due Date",IF(N($R70)<=0,"Not Due Yet",IF(N($R70)<=Settings!$C$8,"1-30 Days Overdue",IF(N($R70)<=Settings!$C$9,"31-60 Days Overdue",IF(N($R70)<=Settings!$C$10,"61-90 Days Overdue","90+ Days Overdue")))))))) | U70: =IF($A70="","",IF(COUNTIFS('Payments Log'!$B$8:$B$207,$A70)=0,"",SUMPRODUCT(MAX(('Payments Log'!$B$8:$B$207=$A70)*'Payments Log'!$E$8:$E$207)))) | V70: =IF($A70="","",IF($J70="","Not Delivered",IF($I70="","No Target Date",IF($J70<=$I70,"On Time","Late")))) | W70: =IF($A70="","",IF($X70="","OK","REVIEW")) | X70: =IF($A70="","",TRIM(IF($B70="","Missing vendor ID. ","")&IF($C70="NOT FOUND","Vendor ID not in Vendor Master. ","")&IF(COUNTIFS('Invoice & Delivery Log'!$A$8:$A$157,$A70)>1,"Duplicate invoice ID. ","")&IF(AND($D70<>"",COUNTIFS('Invoice & Delivery Log'!$D$8:$D$157,$D70,'Invoice & Delivery Log'!$B$8:$B$157,$B70)>1),"Duplicate supplier invoice number. ","")&IF($E70="","Missing PO number. ","")&IF($H70="","Missing invoice date. ","")&IF(N($N70)<=0,"Invoice amount must be greater than zero. ","")&IF(AND($H70<>"",$H70>Settings!$C$5),"Invoice date is in the future. ","")&IF(AND($K70="Received in Full",$J70=""),"Missing actual delivery date. ","")&IF(ROUND(N($O70)-N($N70),2)>0,"Payments exceed the invoice amount. ","")&IF(AND($K70="Rejected",N($O70)>0),"Payment made on a rejected delivery. ","")&IF(AND($B70<>"",IFERROR(INDEX('Vendor Master'!$H$8:$H$47,MATCH($B70,'Vendor Master'!$A$8:$A$47,0)),"")="Inactive",ROUND(N($P70),2)>0),"Open balance with an inactive vendor. ",""))) | Y70: =IF($A70="","",IF(ROUND($P70,2)>0.004,"Yes","No")) | Z70: =IF(OR($Y70<>"Yes",$M70=""),"",COUNTIFS('Invoice & Delivery Log'!$Y$8:$Y$157,"Yes",'Invoice & Delivery Log'!$M$8:$M$157,"<"&$M70)+COUNTIFS('Invoice & Delivery Log'!$Y$8:$Y$157,"Yes",'Invoice & Delivery Log'!$M$8:$M$157,$M70,'Invoice & Delivery Log'!$A$8:$A$157,"<"&$A70)+1)
C71: =IF($B71="","",IFERROR(INDEX('Vendor Master'!$B$8:$B$47,MATCH($B71,'Vendor Master'!$A$8:$A$47,0)),"NOT FOUND")) | F71: =IF($B71="","",IFERROR(INDEX('Vendor Master'!$C$8:$C$47,MATCH($B71,'Vendor Master'!$A$8:$A$47,0)),"")) | L71: =IF($B71="","",IFERROR(INDEX('Vendor Master'!$G$8:$G$47,MATCH($B71,'Vendor Master'!$A$8:$A$47,0)),"")) | M71: =IF(OR($H71="",$L71=""),"",$H71+$L71) | O71: =IF($A71="","",SUMIFS('Payments Log'!$F$8:$F$207,'Payments Log'!$B$8:$B$207,$A71)) | P71: =IF($A71="","",ROUND($N71-$O71,2)) | Q71: =IF($A71="","",IF(N($N71)<=0,"Check Amount",IF(ROUND($O71,2)<=0,"Unpaid",IF(ROUND($O71-$N71,2)>0,"Overpaid",IF(ROUND($P71,2)<=0,"Paid","Partially Paid"))))) | R71: =IF(OR($A71="",$M71=""),"",IF(ROUND($P71,2)<=0,0,MAX(0,Settings!$C$5-$M71-Settings!$C$7))) | S71: =IF($A71="","",IF(N($R71)>0,MAX($P71,0),0)) | T71: =IF($A71="","",IF(ROUND($P71,2)<0,"Supplier Credit",IF(ROUND($P71,2)=0,"Closed",IF($M71="","No Due Date",IF(N($R71)<=0,"Not Due Yet",IF(N($R71)<=Settings!$C$8,"1-30 Days Overdue",IF(N($R71)<=Settings!$C$9,"31-60 Days Overdue",IF(N($R71)<=Settings!$C$10,"61-90 Days Overdue","90+ Days Overdue")))))))) | U71: =IF($A71="","",IF(COUNTIFS('Payments Log'!$B$8:$B$207,$A71)=0,"",SUMPRODUCT(MAX(('Payments Log'!$B$8:$B$207=$A71)*'Payments Log'!$E$8:$E$207)))) | V71: =IF($A71="","",IF($J71="","Not Delivered",IF($I71="","No Target Date",IF($J71<=$I71,"On Time","Late")))) | W71: =IF($A71="","",IF($X71="","OK","REVIEW")) | X71: =IF($A71="","",TRIM(IF($B71="","Missing vendor ID. ","")&IF($C71="NOT FOUND","Vendor ID not in Vendor Master. ","")&IF(COUNTIFS('Invoice & Delivery Log'!$A$8:$A$157,$A71)>1,"Duplicate invoice ID. ","")&IF(AND($D71<>"",COUNTIFS('Invoice & Delivery Log'!$D$8:$D$157,$D71,'Invoice & Delivery Log'!$B$8:$B$157,$B71)>1),"Duplicate supplier invoice number. ","")&IF($E71="","Missing PO number. ","")&IF($H71="","Missing invoice date. ","")&IF(N($N71)<=0,"Invoice amount must be greater than zero. ","")&IF(AND($H71<>"",$H71>Settings!$C$5),"Invoice date is in the future. ","")&IF(AND($K71="Received in Full",$J71=""),"Missing actual delivery date. ","")&IF(ROUND(N($O71)-N($N71),2)>0,"Payments exceed the invoice amount. ","")&IF(AND($K71="Rejected",N($O71)>0),"Payment made on a rejected delivery. ","")&IF(AND($B71<>"",IFERROR(INDEX('Vendor Master'!$H$8:$H$47,MATCH($B71,'Vendor Master'!$A$8:$A$47,0)),"")="Inactive",ROUND(N($P71),2)>0),"Open balance with an inactive vendor. ",""))) | Y71: =IF($A71="","",IF(ROUND($P71,2)>0.004,"Yes","No")) | Z71: =IF(OR($Y71<>"Yes",$M71=""),"",COUNTIFS('Invoice & Delivery Log'!$Y$8:$Y$157,"Yes",'Invoice & Delivery Log'!$M$8:$M$157,"<"&$M71)+COUNTIFS('Invoice & Delivery Log'!$Y$8:$Y$157,"Yes",'Invoice & Delivery Log'!$M$8:$M$157,$M71,'Invoice & Delivery Log'!$A$8:$A$157,"<"&$A71)+1)
C72: =IF($B72="","",IFERROR(INDEX('Vendor Master'!$B$8:$B$47,MATCH($B72,'Vendor Master'!$A$8:$A$47,0)),"NOT FOUND")) | F72: =IF($B72="","",IFERROR(INDEX('Vendor Master'!$C$8:$C$47,MATCH($B72,'Vendor Master'!$A$8:$A$47,0)),"")) | L72: =IF($B72="","",IFERROR(INDEX('Vendor Master'!$G$8:$G$47,MATCH($B72,'Vendor Master'!$A$8:$A$47,0)),"")) | M72: =IF(OR($H72="",$L72=""),"",$H72+$L72) | O72: =IF($A72="","",SUMIFS('Payments Log'!$F$8:$F$207,'Payments Log'!$B$8:$B$207,$A72)) | P72: =IF($A72="","",ROUND($N72-$O72,2)) | Q72: =IF($A72="","",IF(N($N72)<=0,"Check Amount",IF(ROUND($O72,2)<=0,"Unpaid",IF(ROUND($O72-$N72,2)>0,"Overpaid",IF(ROUND($P72,2)<=0,"Paid","Partially Paid"))))) | R72: =IF(OR($A72="",$M72=""),"",IF(ROUND($P72,2)<=0,0,MAX(0,Settings!$C$5-$M72-Settings!$C$7))) | S72: =IF($A72="","",IF(N($R72)>0,MAX($P72,0),0)) | T72: =IF($A72="","",IF(ROUND($P72,2)<0,"Supplier Credit",IF(ROUND($P72,2)=0,"Closed",IF($M72="","No Due Date",IF(N($R72)<=0,"Not Due Yet",IF(N($R72)<=Settings!$C$8,"1-30 Days Overdue",IF(N($R72)<=Settings!$C$9,"31-60 Days Overdue",IF(N($R72)<=Settings!$C$10,"61-90 Days Overdue","90+ Days Overdue")))))))) | U72: =IF($A72="","",IF(COUNTIFS('Payments Log'!$B$8:$B$207,$A72)=0,"",SUMPRODUCT(MAX(('Payments Log'!$B$8:$B$207=$A72)*'Payments Log'!$E$8:$E$207)))) | V72: =IF($A72="","",IF($J72="","Not Delivered",IF($I72="","No Target Date",IF($J72<=$I72,"On Time","Late")))) | W72: =IF($A72="","",IF($X72="","OK","REVIEW")) | X72: =IF($A72="","",TRIM(IF($B72="","Missing vendor ID. ","")&IF($C72="NOT FOUND","Vendor ID not in Vendor Master. ","")&IF(COUNTIFS('Invoice & Delivery Log'!$A$8:$A$157,$A72)>1,"Duplicate invoice ID. ","")&IF(AND($D72<>"",COUNTIFS('Invoice & Delivery Log'!$D$8:$D$157,$D72,'Invoice & Delivery Log'!$B$8:$B$157,$B72)>1),"Duplicate supplier invoice number. ","")&IF($E72="","Missing PO number. ","")&IF($H72="","Missing invoice date. ","")&IF(N($N72)<=0,"Invoice amount must be greater than zero. ","")&IF(AND($H72<>"",$H72>Settings!$C$5),"Invoice date is in the future. ","")&IF(AND($K72="Received in Full",$J72=""),"Missing actual delivery date. ","")&IF(ROUND(N($O72)-N($N72),2)>0,"Payments exceed the invoice amount. ","")&IF(AND($K72="Rejected",N($O72)>0),"Payment made on a rejected delivery. ","")&IF(AND($B72<>"",IFERROR(INDEX('Vendor Master'!$H$8:$H$47,MATCH($B72,'Vendor Master'!$A$8:$A$47,0)),"")="Inactive",ROUND(N($P72),2)>0),"Open balance with an inactive vendor. ",""))) | Y72: =IF($A72="","",IF(ROUND($P72,2)>0.004,"Yes","No")) | Z72: =IF(OR($Y72<>"Yes",$M72=""),"",COUNTIFS('Invoice & Delivery Log'!$Y$8:$Y$157,"Yes",'Invoice & Delivery Log'!$M$8:$M$157,"<"&$M72)+COUNTIFS('Invoice & Delivery Log'!$Y$8:$Y$157,"Yes",'Invoice & Delivery Log'!$M$8:$M$157,$M72,'Invoice & Delivery Log'!$A$8:$A$157,"<"&$A72)+1)
C73: =IF($B73="","",IFERROR(INDEX('Vendor Master'!$B$8:$B$47,MATCH($B73,'Vendor Master'!$A$8:$A$47,0)),"NOT FOUND")) | F73: =IF($B73="","",IFERROR(INDEX('Vendor Master'!$C$8:$C$47,MATCH($B73,'Vendor Master'!$A$8:$A$47,0)),"")) | L73: =IF($B73="","",IFERROR(INDEX('Vendor Master'!$G$8:$G$47,MATCH($B73,'Vendor Master'!$A$8:$A$47,0)),"")) | M73: =IF(OR($H73="",$L73=""),"",$H73+$L73) | O73: =IF($A73="","",SUMIFS('Payments Log'!$F$8:$F$207,'Payments Log'!$B$8:$B$207,$A73)) | P73: =IF($A73="","",ROUND($N73-$O73,2)) | Q73: =IF($A73="","",IF(N($N73)<=0,"Check Amount",IF(ROUND($O73,2)<=0,"Unpaid",IF(ROUND($O73-$N73,2)>0,"Overpaid",IF(ROUND($P73,2)<=0,"Paid","Partially Paid"))))) | R73: =IF(OR($A73="",$M73=""),"",IF(ROUND($P73,2)<=0,0,MAX(0,Settings!$C$5-$M73-Settings!$C$7))) | S73: =IF($A73="","",IF(N($R73)>0,MAX($P73,0),0)) | T73: =IF($A73="","",IF(ROUND($P73,2)<0,"Supplier Credit",IF(ROUND($P73,2)=0,"Closed",IF($M73="","No Due Date",IF(N($R73)<=0,"Not Due Yet",IF(N($R73)<=Settings!$C$8,"1-30 Days Overdue",IF(N($R73)<=Settings!$C$9,"31-60 Days Overdue",IF(N($R73)<=Settings!$C$10,"61-90 Days Overdue","90+ Days Overdue")))))))) | U73: =IF($A73="","",IF(COUNTIFS('Payments Log'!$B$8:$B$207,$A73)=0,"",SUMPRODUCT(MAX(('Payments Log'!$B$8:$B$207=$A73)*'Payments Log'!$E$8:$E$207)))) | V73: =IF($A73="","",IF($J73="","Not Delivered",IF($I73="","No Target Date",IF($J73<=$I73,"On Time","Late")))) | W73: =IF($A73="","",IF($X73="","OK","REVIEW")) | X73: =IF($A73="","",TRIM(IF($B73="","Missing vendor ID. ","")&IF($C73="NOT FOUND","Vendor ID not in Vendor Master. ","")&IF(COUNTIFS('Invoice & Delivery Log'!$A$8:$A$157,$A73)>1,"Duplicate invoice ID. ","")&IF(AND($D73<>"",COUNTIFS('Invoice & Delivery Log'!$D$8:$D$157,$D73,'Invoice & Delivery Log'!$B$8:$B$157,$B73)>1),"Duplicate supplier invoice number. ","")&IF($E73="","Missing PO number. ","")&IF($H73="","Missing invoice date. ","")&IF(N($N73)<=0,"Invoice amount must be greater than zero. ","")&IF(AND($H73<>"",$H73>Settings!$C$5),"Invoice date is in the future. ","")&IF(AND($K73="Received in Full",$J73=""),"Missing actual delivery date. ","")&IF(ROUND(N($O73)-N($N73),2)>0,"Payments exceed the invoice amount. ","")&IF(AND($K73="Rejected",N($O73)>0),"Payment made on a rejected delivery. ","")&IF(AND($B73<>"",IFERROR(INDEX('Vendor Master'!$H$8:$H$47,MATCH($B73,'Vendor Master'!$A$8:$A$47,0)),"")="Inactive",ROUND(N($P73),2)>0),"Open balance with an inactive vendor. ",""))) | Y73: =IF($A73="","",IF(ROUND($P73,2)>0.004,"Yes","No")) | Z73: =IF(OR($Y73<>"Yes",$M73=""),"",COUNTIFS('Invoice & Delivery Log'!$Y$8:$Y$157,"Yes",'Invoice & Delivery Log'!$M$8:$M$157,"<"&$M73)+COUNTIFS('Invoice & Delivery Log'!$Y$8:$Y$157,"Yes",'Invoice & Delivery Log'!$M$8:$M$157,$M73,'Invoice & Delivery Log'!$A$8:$A$157,"<"&$A73)+1)
C74: =IF($B74="","",IFERROR(INDEX('Vendor Master'!$B$8:$B$47,MATCH($B74,'Vendor Master'!$A$8:$A$47,0)),"NOT FOUND")) | F74: =IF($B74="","",IFERROR(INDEX('Vendor Master'!$C$8:$C$47,MATCH($B74,'Vendor Master'!$A$8:$A$47,0)),"")) | L74: =IF($B74="","",IFERROR(INDEX('Vendor Master'!$G$8:$G$47,MATCH($B74,'Vendor Master'!$A$8:$A$47,0)),"")) | M74: =IF(OR($H74="",$L74=""),"",$H74+$L74) | O74: =IF($A74="","",SUMIFS('Payments Log'!$F$8:$F$207,'Payments Log'!$B$8:$B$207,$A74)) | P74: =IF($A74="","",ROUND($N74-$O74,2)) | Q74: =IF($A74="","",IF(N($N74)<=0,"Check Amount",IF(ROUND($O74,2)<=0,"Unpaid",IF(ROUND($O74-$N74,2)>0,"Overpaid",IF(ROUND($P74,2)<=0,"Paid","Partially Paid"))))) | R74: =IF(OR($A74="",$M74=""),"",IF(ROUND($P74,2)<=0,0,MAX(0,Settings!$C$5-$M74-Settings!$C$7))) | S74: =IF($A74="","",IF(N($R74)>0,MAX($P74,0),0)) | T74: =IF($A74="","",IF(ROUND($P74,2)<0,"Supplier Credit",IF(ROUND($P74,2)=0,"Closed",IF($M74="","No Due Date",IF(N($R74)<=0,"Not Due Yet",IF(N($R74)<=Settings!$C$8,"1-30 Days Overdue",IF(N($R74)<=Settings!$C$9,"31-60 Days Overdue",IF(N($R74)<=Settings!$C$10,"61-90 Days Overdue","90+ Days Overdue")))))))) | U74: =IF($A74="","",IF(COUNTIFS('Payments Log'!$B$8:$B$207,$A74)=0,"",SUMPRODUCT(MAX(('Payments Log'!$B$8:$B$207=$A74)*'Payments Log'!$E$8:$E$207)))) | V74: =IF($A74="","",IF($J74="","Not Delivered",IF($I74="","No Target Date",IF($J74<=$I74,"On Time","Late")))) | W74: =IF($A74="","",IF($X74="","OK","REVIEW")) | X74: =IF($A74="","",TRIM(IF($B74="","Missing vendor ID. ","")&IF($C74="NOT FOUND","Vendor ID not in Vendor Master. ","")&IF(COUNTIFS('Invoice & Delivery Log'!$A$8:$A$157,$A74)>1,"Duplicate invoice ID. ","")&IF(AND($D74<>"",COUNTIFS('Invoice & Delivery Log'!$D$8:$D$157,$D74,'Invoice & Delivery Log'!$B$8:$B$157,$B74)>1),"Duplicate supplier invoice number. ","")&IF($E74="","Missing PO number. ","")&IF($H74="","Missing invoice date. ","")&IF(N($N74)<=0,"Invoice amount must be greater than zero. ","")&IF(AND($H74<>"",$H74>Settings!$C$5),"Invoice date is in the future. ","")&IF(AND($K74="Received in Full",$J74=""),"Missing actual delivery date. ","")&IF(ROUND(N($O74)-N($N74),2)>0,"Payments exceed the invoice amount. ","")&IF(AND($K74="Rejected",N($O74)>0),"Payment made on a rejected delivery. ","")&IF(AND($B74<>"",IFERROR(INDEX('Vendor Master'!$H$8:$H$47,MATCH($B74,'Vendor Master'!$A$8:$A$47,0)),"")="Inactive",ROUND(N($P74),2)>0),"Open balance with an inactive vendor. ",""))) | Y74: =IF($A74="","",IF(ROUND($P74,2)>0.004,"Yes","No")) | Z74: =IF(OR($Y74<>"Yes",$M74=""),"",COUNTIFS('Invoice & Delivery Log'!$Y$8:$Y$157,"Yes",'Invoice & Delivery Log'!$M$8:$M$157,"<"&$M74)+COUNTIFS('Invoice & Delivery Log'!$Y$8:$Y$157,"Yes",'Invoice & Delivery Log'!$M$8:$M$157,$M74,'Invoice & Delivery Log'!$A$8:$A$157,"<"&$A74)+1)
C75: =IF($B75="","",IFERROR(INDEX('Vendor Master'!$B$8:$B$47,MATCH($B75,'Vendor Master'!$A$8:$A$47,0)),"NOT FOUND")) | F75: =IF($B75="","",IFERROR(INDEX('Vendor Master'!$C$8:$C$47,MATCH($B75,'Vendor Master'!$A$8:$A$47,0)),"")) | L75: =IF($B75="","",IFERROR(INDEX('Vendor Master'!$G$8:$G$47,MATCH($B75,'Vendor Master'!$A$8:$A$47,0)),"")) | M75: =IF(OR($H75="",$L75=""),"",$H75+$L75) | O75: =IF($A75="","",SUMIFS('Payments Log'!$F$8:$F$207,'Payments Log'!$B$8:$B$207,$A75)) | P75: =IF($A75="","",ROUND($N75-$O75,2)) | Q75: =IF($A75="","",IF(N($N75)<=0,"Check Amount",IF(ROUND($O75,2)<=0,"Unpaid",IF(ROUND($O75-$N75,2)>0,"Overpaid",IF(ROUND($P75,2)<=0,"Paid","Partially Paid"))))) | R75: =IF(OR($A75="",$M75=""),"",IF(ROUND($P75,2)<=0,0,MAX(0,Settings!$C$5-$M75-Settings!$C$7))) | S75: =IF($A75="","",IF(N($R75)>0,MAX($P75,0),0)) | T75: =IF($A75="","",IF(ROUND($P75,2)<0,"Supplier Credit",IF(ROUND($P75,2)=0,"Closed",IF($M75="","No Due Date",IF(N($R75)<=0,"Not Due Yet",IF(N($R75)<=Settings!$C$8,"1-30 Days Overdue",IF(N($R75)<=Settings!$C$9,"31-60 Days Overdue",IF(N($R75)<=Settings!$C$10,"61-90 Days Overdue","90+ Days Overdue")))))))) | U75: =IF($A75="","",IF(COUNTIFS('Payments Log'!$B$8:$B$207,$A75)=0,"",SUMPRODUCT(MAX(('Payments Log'!$B$8:$B$207=$A75)*'Payments Log'!$E$8:$E$207)))) | V75: =IF($A75="","",IF($J75="","Not Delivered",IF($I75="","No Target Date",IF($J75<=$I75,"On Time","Late")))) | W75: =IF($A75="","",IF($X75="","OK","REVIEW")) | X75: =IF($A75="","",TRIM(IF($B75="","Missing vendor ID. ","")&IF($C75="NOT FOUND","Vendor ID not in Vendor Master. ","")&IF(COUNTIFS('Invoice & Delivery Log'!$A$8:$A$157,$A75)>1,"Duplicate invoice ID. ","")&IF(AND($D75<>"",COUNTIFS('Invoice & Delivery Log'!$D$8:$D$157,$D75,'Invoice & Delivery Log'!$B$8:$B$157,$B75)>1),"Duplicate supplier invoice number. ","")&IF($E75="","Missing PO number. ","")&IF($H75="","Missing invoice date. ","")&IF(N($N75)<=0,"Invoice amount must be greater than zero. ","")&IF(AND($H75<>"",$H75>Settings!$C$5),"Invoice date is in the future. ","")&IF(AND($K75="Received in Full",$J75=""),"Missing actual delivery date. ","")&IF(ROUND(N($O75)-N($N75),2)>0,"Payments exceed the invoice amount. ","")&IF(AND($K75="Rejected",N($O75)>0),"Payment made on a rejected delivery. ","")&IF(AND($B75<>"",IFERROR(INDEX('Vendor Master'!$H$8:$H$47,MATCH($B75,'Vendor Master'!$A$8:$A$47,0)),"")="Inactive",ROUND(N($P75),2)>0),"Open balance with an inactive vendor. ",""))) | Y75: =IF($A75="","",IF(ROUND($P75,2)>0.004,"Yes","No")) | Z75: =IF(OR($Y75<>"Yes",$M75=""),"",COUNTIFS('Invoice & Delivery Log'!$Y$8:$Y$157,"Yes",'Invoice & Delivery Log'!$M$8:$M$157,"<"&$M75)+COUNTIFS('Invoice & Delivery Log'!$Y$8:$Y$157,"Yes",'Invoice & Delivery Log'!$M$8:$M$157,$M75,'Invoice & Delivery Log'!$A$8:$A$157,"<"&$A75)+1)
C76: =IF($B76="","",IFERROR(INDEX('Vendor Master'!$B$8:$B$47,MATCH($B76,'Vendor Master'!$A$8:$A$47,0)),"NOT FOUND")) | F76: =IF($B76="","",IFERROR(INDEX('Vendor Master'!$C$8:$C$47,MATCH($B76,'Vendor Master'!$A$8:$A$47,0)),"")) | L76: =IF($B76="","",IFERROR(INDEX('Vendor Master'!$G$8:$G$47,MATCH($B76,'Vendor Master'!$A$8:$A$47,0)),"")) | M76: =IF(OR($H76="",$L76=""),"",$H76+$L76) | O76: =IF($A76="","",SUMIFS('Payments Log'!$F$8:$F$207,'Payments Log'!$B$8:$B$207,$A76)) | P76: =IF($A76="","",ROUND($N76-$O76,2)) | Q76: =IF($A76="","",IF(N($N76)<=0,"Check Amount",IF(ROUND($O76,2)<=0,"Unpaid",IF(ROUND($O76-$N76,2)>0,"Overpaid",IF(ROUND($P76,2)<=0,"Paid","Partially Paid"))))) | R76: =IF(OR($A76="",$M76=""),"",IF(ROUND($P76,2)<=0,0,MAX(0,Settings!$C$5-$M76-Settings!$C$7))) | S76: =IF($A76="","",IF(N($R76)>0,MAX($P76,0),0)) | T76: =IF($A76="","",IF(ROUND($P76,2)<0,"Supplier Credit",IF(ROUND($P76,2)=0,"Closed",IF($M76="","No Due Date",IF(N($R76)<=0,"Not Due Yet",IF(N($R76)<=Settings!$C$8,"1-30 Days Overdue",IF(N($R76)<=Settings!$C$9,"31-60 Days Overdue",IF(N($R76)<=Settings!$C$10,"61-90 Days Overdue","90+ Days Overdue")))))))) | U76: =IF($A76="","",IF(COUNTIFS('Payments Log'!$B$8:$B$207,$A76)=0,"",SUMPRODUCT(MAX(('Payments Log'!$B$8:$B$207=$A76)*'Payments Log'!$E$8:$E$207)))) | V76: =IF($A76="","",IF($J76="","Not Delivered",IF($I76="","No Target Date",IF($J76<=$I76,"On Time","Late")))) | W76: =IF($A76="","",IF($X76="","OK","REVIEW")) | X76: =IF($A76="","",TRIM(IF($B76="","Missing vendor ID. ","")&IF($C76="NOT FOUND","Vendor ID not in Vendor Master. ","")&IF(COUNTIFS('Invoice & Delivery Log'!$A$8:$A$157,$A76)>1,"Duplicate invoice ID. ","")&IF(AND($D76<>"",COUNTIFS('Invoice & Delivery Log'!$D$8:$D$157,$D76,'Invoice & Delivery Log'!$B$8:$B$157,$B76)>1),"Duplicate supplier invoice number. ","")&IF($E76="","Missing PO number. ","")&IF($H76="","Missing invoice date. ","")&IF(N($N76)<=0,"Invoice amount must be greater than zero. ","")&IF(AND($H76<>"",$H76>Settings!$C$5),"Invoice date is in the future. ","")&IF(AND($K76="Received in Full",$J76=""),"Missing actual delivery date. ","")&IF(ROUND(N($O76)-N($N76),2)>0,"Payments exceed the invoice amount. ","")&IF(AND($K76="Rejected",N($O76)>0),"Payment made on a rejected delivery. ","")&IF(AND($B76<>"",IFERROR(INDEX('Vendor Master'!$H$8:$H$47,MATCH($B76,'Vendor Master'!$A$8:$A$47,0)),"")="Inactive",ROUND(N($P76),2)>0),"Open balance with an inactive vendor. ",""))) | Y76: =IF($A76="","",IF(ROUND($P76,2)>0.004,"Yes","No")) | Z76: =IF(OR($Y76<>"Yes",$M76=""),"",COUNTIFS('Invoice & Delivery Log'!$Y$8:$Y$157,"Yes",'Invoice & Delivery Log'!$M$8:$M$157,"<"&$M76)+COUNTIFS('Invoice & Delivery Log'!$Y$8:$Y$157,"Yes",'Invoice & Delivery Log'!$M$8:$M$157,$M76,'Invoice & Delivery Log'!$A$8:$A$157,"<"&$A76)+1)
C77: =IF($B77="","",IFERROR(INDEX('Vendor Master'!$B$8:$B$47,MATCH($B77,'Vendor Master'!$A$8:$A$47,0)),"NOT FOUND")) | F77: =IF($B77="","",IFERROR(INDEX('Vendor Master'!$C$8:$C$47,MATCH($B77,'Vendor Master'!$A$8:$A$47,0)),"")) | L77: =IF($B77="","",IFERROR(INDEX('Vendor Master'!$G$8:$G$47,MATCH($B77,'Vendor Master'!$A$8:$A$47,0)),"")) | M77: =IF(OR($H77="",$L77=""),"",$H77+$L77) | O77: =IF($A77="","",SUMIFS('Payments Log'!$F$8:$F$207,'Payments Log'!$B$8:$B$207,$A77)) | P77: =IF($A77="","",ROUND($N77-$O77,2)) | Q77: =IF($A77="","",IF(N($N77)<=0,"Check Amount",IF(ROUND($O77,2)<=0,"Unpaid",IF(ROUND($O77-$N77,2)>0,"Overpaid",IF(ROUND($P77,2)<=0,"Paid","Partially Paid"))))) | R77: =IF(OR($A77="",$M77=""),"",IF(ROUND($P77,2)<=0,0,MAX(0,Settings!$C$5-$M77-Settings!$C$7))) | S77: =IF($A77="","",IF(N($R77)>0,MAX($P77,0),0)) | T77: =IF($A77="","",IF(ROUND($P77,2)<0,"Supplier Credit",IF(ROUND($P77,2)=0,"Closed",IF($M77="","No Due Date",IF(N($R77)<=0,"Not Due Yet",IF(N($R77)<=Settings!$C$8,"1-30 Days Overdue",IF(N($R77)<=Settings!$C$9,"31-60 Days Overdue",IF(N($R77)<=Settings!$C$10,"61-90 Days Overdue","90+ Days Overdue")))))))) | U77: =IF($A77="","",IF(COUNTIFS('Payments Log'!$B$8:$B$207,$A77)=0,"",SUMPRODUCT(MAX(('Payments Log'!$B$8:$B$207=$A77)*'Payments Log'!$E$8:$E$207)))) | V77: =IF($A77="","",IF($J77="","Not Delivered",IF($I77="","No Target Date",IF($J77<=$I77,"On Time","Late")))) | W77: =IF($A77="","",IF($X77="","OK","REVIEW")) | X77: =IF($A77="","",TRIM(IF($B77="","Missing vendor ID. ","")&IF($C77="NOT FOUND","Vendor ID not in Vendor Master. ","")&IF(COUNTIFS('Invoice & Delivery Log'!$A$8:$A$157,$A77)>1,"Duplicate invoice ID. ","")&IF(AND($D77<>"",COUNTIFS('Invoice & Delivery Log'!$D$8:$D$157,$D77,'Invoice & Delivery Log'!$B$8:$B$157,$B77)>1),"Duplicate supplier invoice number. ","")&IF($E77="","Missing PO number. ","")&IF($H77="","Missing invoice date. ","")&IF(N($N77)<=0,"Invoice amount must be greater than zero. ","")&IF(AND($H77<>"",$H77>Settings!$C$5),"Invoice date is in the future. ","")&IF(AND($K77="Received in Full",$J77=""),"Missing actual delivery date. ","")&IF(ROUND(N($O77)-N($N77),2)>0,"Payments exceed the invoice amount. ","")&IF(AND($K77="Rejected",N($O77)>0),"Payment made on a rejected delivery. ","")&IF(AND($B77<>"",IFERROR(INDEX('Vendor Master'!$H$8:$H$47,MATCH($B77,'Vendor Master'!$A$8:$A$47,0)),"")="Inactive",ROUND(N($P77),2)>0),"Open balance with an inactive vendor. ",""))) | Y77: =IF($A77="","",IF(ROUND($P77,2)>0.004,"Yes","No")) | Z77: =IF(OR($Y77<>"Yes",$M77=""),"",COUNTIFS('Invoice & Delivery Log'!$Y$8:$Y$157,"Yes",'Invoice & Delivery Log'!$M$8:$M$157,"<"&$M77)+COUNTIFS('Invoice & Delivery Log'!$Y$8:$Y$157,"Yes",'Invoice & Delivery Log'!$M$8:$M$157,$M77,'Invoice & Delivery Log'!$A$8:$A$157,"<"&$A77)+1)
C78: =IF($B78="","",IFERROR(INDEX('Vendor Master'!$B$8:$B$47,MATCH($B78,'Vendor Master'!$A$8:$A$47,0)),"NOT FOUND")) | F78: =IF($B78="","",IFERROR(INDEX('Vendor Master'!$C$8:$C$47,MATCH($B78,'Vendor Master'!$A$8:$A$47,0)),"")) | L78: =IF($B78="","",IFERROR(INDEX('Vendor Master'!$G$8:$G$47,MATCH($B78,'Vendor Master'!$A$8:$A$47,0)),"")) | M78: =IF(OR($H78="",$L78=""),"",$H78+$L78) | O78: =IF($A78="","",SUMIFS('Payments Log'!$F$8:$F$207,'Payments Log'!$B$8:$B$207,$A78)) | P78: =IF($A78="","",ROUND($N78-$O78,2)) | Q78: =IF($A78="","",IF(N($N78)<=0,"Check Amount",IF(ROUND($O78,2)<=0,"Unpaid",IF(ROUND($O78-$N78,2)>0,"Overpaid",IF(ROUND($P78,2)<=0,"Paid","Partially Paid"))))) | R78: =IF(OR($A78="",$M78=""),"",IF(ROUND($P78,2)<=0,0,MAX(0,Settings!$C$5-$M78-Settings!$C$7))) | S78: =IF($A78="","",IF(N($R78)>0,MAX($P78,0),0)) | T78: =IF($A78="","",IF(ROUND($P78,2)<0,"Supplier Credit",IF(ROUND($P78,2)=0,"Closed",IF($M78="","No Due Date",IF(N($R78)<=0,"Not Due Yet",IF(N($R78)<=Settings!$C$8,"1-30 Days Overdue",IF(N($R78)<=Settings!$C$9,"31-60 Days Overdue",IF(N($R78)<=Settings!$C$10,"61-90 Days Overdue","90+ Days Overdue")))))))) | U78: =IF($A78="","",IF(COUNTIFS('Payments Log'!$B$8:$B$207,$A78)=0,"",SUMPRODUCT(MAX(('Payments Log'!$B$8:$B$207=$A78)*'Payments Log'!$E$8:$E$207)))) | V78: =IF($A78="","",IF($J78="","Not Delivered",IF($I78="","No Target Date",IF($J78<=$I78,"On Time","Late")))) | W78: =IF($A78="","",IF($X78="","OK","REVIEW")) | X78: =IF($A78="","",TRIM(IF($B78="","Missing vendor ID. ","")&IF($C78="NOT FOUND","Vendor ID not in Vendor Master. ","")&IF(COUNTIFS('Invoice & Delivery Log'!$A$8:$A$157,$A78)>1,"Duplicate invoice ID. ","")&IF(AND($D78<>"",COUNTIFS('Invoice & Delivery Log'!$D$8:$D$157,$D78,'Invoice & Delivery Log'!$B$8:$B$157,$B78)>1),"Duplicate supplier invoice number. ","")&IF($E78="","Missing PO number. ","")&IF($H78="","Missing invoice date. ","")&IF(N($N78)<=0,"Invoice amount must be greater than zero. ","")&IF(AND($H78<>"",$H78>Settings!$C$5),"Invoice date is in the future. ","")&IF(AND($K78="Received in Full",$J78=""),"Missing actual delivery date. ","")&IF(ROUND(N($O78)-N($N78),2)>0,"Payments exceed the invoice amount. ","")&IF(AND($K78="Rejected",N($O78)>0),"Payment made on a rejected delivery. ","")&IF(AND($B78<>"",IFERROR(INDEX('Vendor Master'!$H$8:$H$47,MATCH($B78,'Vendor Master'!$A$8:$A$47,0)),"")="Inactive",ROUND(N($P78),2)>0),"Open balance with an inactive vendor. ",""))) | Y78: =IF($A78="","",IF(ROUND($P78,2)>0.004,"Yes","No")) | Z78: =IF(OR($Y78<>"Yes",$M78=""),"",COUNTIFS('Invoice & Delivery Log'!$Y$8:$Y$157,"Yes",'Invoice & Delivery Log'!$M$8:$M$157,"<"&$M78)+COUNTIFS('Invoice & Delivery Log'!$Y$8:$Y$157,"Yes",'Invoice & Delivery Log'!$M$8:$M$157,$M78,'Invoice & Delivery Log'!$A$8:$A$157,"<"&$A78)+1)
C79: =IF($B79="","",IFERROR(INDEX('Vendor Master'!$B$8:$B$47,MATCH($B79,'Vendor Master'!$A$8:$A$47,0)),"NOT FOUND")) | F79: =IF($B79="","",IFERROR(INDEX('Vendor Master'!$C$8:$C$47,MATCH($B79,'Vendor Master'!$A$8:$A$47,0)),"")) | L79: =IF($B79="","",IFERROR(INDEX('Vendor Master'!$G$8:$G$47,MATCH($B79,'Vendor Master'!$A$8:$A$47,0)),"")) | M79: =IF(OR($H79="",$L79=""),"",$H79+$L79) | O79: =IF($A79="","",SUMIFS('Payments Log'!$F$8:$F$207,'Payments Log'!$B$8:$B$207,$A79)) | P79: =IF($A79="","",ROUND($N79-$O79,2)) | Q79: =IF($A79="","",IF(N($N79)<=0,"Check Amount",IF(ROUND($O79,2)<=0,"Unpaid",IF(ROUND($O79-$N79,2)>0,"Overpaid",IF(ROUND($P79,2)<=0,"Paid","Partially Paid"))))) | R79: =IF(OR($A79="",$M79=""),"",IF(ROUND($P79,2)<=0,0,MAX(0,Settings!$C$5-$M79-Settings!$C$7))) | S79: =IF($A79="","",IF(N($R79)>0,MAX($P79,0),0)) | T79: =IF($A79="","",IF(ROUND($P79,2)<0,"Supplier Credit",IF(ROUND($P79,2)=0,"Closed",IF($M79="","No Due Date",IF(N($R79)<=0,"Not Due Yet",IF(N($R79)<=Settings!$C$8,"1-30 Days Overdue",IF(N($R79)<=Settings!$C$9,"31-60 Days Overdue",IF(N($R79)<=Settings!$C$10,"61-90 Days Overdue","90+ Days Overdue")))))))) | U79: =IF($A79="","",IF(COUNTIFS('Payments Log'!$B$8:$B$207,$A79)=0,"",SUMPRODUCT(MAX(('Payments Log'!$B$8:$B$207=$A79)*'Payments Log'!$E$8:$E$207)))) | V79: =IF($A79="","",IF($J79="","Not Delivered",IF($I79="","No Target Date",IF($J79<=$I79,"On Time","Late")))) | W79: =IF($A79="","",IF($X79="","OK","REVIEW")) | X79: =IF($A79="","",TRIM(IF($B79="","Missing vendor ID. ","")&IF($C79="NOT FOUND","Vendor ID not in Vendor Master. ","")&IF(COUNTIFS('Invoice & Delivery Log'!$A$8:$A$157,$A79)>1,"Duplicate invoice ID. ","")&IF(AND($D79<>"",COUNTIFS('Invoice & Delivery Log'!$D$8:$D$157,$D79,'Invoice & Delivery Log'!$B$8:$B$157,$B79)>1),"Duplicate supplier invoice number. ","")&IF($E79="","Missing PO number. ","")&IF($H79="","Missing invoice date. ","")&IF(N($N79)<=0,"Invoice amount must be greater than zero. ","")&IF(AND($H79<>"",$H79>Settings!$C$5),"Invoice date is in the future. ","")&IF(AND($K79="Received in Full",$J79=""),"Missing actual delivery date. ","")&IF(ROUND(N($O79)-N($N79),2)>0,"Payments exceed the invoice amount. ","")&IF(AND($K79="Rejected",N($O79)>0),"Payment made on a rejected delivery. ","")&IF(AND($B79<>"",IFERROR(INDEX('Vendor Master'!$H$8:$H$47,MATCH($B79,'Vendor Master'!$A$8:$A$47,0)),"")="Inactive",ROUND(N($P79),2)>0),"Open balance with an inactive vendor. ",""))) | Y79: =IF($A79="","",IF(ROUND($P79,2)>0.004,"Yes","No")) | Z79: =IF(OR($Y79<>"Yes",$M79=""),"",COUNTIFS('Invoice & Delivery Log'!$Y$8:$Y$157,"Yes",'Invoice & Delivery Log'!$M$8:$M$157,"<"&$M79)+COUNTIFS('Invoice & Delivery Log'!$Y$8:$Y$157,"Yes",'Invoice & Delivery Log'!$M$8:$M$157,$M79,'Invoice & Delivery Log'!$A$8:$A$157,"<"&$A79)+1)
